Workbook
Name UPDATE: 'Data Sheet'!$E$1

Sheet Model Checks
A1: INFOSYS LTD - Model Checks & Audit Dashboard
A2: Green = pass; red = review. Checks are formula-driven and intended to catch linkage, assumption and valuation-consistency issues.
A4: Core Checks
A5: Check | B5: Result | C5: Status | D5: Comment
A6: Historical balance sheet balances | B6: =AND(HistoricalFS!C66:L66) -> TRUE | C6: =IF(B6,"PASS","REVIEW") -> PASS | D6: HistoricalFS check should be TRUE in every year
A7: Terminal growth below WACC | B7: ='Operating Drivers'!B47="PASS" -> TRUE | C7: =IF(B7,"PASS","REVIEW") -> PASS | D7: Terminal g must remain below WACC
A8: Terminal reinvestment formula | B8: =ABS('Operating Drivers'!B46-'Operating Drivers'!B44/'Operating Drivers'!B45)<0.000001 -> TRUE | C8: =IF(B8,"PASS","REVIEW") -> PASS | D8: Terminal reinvestment = g / terminal ROIC
A9: FY27 reinvestment formula | B9: =ABS('Operating Drivers'!B37-'Operating Drivers'!B34/'Operating Drivers'!B36)<0.000001 -> TRUE | C9: =IF(B9,"PASS","REVIEW") -> PASS | D9: Explicit reinvestment = growth / target ROIC
A10: DCF tax linked to normalized effective tax | B10: =ABS('DCF>'!F10-'Operating Drivers'!B38)<0.000001 -> TRUE | C10: =IF(B10,"PASS","REVIEW") -> PASS | D10: DCF FCFF tax should use the normalized 29.5% effective tax assumption.
A11: WACC tax shield rate separately defined | B11: =ABS(WACC!E28-'Operating Drivers'!B48)<0.000001 -> TRUE | C11: =IF(B11,"PASS","REVIEW") -> PASS | D11: WACC debt tax shield uses the separately defined marginal/statutory tax rate.
A12: DCF terminal discount uses 4.5 years | B12: =ABS(('DCF>'!D40/('DCF>'!D34))-1/(1+'DCF>'!F26)^4.5)<0.000001 -> TRUE | C12: =IF(B12,"PASS","REVIEW") -> PASS | D12: Mid-year explicit forecast ends at 4.5 years
A13: DCF base agrees with scenario base | B13: =ABS('DCF>'!D48-Scenarios!K4)<1 -> TRUE | C13: =IF(B13,"PASS","REVIEW") -> PASS | D13: Base scenario should reconcile to main DCF within ₹1/share
A14: Terminal value multiple check | B14: =ISNUMBER('DCF>'!D65) -> TRUE | C14: =IF(B14,"PASS","REVIEW") -> PASS | D14: Terminal-value implied EV/EBITDA is a diagnostic only; compare with the core-peer median and do not treat it as an exit-multiple input.
A15: No terminal growth error | B15: =Forecasting!R18="PASS" -> TRUE | C15: =IF(B15,"PASS","REVIEW") -> PASS | D15: Forecasting terminal-growth check should pass
A16: Forecast tax rate consistent across FY27-FY31 | B16: =AND('Operating Drivers'!B38='Operating Drivers'!C38,'Operating Drivers'!C38='Operating Drivers'!D38,'Operating Drivers'!D38='Operating Drivers'!E38,'Operating Drivers'!E38='Operating Drivers'!F38) -> TRUE | C16: =IF(B16,"PASS","REVIEW") -> PASS | D16: All explicit DCF forecast years use the normalized effective tax rate.
A17: Segment-weighted growth ties to top-down total (internal tie, not a guidance check) | B17: =ABS('Operating Drivers'!B29-'Operating Drivers'!B34)<0.001 -> TRUE | C17: =IF(B17,"PASS","REVIEW") -> PASS | D17: Internal segment-to-total tie: FY27 weighted segment growth is definitionally close to the top-down base growth because both derive from the same segment total. It does NOT test against company CC guidance (see Operating Drivers!D29 for that comparison, 2.458% model vs 2.25% guidance midpoint, ~21bps gap, shown for context but not wired into this dashboard).
A18: Segment FY27-FY31 links reconcile | B18: =SUMPRODUCT(ABS('Segment Profitability'!C3:C10-'Segment Forecast'!D3:D10))+SUMPRODUCT(ABS('Segment Profitability'!D3:D10-'Segment Forecast'!E3:E10))+SUMPRODUCT(ABS('Segment Profitability'!E3:E10-'Segment Forecast'!F3:F10))+SUMPRODUCT(ABS('Segment Profitability'!F3:F10-'Segment Forecast'!G3:G10))+SUMPRODUCT(ABS('Segment Profitability'!G3:G10-'Segment Forecast'!H3:H10))<0.01 -> TRUE | C18: =IF(B18,"PASS","REVIEW") -> PASS | D18: All forecast segment years must link to the matching year.
A19: All Other segment is linked | B19: =SUMPRODUCT(ABS('Segment Profitability'!C10:G10-'Segment Forecast'!D10:H10))<0.01 -> TRUE | C19: =IF(B19,"PASS","REVIEW") -> PASS | D19: All Other should not have a separate hardcoded growth engine.
A20: Weighted FY27 growth uses FY26 weights | B20: =ABS('Operating Drivers'!B29-SUMPRODUCT('Operating Drivers'!C21:C28,'Operating Drivers'!E21:E28)/SUM('Operating Drivers'!C21:C28))<0.000001 -> TRUE | C20: =IF(B20,"PASS","REVIEW") -> PASS | D20: Cross-check uses FY26 segment revenue weights.
A21: Corporate cost bridge anchored to FY26 normalization | B21: =ABS('Operating Drivers'!B41-('Segment Profitability'!B32-'Normalization Bridge'!B5)/'Segment Profitability'!B31)<0.000001 -> TRUE | C21: =IF(B21,"PASS","REVIEW") -> PASS | D21: FY26 normalized corporate/unallocated costs are explicit.
A22: Integrated EBIT bridge | B22: =SUMPRODUCT(ABS('Integrated Operating Model'!C8:G8-('Integrated Operating Model'!C5:G5-'Integrated Operating Model'!C7:G7)))<0.01 -> TRUE | C22: =IF(B22,"PASS","REVIEW") -> PASS | D22: Consolidated EBIT = segment operating income - corporate/unallocated costs.
A23: Integrated DCF terminal assumptions linked | B23: =AND('DCF Integration'!B8='Operating Drivers'!B44,'DCF Integration'!G8='Operating Drivers'!B44,'DCF Integration'!B9='Operating Drivers'!B45) -> TRUE | C23: =IF(B23,"PASS","REVIEW") -> PASS | D23: Integrated DCF terminal inputs have one source of truth.
A24: Integrated equity bridge | B24: =ABS('DCF Integration'!G19-('DCF Integration'!G15-'DCF Integration'!G18))<0.01 -> TRUE | C24: =IF(B24,"PASS","REVIEW") -> PASS | D24: Equity value = enterprise value - net debt.
A25: Integrated per-share bridge | B25: =ABS('DCF Integration'!G21-'DCF Integration'!G19/'DCF Integration'!G20)<0.01 -> TRUE | C25: =IF(B25,"PASS","REVIEW") -> PASS | D25: Intrinsic value/share recomputes from equity value and shares.
A26: Core peer median populated | B26: =AND(ISNUMBER('Comps Val'!O28),ISNUMBER('Comps Val'!P28),ISNUMBER('Comps Val'!Q28)) -> TRUE | C26: =IF(B26,"PASS","REVIEW") -> PASS | D26: Core peer set is separately identified from extended peers.
A27: Beta data freshness flagged | B27: =MAX('Beta - Regression'!B10:B114)>=DATE(2026,8,1) -> TRUE | C27: =IF(B27,"PASS","REVIEW") -> PASS | D27: Beta window runs through the last available weekly close before the 22-Aug-2026 valuation date; weekly series refreshed through the week of 18-Aug-2026 (last observation 16-Aug-2026).
A28: Key Outputs
A29: WACC | B29: =WACC!L45 -> 0.11593086
A30: DCF Value / Share | B30: ='DCF>'!D48 -> 796.21701
A31: Current Price | B31: ='DCF>'!D50 -> 1121
A32: Terminal Growth | B32: ='Operating Drivers'!B44 -> 0.03
A33: Terminal ROIC | B33: ='Operating Drivers'!B45 -> 0.4
A34: Terminal Reinvestment | B34: ='Operating Drivers'!B46 -> 0.075
A35: Scenario Range | B35: =TEXT(Scenarios!K3,"₹#,##0")&" to "&TEXT(Scenarios!K5,"₹#,##0") -> ₹715 to ₹910

Sheet Valuation Summary
A1: Infosys Equity Research — Valuation Summary
A2: Metric | B2: Output / Methodology
A3: Legacy DCF Value / Share | B3: ='DCF>'!D48 -> 796.21701
A4: Integrated DCF Value / Share | B4: ='DCF Integration'!G21 -> 796.21701
A5: DCF Center | B5: =AVERAGE(B3:B4) -> 796.21701
A6: Core EV / Revenue Value / Share | B6: ='Comps Val'!O37 -> 1202.9478
A7: Core EV / EBITDA Value / Share | B7: ='Comps Val'!P37 -> 1398.6938
A8: Core P / E Value / Share | B8: ='Comps Val'!Q37 -> 1515.0278
A9: Primary Comps Cross-Check | B9: =B7 -> 1398.6938
A10: DCF Weight | B10: 0.6
A11: Comps Weight | B11: 0.4
A12: Indicative Target Price | B12: =B5*B10+B9*B11 -> 1037.2077
A13: Current Share Price | B13: ='DCF>'!D50 -> 1121
A14: Upside / (Downside) | B14: =B12/B13-1 -> -0.074747796
A15: Core Peer Set | B15: TCS, HCL Technologies, Wipro, Tech Mahindra, LTIMindtree
A16: Extended Peer Context | B16: Persistent Systems, Coforge, Mphasis, Hexaware
A17: Target methodology | B17: 60% DCF center / 40% core-peer EV/EBITDA. DCF is primary; comps are a market-based cross-check.
A18: Important limitation | B18: Beta: the 2-year weekly regression window is refreshed through the week of 18 Aug 2026 (last observation 16 Aug 2026, the last trading week before the valuation date); the beta-freshness model check passes.

Sheet Investment Thesis
A1: Infosys Equity Research — Investment Thesis
A2: Section | B2: Current conclusion
A3: Valuation | B3: DCF remains below the current market valuation, while trading comps imply materially higher values. The dispersion is a research question, not something to engineer away.
A4: Business outlook | B4: FY26 revenue was ₹178,650 crore; Q1 FY27 revenue was ₹48,211 crore and Q1 FY27 operating margin was 21.1%.
A5: Guidance | B5: FY27 constant-currency revenue growth guidance is 1.5%-3.0%.
A6: Catalyst 1 | B6: AI monetization and conversion of AI-led demand into higher-value services.
A7: Catalyst 2 | B7: Large-deal conversion and sustained transformation/cloud/data spending.
A8: Catalyst 3 | B8: Productivity and utilization improvements supporting margins.
A9: Risk 1 | B9: AI pricing pressure or automation may outpace new AI revenue.
A10: Risk 2 | B10: Weak discretionary IT spending and macro uncertainty.
A11: Risk 3 | B11: Communications and Hi-Tech remain more exposed to sector-specific pressure.
A12: Key valuation drivers | B12: Revenue growth, EBIT margin, WACC, terminal growth and terminal ROIC.
A13: What would change the view | B13: A sustained change in growth, margins, deal conversion or AI monetization would materially change intrinsic value.
A14: Methodology | B14: DCF uses FCFF; integrated DCF is bottom-up from segment operating income less normalized corporate/unallocated costs; terminal reinvestment = terminal growth / terminal ROIC; core trading comps provide the primary market cross-check.
A15: Legacy DCF Value / Share | B15: ='DCF>'!D48 -> 796.21701
A16: Integrated DCF Value / Share | B16: ='DCF Integration'!G21 -> 796.21701
A17: DCF Center | B17: ='Valuation Summary'!B5 -> 796.21701
A18: Core EV/EBITDA Cross-Check | B18: ='Valuation Summary'!B9 -> 1398.6938
A19: Indicative Target Price | B19: ='Valuation Summary'!B12 -> 1037.2077
A20: Current Share Price | B20: ='Valuation Summary'!B13 -> 1121
A21: Upside / (Downside) | B21: ='Valuation Summary'!B14 -> -0.074747796
A22: Indicative View | B22: HOLD / NEUTRAL — low conviction; DCF is below market while core-peer multiples provide a higher valuation cross-check.
A23: Target Price Method | B23: 60% DCF center + 40% core-peer EV/EBITDA. Core peers are used as the primary market cross-check; extended peers remain contextual.

Sheet Legacy vs Integrated
A1: Legacy DCF vs Integrated DCF
A2: Metric | B2: Legacy DCF | C2: Integrated DCF | D2: Difference | E2: Audit interpretation | F2: Status
A3: WACC | B3: ='DCF>'!D31 -> 0.11593086 | C3: ='DCF Integration'!G5 -> 0.11593086 | D3: =C3-B3 -> 0 | E3: Compare after recalculation. Any remaining gap should be attributable to the top-down vs. bottom-up forecast methodology, not broken year links. | F3: =IF(ABS(D3)<0.0005,"CONSISTENT","REVIEW: WACC inputs diverge") -> CONSISTENT
A4: Terminal Growth | B4: ='DCF>'!F25 -> 0.03 | C4: ='DCF Integration'!G8 -> 0.03 | D4: =C4-B4 -> 0 | E4: Compare after recalculation. Any remaining gap should be attributable to the top-down vs. bottom-up forecast methodology, not broken year links. | F4: =IF(ABS(D4)<0.0005,"CONSISTENT","REVIEW: terminal growth inputs diverge") -> CONSISTENT
A5: Terminal Value | B5: ='DCF>'!D34 -> 339178.39 | C5: ='DCF Integration'!G13 -> 339178.39 | D5: =C5-B5 -> 0 | E5: Compare after recalculation. Any remaining gap should be attributable to the top-down vs. bottom-up forecast methodology, not broken year links. | F5: =IF(ABS(D5/B5)<0.05,"CONSISTENT (within 5%)","REVIEW: methodology gap >5% - see interpretation") -> CONSISTENT (within 5%)
A6: Enterprise Value | B6: ='DCF>'!D41 -> 310087.82 | C6: ='DCF Integration'!G15 -> 310087.82 | D6: =C6-B6 -> 0 | E6: Compare after recalculation. Any remaining gap should be attributable to the top-down vs. bottom-up forecast methodology, not broken year links. | F6: =IF(ABS(D6/B6)<0.05,"CONSISTENT (within 5%)","REVIEW: methodology gap >5% - see interpretation") -> CONSISTENT (within 5%)
A7: Equity Value | B7: ='DCF>'!D45 -> 323112.82 | C7: ='DCF Integration'!G19 -> 323112.82 | D7: =C7-B7 -> 0 | E7: Compare after recalculation. Any remaining gap should be attributable to the top-down vs. bottom-up forecast methodology, not broken year links. | F7: =IF(ABS(D7/B7)<0.05,"CONSISTENT (within 5%)","REVIEW: methodology gap >5% - see interpretation") -> CONSISTENT (within 5%)
A8: Intrinsic Value / Share | B8: ='DCF>'!D48 -> 796.21701 | C8: ='DCF Integration'!G21 -> 796.21701 | D8: =C8-B8 -> 0 | E8: Compare after recalculation. Any remaining gap should be attributable to the top-down vs. bottom-up forecast methodology, not broken year links. | F8: =IF(ABS(D8/B8)<0.05,"CONSISTENT (within 5%)","REVIEW: methodology gap >5% - see interpretation") -> CONSISTENT (within 5%)
A9: Current Share Price | B9: ='DCF>'!D50 -> 1121 | C9: ='DCF Integration'!G23 -> 1121 | D9: =C9-B9 -> 0 | E9: Compare after recalculation. Any remaining gap should be attributable to the top-down vs. bottom-up forecast methodology, not broken year links. | F9: =IF(ABS(D9)<0.01,"CONSISTENT","REVIEW: share price inputs diverge") -> CONSISTENT
A11: Forecast Comparison
A12: Metric | B12: Legacy Forecast | C12: Integrated Forecast | D12: Difference | E12: Interpretation | F12: Status
A13: Metric | B13: FY27E | C13: FY28E | D13: FY29E | E13: FY30E | F13: FY31E
A14: Legacy Revenue (Rs Cr) | B14: =Forecasting!R5 -> 183041.22 | C14: =Forecasting!S5 -> 187795.96 | D14: =Forecasting!T5 -> 192927.49 | E14: =Forecasting!U5 -> 198458.63 | F14: =Forecasting!V5 -> 204412.39
A15: Integrated (Segment) Revenue (Rs Cr) | B15: ='Segment Profitability'!C31 -> 183041.22 | C15: ='Segment Profitability'!D31 -> 187795.96 | D15: ='Segment Profitability'!E31 -> 192927.49 | E15: ='Segment Profitability'!F31 -> 198458.63 | F15: ='Segment Profitability'!G31 -> 204412.39
A16: Revenue Difference (%) | B16: =B15/B14-1 -> 0 | C16: =C15/C14-1 -> 0 | D16: =D15/D14-1 -> 0 | E16: =E15/E14-1 -> 0 | F16: =F15/F14-1 -> 0
A18: Legacy EBIT (Rs Cr) | B18: =Forecasting!R7 -> 38384.84 | C18: =Forecasting!S7 -> 39524.433 | D18: =Forecasting!T7 -> 40801.562 | E18: =Forecasting!U7 -> 42094.066 | F18: =Forecasting!V7 -> 43391.96
A19: Integrated (Segment) Operating Income (Rs Cr) | B19: ='Segment Profitability'!C32 -> 43407.331 | C19: ='Segment Profitability'!D32 -> 44677.39 | D19: ='Segment Profitability'!E32 -> 46095.324 | E19: ='Segment Profitability'!F32 -> 47539.598 | F19: ='Segment Profitability'!G32 -> 49000.857
A20: EBIT Difference (%) | B20: =B19/B18-1 -> 0.1308457 | C20: =C19/C18-1 -> 0.13037397 | D20: =D19/D18-1 -> 0.1297441 | E20: =E19/E18-1 -> 0.12936578 | F20: =F19/F18-1 -> 0.12926122
A22: Interpretation: the integrated (bottom-up) DCF uses the FY27-FY31 segment links and an explicit corporate/unallocable cost bridge anchored to FY26 normalized EBIT. Because the top-down (Legacy) build takes its revenue growth and EBIT margin from the same segment engine, and both builds now apply the terminal (1+g) convention consistently, the two builds reconcile to the same value (~Rs 796/share). This is an internal build-integrity check, not two independent valuations. Segment operating margin is not treated as consolidated EBIT until the corporate-cost bridge is applied.

Sheet Audit Summary
A1: Infosys Equity Research Model -- Methodology & Audit Notes
A3: Purpose | B3: Methodology and QA reference for the Infosys Equity Research Model
A4: DCF forecast tax rate | B4: 29.5% normalized effective tax rate (FCFF)
A5: WACC debt tax shield rate | B5: 25.17% marginal/statutory rate (Sec. 115BAA) -- kept distinct from the 29.5% effective rate by design
A6: Terminal growth | B6: 3.0% base case (2.5% bear / 3.5% bull)
A7: Terminal ROIC | B7: 40.0% base case (35% bear / 45% bull) -- normalizes down from FY26 actual ROIC
A8: Terminal reinvestment | B8: Terminal growth / terminal ROIC = 7.5%, formula-linked, not a fixed input
A9: Revenue forecast basis | B9: Segment-driven base-case revenue growth; Integrated DCF is now bottom-up from segment operating income less a normalized corporate/unallocated cost bridge.
A10: EBIT margin normalization | B10: FY26A reported operating margin is 20.3%; FY27E onward consolidated EBIT is derived bottom-up from segment operating income less normalized unallocable/corporate costs. This produces a consolidated margin consistent with the 20%-22% company guidance range.
A11: Scenario design | B11: Bear/Base/Bull operating assumptions (revenue growth, EBIT margin, terminal inputs) flow directly into three separately computed scenario DCFs
A12: Cross-check design | B12: The single FCFF DCF is expressed through a top-down Legacy build and a bottom-up Integrated build. The Integrated build aggregates segment operating income and explicitly reconciles it to consolidated EBIT through normalized corporate/unallocated costs; the two builds are an internal build-integrity check, not independent valuations.
A13: Comps | B13: TCS, HCL Technologies, Wipro, Tech Mahindra, LTIMindtree, plus mid-cap context; independent market cross-check, not used to force the DCF
A14: Beta | B14: Peer-based unlevered beta re-levered to Infosys capital structure; 2-year weekly regression
... A18: Deliverables | B18: Deliverables: Excel model + written investment note + tear sheet. Beta data is refreshed through the week of 18 Aug 2026 (last observation 16 Aug 2026), the last trading week before the 22 Aug 2026 valuation date.

Sheet HistoricalFS
B2: ="Historical Financial Statement - "&'Data Sheet'!B1 -> Historical Financial Statement - INFOSYS LTD
B3: Years | C3: ='Data Sheet'!B16 -> 42825 | D3: ='Data Sheet'!C16 -> 43190 | E3: ='Data Sheet'!D16 -> 43555 | F3: ='Data Sheet'!E16 -> 43921 | G3: ='Data Sheet'!F16 -> 44286 | H3: ='Data Sheet'!G16 -> 44651 | I3: ='Data Sheet'!H16 -> 45016 | J3: ='Data Sheet'!I16 -> 45382 | ... L3: ='Data Sheet'!K16 -> 46112 | M3: LTM
A5: # | B5: Income Statement
B6: Sales | C6: =IFERROR('Data Sheet'!B17,0) -> 68484 | D6: =IFERROR('Data Sheet'!C17,0) -> 70522 | E6: =IFERROR('Data Sheet'!D17,0) -> 82675 | F6: =IFERROR('Data Sheet'!E17,0) -> 90791 | G6: =IFERROR('Data Sheet'!F17,0) -> 100472 | H6: =IFERROR('Data Sheet'!G17,0) -> 121641 | I6: =IFERROR('Data Sheet'!H17,0) -> 146767 | J6: =IFERROR('Data Sheet'!I17,0) -> 153670 | ... L6: =IFERROR('Data Sheet'!K17,0) -> 178650 | M6: =IFERROR(SUM('Data Sheet'!H42:K42),0) -> 184582
B7: Sales Growth | C7: - | D7: =D6/C6-1 -> 0.029758776 | E7: =E6/D6-1 -> 0.1723292 | F7: =F6/E6-1 -> 0.098167523 | G7: =G6/F6-1 -> 0.10662951 | H7: =H6/G6-1 -> 0.21069552 | I7: =I6/H6-1 -> 0.20655864 | J7: =J6/I6-1 -> 0.047033734 | K7: =K6/J6-1 -> 0.060649444 | ... M7: =M6/L6-1 -> 0.03320459
B9: COGS | C9: =IFERROR(SUM('Data Sheet'!B18,'Data Sheet'!B20:B22)-1*'Data Sheet'!B19,0) -> 44609 | D9: =IFERROR(SUM('Data Sheet'!C18,'Data Sheet'!C20:C22)-1*'Data Sheet'!C19,0) -> 46395 | E9: =IFERROR(SUM('Data Sheet'!D18,'Data Sheet'!D20:D22)-1*'Data Sheet'!D19,0) -> 55446 | F9: =IFERROR(SUM('Data Sheet'!E18,'Data Sheet'!E20:E22)-1*'Data Sheet'!E19,0) -> 62210 | G9: =IFERROR(SUM('Data Sheet'!F18,'Data Sheet'!F20:F22)-1*'Data Sheet'!F19,0) -> 68490 | H9: =IFERROR(SUM('Data Sheet'!G18,'Data Sheet'!G20:G22)-1*'Data Sheet'!G19,0) -> 84819 | I9: =IFERROR(SUM('Data Sheet'!H18,'Data Sheet'!H20:H22)-1*'Data Sheet'!H19,0) -> 104880 | J9: =IFERROR(SUM('Data Sheet'!I18,'Data Sheet'!I20:I22)-1*'Data Sheet'!I19,0) -> 110030 | ... L9: =IFERROR(SUM('Data Sheet'!K18,'Data Sheet'!K20:K22)-1*'Data Sheet'!K19,0) -> 128257 | M9: =IFERROR(SUM('Data Sheet'!H43:K43),0) -> 140837
B10: COGS % Sales | C10: =C9/C6 -> 0.65137842 | D10: =D9/D6 -> 0.65787981 | E10: =E9/E6 -> 0.67065014 | F10: =F9/F6 -> 0.68520007 | G10: =G9/G6 -> 0.68168246 | H10: =H9/H6 -> 0.69728957 | I10: =I9/I6 -> 0.71460206 | J10: =J9/J6 -> 0.71601484 | ... M10: =M9/M6 -> 0.76300506
B12: Gross Profit | C12: =C6-C9 -> 23875 | D12: =D6-D9 -> 24127 | E12: =E6-E9 -> 27229 | F12: =F6-F9 -> 28581 | G12: =G6-G9 -> 31982 | H12: =H6-H9 -> 36822 | I12: =I6-I9 -> 41887 | J12: =J6-J9 -> 43640 | ... M12: =M6-M9 -> 43745
B13: Gross Margins | C13: =C12/C6 -> 0.34862158 | D13: =D12/D6 -> 0.34212019 | E13: =E12/E6 -> 0.32934986 | F13: =F12/F6 -> 0.31479993 | G13: =G12/G6 -> 0.31831754 | H13: =H12/H6 -> 0.30271043 | I13: =I12/I6 -> 0.28539794 | J13: =J12/J6 -> 0.28398516 | ... M13: =M12/M6 -> 0.23699494
B15: Selling & General Expenses | C15: =IFERROR(SUM('Data Sheet'!B23:B24),0) -> 5271 | D15: =IFERROR(SUM('Data Sheet'!C23:C24),0) -> 5305 | E15: =IFERROR(SUM('Data Sheet'!D23:D24),0) -> 7059 | F15: =IFERROR(SUM('Data Sheet'!E23:E24),0) -> 6314 | G15: =IFERROR(SUM('Data Sheet'!F23:F24),0) -> 4093 | H15: =IFERROR(SUM('Data Sheet'!G23:G24),0) -> 5331 | I15: =IFERROR(SUM('Data Sheet'!H23:H24),0) -> 6757 | J15: =IFERROR(SUM('Data Sheet'!I23:I24),0) -> 7215 | ... L15: =IFERROR(SUM('Data Sheet'!K23:K24),0) -> 8113
B16: S&G Exp % Sales | C16: =C15/C6 -> 0.076966883 | D16: =D15/D6 -> 0.075224753 | E16: =E15/E6 -> 0.085382522 | F16: =F15/F6 -> 0.069544338 | G16: =G15/G6 -> 0.040737718 | H16: =H15/H6 -> 0.043825684 | I16: =I15/I6 -> 0.04603896 | J16: =J15/J6 -> 0.046951259 | ... L16: =L15/L6 -> 0.045412818
B18: EBITDA | C18: =C12-C15 -> 18604 | D18: =D12-D15 -> 18822 | E18: =E12-E15 -> 20170 | F18: =F12-F15 -> 22267 | G18: =G12-G15 -> 27889 | H18: =H12-H15 -> 31491 | I18: =I12-I15 -> 35130 | J18: =J12-J15 -> 36425 | ... L18: =L12-L15 -> 42280 | M18: =IFERROR(SUM('Data Sheet'!H51:K51),0) -> 46683
B19: EBITDA % Margins | C19: =C18/C6 -> 0.27165469 | D19: =D18/D6 -> 0.26689544 | E19: =E18/E6 -> 0.24396734 | F19: =F18/F6 -> 0.24525559 | G19: =G18/G6 -> 0.27757982 | H19: =H18/H6 -> 0.25888475 | I19: =I18/I6 -> 0.23935898 | J19: =J18/J6 -> 0.2370339 | ... M19: =M18/M6 -> 0.25291198
B21: Interest | C21: =IFERROR('Data Sheet'!B27,0) -> 0 | D21: =IFERROR('Data Sheet'!C27,0) -> 0 | E21: =IFERROR('Data Sheet'!D27,0) -> 0 | F21: =IFERROR('Data Sheet'!E27,0) -> 170 | G21: =IFERROR('Data Sheet'!F27,0) -> 195 | H21: =IFERROR('Data Sheet'!G27,0) -> 200 | I21: =IFERROR('Data Sheet'!H27,0) -> 284 | J21: =IFERROR('Data Sheet'!I27,0) -> 470 | ... L21: =IFERROR('Data Sheet'!K27,0) -> 416 | M21: =IFERROR(SUM('Data Sheet'!H46:K46),0) -> 430
B22: Interest % Sales | C22: =C21/C6 -> 0 | D22: =D21/D6 -> 0 | E22: =E21/E6 -> 0 | F22: =F21/F6 -> 0.0018724323 | G22: =G21/G6 -> 0.0019408392 | H22: =H21/H6 -> 0.0016441825 | I22: =I21/I6 -> 0.0019350399 | J22: =J21/J6 -> 0.003058502 | ... M22: =M21/M6 -> 0.0023295879
B24: Depreciation | C24: =IFERROR('Data Sheet'!B26,0) -> 1703 | D24: =IFERROR('Data Sheet'!C26,0) -> 1863 | E24: =IFERROR('Data Sheet'!D26,0) -> 2011 | F24: =IFERROR('Data Sheet'!E26,0) -> 2893 | G24: =IFERROR('Data Sheet'!F26,0) -> 3267 | H24: =IFERROR('Data Sheet'!G26,0) -> 3476 | I24: =IFERROR('Data Sheet'!H26,0) -> 4225 | J24: =IFERROR('Data Sheet'!I26,0) -> 4678 | ... L24: =IFERROR('Data Sheet'!K26,0) -> 4902 | M24: =IFERROR(SUM('Data Sheet'!H45:K45),0) -> 5007
B25: Depreciations % Sales | C25: =C24/C6 -> 0.024867122 | D25: =D24/D6 -> 0.026417288 | E25: =E24/E6 -> 0.024324161 | F25: =F24/F6 -> 0.031864392 | G25: =G24/G6 -> 0.032516522 | H25: =H24/H6 -> 0.028575891 | I25: =I24/I6 -> 0.028787125 | J25: =J24/J6 -> 0.030441856 | ... M25: =M24/M6 -> 0.027126155
B27: Earnings Before Tax | C27: =IFERROR(C18-SUM(C24,C21),0) -> 16901 | D27: =IFERROR(D18-SUM(D24,D21),0) -> 16959 | E27: =IFERROR(E18-SUM(E24,E21),0) -> 18159 | F27: =IFERROR(F18-SUM(F24,F21),0) -> 19204 | G27: =IFERROR(G18-SUM(G24,G21),0) -> 24427 | H27: =IFERROR(H18-SUM(H24,H21),0) -> 27815 | I27: =IFERROR(I18-SUM(I24,I21),0) -> 30621 | J27: =IFERROR(J18-SUM(J24,J21),0) -> 31277 | ... M27: =IFERROR(M18-SUM(M24,M21),0) -> 41246
B28: EBT % Sales | C28: =C27/C6 -> 0.24678757 | D28: =D27/D6 -> 0.24047815 | E28: =E27/E6 -> 0.21964318 | F28: =F27/F6 -> 0.21151876 | G28: =G27/G6 -> 0.24312246 | H28: =H27/H6 -> 0.22866468 | I28: =I27/I6 -> 0.20863682 | J28: =J27/J6 -> 0.20353355 | ... M28: =M27/M6 -> 0.22345624
B30: Tax | C30: =IFERROR('Data Sheet'!B29,0) -> 5598 | D30: =IFERROR('Data Sheet'!C29,0) -> 4241 | E30: =IFERROR('Data Sheet'!D29,0) -> 5631 | F30: =IFERROR('Data Sheet'!E29,0) -> 5368 | G30: =IFERROR('Data Sheet'!F29,0) -> 7205 | H30: =IFERROR('Data Sheet'!G29,0) -> 7964 | I30: =IFERROR('Data Sheet'!H29,0) -> 9214 | J30: =IFERROR('Data Sheet'!I29,0) -> 9740 | ... L30: =IFERROR('Data Sheet'!K29,0) -> 10521 | M30: =IFERROR(SUM('Data Sheet'!H48:K48),0) -> 10958
B31: Effective Tax Rate | C31: =C30/C27 -> 0.331223 | D31: =D30/D27 -> 0.25007371 | E31: =E30/E27 -> 0.31009417 | F31: =F30/F27 -> 0.2795251 | G31: =G30/G27 -> 0.29496049 | H31: =H30/H27 -> 0.28632033 | I31: =I30/I27 -> 0.30090461 | J31: =J30/J27 -> 0.31141094 | ... M31: =M30/M27 -> 0.26567425
B33: Net Profit | C33: =IFERROR(C27-C30,0) -> 11303 | D33: =IFERROR(D27-D30,0) -> 12718 | E33: =IFERROR(E27-E30,0) -> 12528 | F33: =IFERROR(F27-F30,0) -> 13836 | G33: =IFERROR(G27-G30,0) -> 17222 | H33: =IFERROR(H27-H30,0) -> 19851 | I33: =IFERROR(I27-I30,0) -> 21407 | J33: =IFERROR(J27-J30,0) -> 21537 | ... M33: =IFERROR(M27-M30,0) -> 30288
B34: Net Margins | C34: =C33/C6 -> 0.16504585 | D34: =D33/D6 -> 0.18034089 | E34: =E33/E6 -> 0.15153311 | F34: =F33/F6 -> 0.15239396 | G34: =G33/G6 -> 0.17141094 | H34: =H33/H6 -> 0.16319333 | I34: =I33/I6 -> 0.14585704 | J34: =J33/J6 -> 0.14015097 | ... M34: =M33/M6 -> 0.16408967
B36: No of Equity Shares | C36: =IFERROR('Data Sheet'!B93,0) -> 459.39 | D36: =IFERROR('Data Sheet'!C93,0) -> 436.82 | E36: =IFERROR('Data Sheet'!D93,0) -> 436.89 | F36: =IFERROR('Data Sheet'!E93,0) -> 425.9 | G36: =IFERROR('Data Sheet'!F93,0) -> 426.07 | H36: =IFERROR('Data Sheet'!G93,0) -> 420.67 | I36: =IFERROR('Data Sheet'!H93,0) -> 414.86 | J36: =IFERROR('Data Sheet'!I93,0) -> 415.09 | ... L36: =IFERROR('Data Sheet'!K93,0) -> 405.56 | M36: ='Data Sheet'!B6 -> 405.81
B38: EPS | C38: =IFERROR(C33/C36,0) -> 24.604367 | D38: =IFERROR(D33/D36,0) -> 29.114967 | E38: =IFERROR(E33/E36,0) -> 28.67541 | F38: =IFERROR(F33/F36,0) -> 32.486499 | G38: =IFERROR(G33/G36,0) -> 40.420588 | H38: =IFERROR(H33/H36,0) -> 47.189008 | I38: =IFERROR(I33/I36,0) -> 51.60054 | J38: =IFERROR(J33/J36,0) -> 51.885133 | ... M38: =IFERROR(M33/M36,0) -> 74.635913
B39: EPS Growth % | D39: =IFERROR((D38-C38)/ABS(C38),0) -> 0.18332521 | E39: =IFERROR(E38/D38-1,0) -> -0.015097286 | F39: =IFERROR(F38/E38-1,0) -> 0.13290442 | G39: =IFERROR(G38/F38-1,0) -> 0.24422727 | H39: =IFERROR(H38/G38-1,0) -> 0.16744981 | I39: =IFERROR(I38/H38-1,0) -> 0.093486431 | J39: =IFERROR(J38/I38-1,0) -> 0.0055153183 | K39: =IFERROR(K38/J38-1,0) -> 0.074273236 | L39: =IFERROR(L38/K38-1,0) -> 0.16967463 | M39: =IFERROR(M38/L38-1,0) -> 0.14478806
B41: Dividend Per Share | C41: =IFERROR('Data Sheet'!B31/HistoricalFS!C36,0) -> 12.824833 | D41: =IFERROR('Data Sheet'!C31/HistoricalFS!D36,0) -> 21.669337 | E41: =IFERROR('Data Sheet'!D31/HistoricalFS!E36,0) -> 21.109433 | F41: =IFERROR('Data Sheet'!E31/HistoricalFS!F36,0) -> 17.438366 | G41: =IFERROR('Data Sheet'!F31/HistoricalFS!G36,0) -> 26.91952 | H41: =IFERROR('Data Sheet'!G31/HistoricalFS!H36,0) -> 30.92115 | I41: =IFERROR('Data Sheet'!H31/HistoricalFS!I36,0) -> 33.913127 | J41: =IFERROR('Data Sheet'!I31/HistoricalFS!J36,0) -> 45.901371 | ... M41: =IFERROR('Data Sheet'!L31/HistoricalFS!M36,0) -> 0
B42: Divident payout ratio | C42: =IFERROR(C41/C38,0) -> 0.52124215 | D42: =IFERROR(D41/D38,0) -> 0.74426797 | E42: =IFERROR(E41/E38,0) -> 0.73615102 | F42: =IFERROR(F41/F38,0) -> 0.53678809 | G42: =IFERROR(G41/G38,0) -> 0.66598537 | H42: =IFERROR(H41/H38,0) -> 0.6552617 | I42: =IFERROR(I41/I38,0) -> 0.65722427 | J42: =IFERROR(J41/J38,0) -> 0.88467289 | ... M42: =IFERROR(M41/M38,0) -> 0
B44: Retention Ratio | C44: =IFERROR(IF(C38>C41,1-C42,0),0) -> 0.47875785 | D44: =IFERROR(IF(D38>D41,1-D42,0),0) -> 0.25573203 | E44: =IFERROR(IF(E38>E41,1-E42,0),0) -> 0.26384898 | F44: =IFERROR(IF(F38>F41,1-F42,0),0) -> 0.46321191 | G44: =IFERROR(IF(G38>G41,1-G42,0),0) -> 0.33401463 | H44: =IFERROR(IF(H38>H41,1-H42,0),0) -> 0.3447383 | I44: =IFERROR(IF(I38>I41,1-I42,0),0) -> 0.34277573 | J44: =IFERROR(IF(J38>J41,1-J42,0),0) -> 0.11532711 | ... M44: =IFERROR(IF(M38>M41,1-M42,0),0) -> 1
A46: # | B46: Balance Sheet
B47: Equity Share Capital | C47: =IFERROR('Data Sheet'!B57,0) -> 1144 | D47: =IFERROR('Data Sheet'!C57,0) -> 1088 | E47: =IFERROR('Data Sheet'!D57,0) -> 2170 | F47: =IFERROR('Data Sheet'!E57,0) -> 2122 | G47: =IFERROR('Data Sheet'!F57,0) -> 2124 | H47: =IFERROR('Data Sheet'!G57,0) -> 2098 | I47: =IFERROR('Data Sheet'!H57,0) -> 2069 | J47: =IFERROR('Data Sheet'!I57,0) -> 2071 | ... L47: =IFERROR('Data Sheet'!K57,0) -> 2024
B48: Reserves | C48: =IFERROR('Data Sheet'!B58,0) -> 67838 | D48: =IFERROR('Data Sheet'!C58,0) -> 63835 | E48: =IFERROR('Data Sheet'!D58,0) -> 62778 | F48: =IFERROR('Data Sheet'!E58,0) -> 63328 | G48: =IFERROR('Data Sheet'!F58,0) -> 74227 | H48: =IFERROR('Data Sheet'!G58,0) -> 73252 | I48: =IFERROR('Data Sheet'!H58,0) -> 73338 | J48: =IFERROR('Data Sheet'!I58,0) -> 86045 | ... L48: =IFERROR('Data Sheet'!K58,0) -> 90828
B49: Borrowings | C49: =IFERROR('Data Sheet'!B59,0) -> 0 | D49: =IFERROR('Data Sheet'!C59,0) -> 0 | E49: =IFERROR('Data Sheet'!D59,0) -> 0 | F49: =IFERROR('Data Sheet'!E59,0) -> 4633 | G49: =IFERROR('Data Sheet'!F59,0) -> 5325 | H49: =IFERROR('Data Sheet'!G59,0) -> 5474 | I49: =IFERROR('Data Sheet'!H59,0) -> 8299 | J49: =IFERROR('Data Sheet'!I59,0) -> 8359 | ... L49: =IFERROR('Data Sheet'!K59,0) -> 9176
B50: Other Liabilities | C50: =IFERROR('Data Sheet'!B60,0) -> 14166 | D50: =IFERROR('Data Sheet'!C60,0) -> 14426 | E50: =IFERROR('Data Sheet'!D60,0) -> 19118 | F50: =IFERROR('Data Sheet'!E60,0) -> 21717 | G50: =IFERROR('Data Sheet'!F60,0) -> 25835 | H50: =IFERROR('Data Sheet'!G60,0) -> 35905 | I50: =IFERROR('Data Sheet'!H60,0) -> 40890 | J50: =IFERROR('Data Sheet'!I60,0) -> 39545 | ... L50: =IFERROR('Data Sheet'!K60,0) -> 52260
B51: Total Liabilities | C51: =IFERROR('Data Sheet'!B61,0) -> 83148 | D51: =IFERROR('Data Sheet'!C61,0) -> 79349 | E51: =IFERROR('Data Sheet'!D61,0) -> 84066 | F51: =IFERROR('Data Sheet'!E61,0) -> 91800 | G51: =IFERROR('Data Sheet'!F61,0) -> 107511 | H51: =IFERROR('Data Sheet'!G61,0) -> 116729 | I51: =IFERROR('Data Sheet'!H61,0) -> 124596 | J51: =IFERROR('Data Sheet'!I61,0) -> 136020 | ... L51: =IFERROR('Data Sheet'!K61,0) -> 154288
B53: Fixed Assets Net Block | C53: =IFERROR('Data Sheet'!B62,0) -> 14179 | D53: =IFERROR('Data Sheet'!C62,0) -> 12574 | E53: =IFERROR('Data Sheet'!D62,0) -> 15710 | F53: =IFERROR('Data Sheet'!E62,0) -> 23789 | G53: =IFERROR('Data Sheet'!F62,0) -> 25505 | H53: =IFERROR('Data Sheet'!G62,0) -> 25800 | I53: =IFERROR('Data Sheet'!H62,0) -> 29225 | J53: =IFERROR('Data Sheet'!I62,0) -> 27622 | ... L53: =IFERROR('Data Sheet'!K62,0) -> 33770
B54: Capital Work in Progress | C54: =IFERROR('Data Sheet'!B63,0) -> 1365 | D54: =IFERROR('Data Sheet'!C63,0) -> 1606 | E54: =IFERROR('Data Sheet'!D63,0) -> 1388 | F54: =IFERROR('Data Sheet'!E63,0) -> 954 | G54: =IFERROR('Data Sheet'!F63,0) -> 922 | H54: =IFERROR('Data Sheet'!G63,0) -> 416 | I54: =IFERROR('Data Sheet'!H63,0) -> 288 | J54: =IFERROR('Data Sheet'!I63,0) -> 293 | ... L54: =IFERROR('Data Sheet'!K63,0) -> 526
B55: Investments | C55: =IFERROR('Data Sheet'!B64,0) -> 16423 | D55: =IFERROR('Data Sheet'!C64,0) -> 12163 | E55: =IFERROR('Data Sheet'!D64,0) -> 11261 | F55: =IFERROR('Data Sheet'!E64,0) -> 8792 | G55: =IFERROR('Data Sheet'!F64,0) -> 14205 | H55: =IFERROR('Data Sheet'!G64,0) -> 20324 | I55: =IFERROR('Data Sheet'!H64,0) -> 19478 | J55: =IFERROR('Data Sheet'!I64,0) -> 24623 | ... L55: =IFERROR('Data Sheet'!K64,0) -> 21880
B56: Other Assets | C56: =IFERROR('Data Sheet'!B65-SUM('Data Sheet'!B67:B69),0) -> 16234 | D56: =IFERROR('Data Sheet'!C65-SUM('Data Sheet'!C67:C69),0) -> 20046 | E56: =IFERROR('Data Sheet'!D65-SUM('Data Sheet'!D67:D69),0) -> 21312 | F56: =IFERROR('Data Sheet'!E65-SUM('Data Sheet'!E67:E69),0) -> 21129 | G56: =IFERROR('Data Sheet'!F65-SUM('Data Sheet'!F67:F69),0) -> 22871 | H56: =IFERROR('Data Sheet'!G65-SUM('Data Sheet'!G67:G69),0) -> 30019 | I56: =IFERROR('Data Sheet'!H65-SUM('Data Sheet'!H67:H69),0) -> 38008 | J56: =IFERROR('Data Sheet'!I65-SUM('Data Sheet'!I67:I69),0) -> 38503 | ... L56: =IFERROR('Data Sheet'!K65-SUM('Data Sheet'!K67:K69),0) -> 40677
B57: Total Non Current Assets | C57: =SUM(C53:C56) -> 48201 | D57: =SUM(D53:D56) -> 46389 | E57: =SUM(E53:E56) -> 49671 | F57: =SUM(F53:F56) -> 54664 | G57: =SUM(G53:G56) -> 63503 | H57: =SUM(H53:H56) -> 76559 | I57: =SUM(I53:I56) -> 86999 | J57: =SUM(J53:J56) -> 91041 | ... L57: =SUM(L53:L56) -> 96853
B59: Receivables | C59: =IFERROR('Data Sheet'!B67,0) -> 12322 | D59: =IFERROR('Data Sheet'!C67,0) -> 13142 | E59: =IFERROR('Data Sheet'!D67,0) -> 14827 | F59: =IFERROR('Data Sheet'!E67,0) -> 18487 | G59: =IFERROR('Data Sheet'!F67,0) -> 19294 | H59: =IFERROR('Data Sheet'!G67,0) -> 22698 | I59: =IFERROR('Data Sheet'!H67,0) -> 25424 | J59: =IFERROR('Data Sheet'!I67,0) -> 30193 | ... L59: =IFERROR('Data Sheet'!K67,0) -> 35234
B60: Inventory | C60: =IFERROR('Data Sheet'!B68,0) -> 0 | D60: =IFERROR('Data Sheet'!C68,0) -> 0 | E60: =IFERROR('Data Sheet'!D68,0) -> 0 | F60: =IFERROR('Data Sheet'!E68,0) -> 0 | G60: =IFERROR('Data Sheet'!F68,0) -> 0 | H60: =IFERROR('Data Sheet'!G68,0) -> 0 | I60: =IFERROR('Data Sheet'!H68,0) -> 0 | J60: =IFERROR('Data Sheet'!I68,0) -> 0 | ... L60: =IFERROR('Data Sheet'!K68,0) -> 0
B61: Cash & Bank | C61: =IFERROR('Data Sheet'!B69,0) -> 22625 | D61: =IFERROR('Data Sheet'!C69,0) -> 19818 | E61: =IFERROR('Data Sheet'!D69,0) -> 19568 | F61: =IFERROR('Data Sheet'!E69,0) -> 18649 | G61: =IFERROR('Data Sheet'!F69,0) -> 24714 | H61: =IFERROR('Data Sheet'!G69,0) -> 17472 | I61: =IFERROR('Data Sheet'!H69,0) -> 12173 | J61: =IFERROR('Data Sheet'!I69,0) -> 14786 | ... L61: =IFERROR('Data Sheet'!K69,0) -> 22201
B62: Total Current Assets | C62: =IFERROR(SUM(C59:C61),0) -> 34947 | D62: =IFERROR(SUM(D59:D61),0) -> 32960 | E62: =IFERROR(SUM(E59:E61),0) -> 34395 | F62: =IFERROR(SUM(F59:F61),0) -> 37136 | G62: =IFERROR(SUM(G59:G61),0) -> 44008 | H62: =IFERROR(SUM(H59:H61),0) -> 40170 | I62: =IFERROR(SUM(I59:I61),0) -> 37597 | J62: =IFERROR(SUM(J59:J61),0) -> 44979 | ... L62: =IFERROR(SUM(L59:L61),0) -> 57435
B64: Total Assets | C64: =IFERROR(C62+C57,0) -> 83148 | D64: =IFERROR(D62+D57,0) -> 79349 | E64: =IFERROR(E62+E57,0) -> 84066 | F64: =IFERROR(F62+F57,0) -> 91800 | G64: =IFERROR(G62+G57,0) -> 107511 | H64: =IFERROR(H62+H57,0) -> 116729 | I64: =IFERROR(I62+I57,0) -> 124596 | J64: =IFERROR(J62+J57,0) -> 136020 | ... L64: =IFERROR(L62+L57,0) -> 154288
B66: Check | C66: =C64=C51 -> TRUE | D66: =D64=D51 -> TRUE | E66: =E64=E51 -> TRUE | F66: =F64=F51 -> TRUE | G66: =G64=G51 -> TRUE | H66: =H64=H51 -> TRUE | I66: =I64=I51 -> TRUE | J66: =J64=J51 -> TRUE | ... L66: =L64=L51 -> TRUE
A68: # | B68: Cash Flow Statements
B69: Operating Activities
B70: Profit from operations | C70: =IFERROR('Cash Flow Data'!C4,0) -> 19340 | D70: =IFERROR('Cash Flow Data'!D4,0) -> 19963 | E70: =IFERROR('Cash Flow Data'!E4,0) -> 22126 | F70: =IFERROR('Cash Flow Data'!F4,0) -> 23920 | G70: =IFERROR('Cash Flow Data'!G4,0) -> 28845 | H70: =IFERROR('Cash Flow Data'!H4,0) -> 32921 | I70: =IFERROR('Cash Flow Data'!I4,0) -> 37605 | J70: =IFERROR('Cash Flow Data'!J4,0) -> 39523 | ... L70: =IFERROR('Cash Flow Data'!L4,0) -> 45273
B71: Receivables | C71: =IFERROR('Cash Flow Data'!C5,0) -> -1743 | D71: =IFERROR('Cash Flow Data'!D5,0) -> -1523 | E71: =IFERROR('Cash Flow Data'!E5,0) -> -2881 | F71: =IFERROR('Cash Flow Data'!F5,0) -> -3861 | G71: =IFERROR('Cash Flow Data'!G5,0) -> -1835 | H71: =IFERROR('Cash Flow Data'!H5,0) -> -7937 | I71: =IFERROR('Cash Flow Data'!I5,0) -> -7076 | J71: =IFERROR('Cash Flow Data'!J5,0) -> -2667 | ... L71: =IFERROR('Cash Flow Data'!L5,0) -> -5177
B72: Inventory | C72: 0 | D72: 0 | E72: 0 | F72: 0 | G72: 0 | H72: 0 | I72: 0 | J72: 0 | K72: 0 | L72: 0
B73: Payables | C73: =IFERROR('Cash Flow Data'!C6,0) -> -19 | D73: =IFERROR('Cash Flow Data'!D6,0) -> 328 | E73: =IFERROR('Cash Flow Data'!E6,0) -> 916 | F73: =IFERROR('Cash Flow Data'!F6,0) -> -373 | G73: =IFERROR('Cash Flow Data'!G6,0) -> -245 | H73: =IFERROR('Cash Flow Data'!H6,0) -> 1489 | I73: =IFERROR('Cash Flow Data'!I6,0) -> -279 | J73: =IFERROR('Cash Flow Data'!J6,0) -> 91 | ... L73: =IFERROR('Cash Flow Data'!L6,0) -> -26
B74: Other WC items | C74: =IFERROR('Cash Flow Data'!C8,0) -> -394 | D74: =IFERROR('Cash Flow Data'!D8,0) -> 1279 | E74: =IFERROR('Cash Flow Data'!E8,0) -> 1512 | F74: =IFERROR('Cash Flow Data'!F8,0) -> 1867 | G74: =IFERROR('Cash Flow Data'!G8,0) -> 3382 | H74: =IFERROR('Cash Flow Data'!H8,0) -> 6938 | I74: =IFERROR('Cash Flow Data'!I8,0) -> 4119 | J74: =IFERROR('Cash Flow Data'!J8,0) -> -1334 | ... L74: =IFERROR('Cash Flow Data'!L8,0) -> 5209
B75: Working capital changes | C75: =IFERROR('Cash Flow Data'!C9,0) -> -2156 | D75: =IFERROR('Cash Flow Data'!D9,0) -> 84 | E75: =IFERROR('Cash Flow Data'!E9,0) -> -453 | F75: =IFERROR('Cash Flow Data'!F9,0) -> -2367 | G75: =IFERROR('Cash Flow Data'!G9,0) -> 768 | H75: =IFERROR('Cash Flow Data'!H9,0) -> -1424 | I75: =IFERROR('Cash Flow Data'!I9,0) -> -6344 | J75: =IFERROR('Cash Flow Data'!J9,0) -> -5082 | ... L75: =IFERROR('Cash Flow Data'!L9,0) -> -2639
B76: Direct taxes | C76: =IFERROR('Cash Flow Data'!C10,0) -> -5653 | D76: =IFERROR('Cash Flow Data'!D10,0) -> -6829 | E76: =IFERROR('Cash Flow Data'!E10,0) -> -6832 | F76: =IFERROR('Cash Flow Data'!F10,0) -> -4550 | G76: =IFERROR('Cash Flow Data'!G10,0) -> -6389 | H76: =IFERROR('Cash Flow Data'!H10,0) -> -7612 | I76: =IFERROR('Cash Flow Data'!I10,0) -> -8794 | J76: =IFERROR('Cash Flow Data'!J10,0) -> -9231 | ... L76: =IFERROR('Cash Flow Data'!L10,0) -> -8648
B77: Cash from Operating Activities | C77: =SUM(C70:C76) -> 9375 | D77: =SUM(D70:D76) -> 13302 | E77: =SUM(E70:E76) -> 14388 | F77: =SUM(F70:F76) -> 14636 | G77: =SUM(G70:G76) -> 24526 | H77: =SUM(H70:H76) -> 24375 | I77: =SUM(I70:I76) -> 19231 | J77: =SUM(J70:J76) -> 21300 | ... L77: =SUM(L70:L76) -> 33992
B79: Investing Activities
B80: Fixed assets purchased | C80: =IFERROR('Cash Flow Data'!C12,0) -> -2760 | D80: =IFERROR('Cash Flow Data'!D12,0) -> -1998 | E80: =IFERROR('Cash Flow Data'!E12,0) -> -2445 | F80: =IFERROR('Cash Flow Data'!F12,0) -> -3307 | G80: =IFERROR('Cash Flow Data'!G12,0) -> -2107 | H80: =IFERROR('Cash Flow Data'!H12,0) -> -2161 | I80: =IFERROR('Cash Flow Data'!I12,0) -> -2579 | J80: =IFERROR('Cash Flow Data'!J12,0) -> -2201 | ... L80: =IFERROR('Cash Flow Data'!L12,0) -> -2727
B81: Fixed assets sold | C81: 0 | D81: 0 | E81: 0 | F81: 0 | G81: 0 | H81: 0 | I81: 0 | J81: 0 | K81: 0 | L81: 0
B82: Investments purchased | C82: =IFERROR('Cash Flow Data'!C13,0) -> -66410 | D82: =IFERROR('Cash Flow Data'!D13,0) -> -69159 | E82: =IFERROR('Cash Flow Data'!E13,0) -> -79410 | F82: =IFERROR('Cash Flow Data'!F13,0) -> -37482 | G82: =IFERROR('Cash Flow Data'!G13,0) -> -46738 | H82: =IFERROR('Cash Flow Data'!H13,0) -> -59951 | I82: =IFERROR('Cash Flow Data'!I13,0) -> -75800 | J82: =IFERROR('Cash Flow Data'!J13,0) -> -78092 | ... L82: =IFERROR('Cash Flow Data'!L13,0) -> -82617
B83: Investments sold | C83: =IFERROR('Cash Flow Data'!C14,0) -> 52048 | D83: =IFERROR('Cash Flow Data'!D14,0) -> 74003 | E83: =IFERROR('Cash Flow Data'!E14,0) -> 78098 | F83: =IFERROR('Cash Flow Data'!F14,0) -> 38861 | G83: =IFERROR('Cash Flow Data'!G14,0) -> 40381 | H83: =IFERROR('Cash Flow Data'!H14,0) -> 57356 | I83: =IFERROR('Cash Flow Data'!I14,0) -> 76722 | J83: =IFERROR('Cash Flow Data'!J14,0) -> 72930 | ... L83: =IFERROR('Cash Flow Data'!L14,0) -> 89699
B84: Interest received | C84: =IFERROR('Cash Flow Data'!C15,0) -> 0 | D84: =IFERROR('Cash Flow Data'!D15,0) -> 0 | E84: =IFERROR('Cash Flow Data'!E15,0) -> 0 | F84: =IFERROR('Cash Flow Data'!F15,0) -> 0 | G84: =IFERROR('Cash Flow Data'!G15,0) -> 0 | H84: =IFERROR('Cash Flow Data'!H15,0) -> 0 | I84: =IFERROR('Cash Flow Data'!I15,0) -> 0 | J84: =IFERROR('Cash Flow Data'!J15,0) -> 0 | ... L84: =IFERROR('Cash Flow Data'!L15,0) -> 0
B85: Dividends received | C85: =IFERROR('Cash Flow Data'!C16,0) -> 2753 | D85: =IFERROR('Cash Flow Data'!D16,0) -> 1768 | E85: =IFERROR('Cash Flow Data'!E16,0) -> 1557 | F85: =IFERROR('Cash Flow Data'!F16,0) -> 1929 | G85: =IFERROR('Cash Flow Data'!G16,0) -> 1418 | H85: =IFERROR('Cash Flow Data'!H16,0) -> 1898 | I85: =IFERROR('Cash Flow Data'!I16,0) -> 1525 | J85: =IFERROR('Cash Flow Data'!J16,0) -> 1768 | ... L85: =IFERROR('Cash Flow Data'!L16,0) -> 2713
B86: Redemp n Canc of Shares | C86: 0 | D86: 0 | E86: 0 | F86: 0 | G86: 0 | H86: 0 | I86: 0 | J86: 0 | K86: 0 | L86: 0
B87: Acquisition of companies | C87: =IFERROR('Cash Flow Data'!C17,0) -> 0 | D87: =IFERROR('Cash Flow Data'!D17,0) -> 0 | E87: =IFERROR('Cash Flow Data'!E17,0) -> 0 | F87: =IFERROR('Cash Flow Data'!F17,0) -> 0 | G87: =IFERROR('Cash Flow Data'!G17,0) -> 0 | H87: =IFERROR('Cash Flow Data'!H17,0) -> 0 | I87: =IFERROR('Cash Flow Data'!I17,0) -> 0 | J87: =IFERROR('Cash Flow Data'!J17,0) -> 0 | ... L87: =IFERROR('Cash Flow Data'!L17,0) -> 0
B88: Inter corporate deposits | C88: =IFERROR('Cash Flow Data'!C18,0) -> -164 | D88: =IFERROR('Cash Flow Data'!D18,0) -> -130 | E88: =IFERROR('Cash Flow Data'!E18,0) -> -24 | F88: =IFERROR('Cash Flow Data'!F18,0) -> -108 | G88: =IFERROR('Cash Flow Data'!G18,0) -> 0 | H88: =IFERROR('Cash Flow Data'!H18,0) -> 0 | I88: =IFERROR('Cash Flow Data'!I18,0) -> 0 | J88: =IFERROR('Cash Flow Data'!J18,0) -> 0 | ... L88: =IFERROR('Cash Flow Data'!L18,0) -> 0
B89: Other investing items | C89: =IFERROR('Cash Flow Data'!C19,0) -> -131 | D89: =IFERROR('Cash Flow Data'!D19,0) -> 49 | E89: =IFERROR('Cash Flow Data'!E19,0) -> 1592 | F89: =IFERROR('Cash Flow Data'!F19,0) -> -224 | G89: =IFERROR('Cash Flow Data'!G19,0) -> -327 | H89: =IFERROR('Cash Flow Data'!H19,0) -> -3627 | I89: =IFERROR('Cash Flow Data'!I19,0) -> -939 | J89: =IFERROR('Cash Flow Data'!J19,0) -> 502 | ... L89: =IFERROR('Cash Flow Data'!L19,0) -> -3522
B90: Cash From Investing Activities | C90: =SUM(C80:C89) -> -14664 | D90: =SUM(D80:D89) -> 4533 | E90: =SUM(E80:E89) -> -632 | F90: =SUM(F80:F89) -> -331 | G90: =SUM(G80:G89) -> -7373 | H90: =SUM(H80:H89) -> -6485 | I90: =SUM(I80:I89) -> -1071 | J90: =SUM(J80:J89) -> -5093 | ... L90: =SUM(L80:L89) -> 3546
B92: Financing Activities
B93: Proceeds from shares | C93: =IFERROR('Cash Flow Data'!C21,0) -> 0 | D93: =IFERROR('Cash Flow Data'!D21,0) -> 5 | E93: =IFERROR('Cash Flow Data'!E21,0) -> 6 | F93: =IFERROR('Cash Flow Data'!F21,0) -> 6 | G93: =IFERROR('Cash Flow Data'!G21,0) -> 15 | H93: =IFERROR('Cash Flow Data'!H21,0) -> 21 | I93: =IFERROR('Cash Flow Data'!I21,0) -> 35 | J93: =IFERROR('Cash Flow Data'!J21,0) -> 5 | ... L93: =IFERROR('Cash Flow Data'!L21,0) -> 2
B94: Proceeds from borrowings | C94: 0 | D94: 0 | E94: 0 | F94: 0 | G94: 0 | H94: 0 | I94: 0 | J94: 0 | K94: 0 | L94: 0
B95: Repayment of borrowings | C95: =IFERROR('Cash Flow Data'!C22,0) -> 0 | D95: =IFERROR('Cash Flow Data'!D22,0) -> 0 | E95: =IFERROR('Cash Flow Data'!E22,0) -> 0 | F95: =IFERROR('Cash Flow Data'!F22,0) -> 0 | G95: =IFERROR('Cash Flow Data'!G22,0) -> 0 | H95: =IFERROR('Cash Flow Data'!H22,0) -> 0 | I95: =IFERROR('Cash Flow Data'!I22,0) -> 0 | J95: =IFERROR('Cash Flow Data'!J22,0) -> 0 | ... L95: =IFERROR('Cash Flow Data'!L22,0) -> 0
B96: Interest paid fin | C96: 0 | D96: 0 | E96: 0 | F96: 0 | G96: 0 | H96: 0 | I96: 0 | J96: 0 | K96: 0 | L96: 0
B97: Dividends paid | C97: =IFERROR('Cash Flow Data'!C23,0) -> -6939 | D97: =IFERROR('Cash Flow Data'!D23,0) -> -7464 | E97: =IFERROR('Cash Flow Data'!E23,0) -> -13705 | F97: =IFERROR('Cash Flow Data'!F23,0) -> -9548 | G97: =IFERROR('Cash Flow Data'!G23,0) -> -9137 | H97: =IFERROR('Cash Flow Data'!H23,0) -> -12731 | I97: =IFERROR('Cash Flow Data'!I23,0) -> -13653 | J97: =IFERROR('Cash Flow Data'!J23,0) -> -14731 | ... L97: =IFERROR('Cash Flow Data'!L23,0) -> -18656
B98: Financial liabilities | C98: =IFERROR('Cash Flow Data'!C24,0) -> 0 | D98: =IFERROR('Cash Flow Data'!D24,0) -> 0 | E98: =IFERROR('Cash Flow Data'!E24,0) -> 0 | F98: =IFERROR('Cash Flow Data'!F24,0) -> -571 | G98: =IFERROR('Cash Flow Data'!G24,0) -> -698 | H98: =IFERROR('Cash Flow Data'!H24,0) -> -915 | I98: =IFERROR('Cash Flow Data'!I24,0) -> -1231 | J98: =IFERROR('Cash Flow Data'!J24,0) -> -2024 | ... L98: =IFERROR('Cash Flow Data'!L24,0) -> -2824
B99: Other financing items | C99: =IFERROR('Cash Flow Data'!C25,0) -> 0 | D99: =IFERROR('Cash Flow Data'!D25,0) -> -13046 | E99: =IFERROR('Cash Flow Data'!E25,0) -> -813 | F99: =IFERROR('Cash Flow Data'!F25,0) -> -7478 | G99: =IFERROR('Cash Flow Data'!G25,0) -> 34 | H99: =IFERROR('Cash Flow Data'!H25,0) -> -11017 | I99: =IFERROR('Cash Flow Data'!I25,0) -> -11846 | J99: =IFERROR('Cash Flow Data'!J25,0) -> -754 | ... L99: =IFERROR('Cash Flow Data'!L25,0) -> -18308
B100: Cash From Financing Activities | C100: =SUM(C93:C99) -> -6939 | D100: =SUM(D93:D99) -> -20505 | E100: =SUM(E93:E99) -> -14512 | F100: =SUM(F93:F99) -> -17591 | G100: =SUM(G93:G99) -> -9786 | H100: =SUM(H93:H99) -> -24642 | I100: =SUM(I93:I99) -> -26695 | J100: =SUM(J93:J99) -> -17504 | ... L100: =SUM(L93:L99) -> -39786
B102: Net Cash Flow | C102: =IFERROR(C77+C90+C100,0) -> -12228 | D102: =IFERROR(D77+D90+D100,0) -> -2670 | E102: =IFERROR(E77+E90+E100,0) -> -756 | F102: =IFERROR(F77+F90+F100,0) -> -3286 | G102: =IFERROR(G77+G90+G100,0) -> 7367 | H102: =IFERROR(H77+H90+H100,0) -> -6752 | I102: =IFERROR(I77+I90+I100,0) -> -8535 | J102: =IFERROR(J77+J90+J100,0) -> -1297 | ... L102: =IFERROR(L77+L90+L100,0) -> -2248
A104: # | B104: Cash Flow Statements
B105: Cash from Operating Activity | C105: 11531 | D105: 13218 | E105: 14841 | F105: 17003 | G105: 23224 | H105: 23885 | I105: 22467 | J105: 25210 | K105: 35694 | L105: 33986
B107: Cash from Investing Activity | C107: -14664 | D107: 4533 | E107: -632 | F107: -331 | G107: -7373 | H107: -6485 | I107: -1071 | J107: -5093 | K107: -1864 | L107: 3546
B109: Cash from Financing Activity | C109: -6939 | D109: -20505 | E109: -14512 | F109: -17591 | G109: -9786 | H109: -24642 | I109: -26695 | J109: -17504 | K109: -24161 | L109: -39786
B111: Net Cash Flow | C111: -10072 | D111: -2754 | E111: -303 | F111: -919 | G111: 6065 | H111: -7242 | I111: -5299 | J111: 2613 | K111: 9669 | L111: -2254

Sheet Profit & Loss
A1: ='Data Sheet'!B1 -> INFOSYS LTD | H1: UPDATE | M1: SCREENER.IN
A3: Narration | B3: ='Data Sheet'!B16 -> 42825 | C3: ='Data Sheet'!C16 -> 43190 | D3: ='Data Sheet'!D16 -> 43555 | E3: ='Data Sheet'!E16 -> 43921 | F3: ='Data Sheet'!F16 -> 44286 | G3: ='Data Sheet'!G16 -> 44651 | H3: ='Data Sheet'!H16 -> 45016 | I3: ='Data Sheet'!I16 -> 45382 | ... K3: ='Data Sheet'!K16 -> 46112 | L3: Trailing | M3: Best Case | N3: Worst Case
A4: Sales | B4: ='Data Sheet'!B17 -> 68484 | C4: ='Data Sheet'!C17 -> 70522 | D4: ='Data Sheet'!D17 -> 82675 | E4: ='Data Sheet'!E17 -> 90791 | F4: ='Data Sheet'!F17 -> 100472 | G4: ='Data Sheet'!G17 -> 121641 | H4: ='Data Sheet'!H17 -> 146767 | I4: ='Data Sheet'!I17 -> 153670 | ... K4: ='Data Sheet'!K17 -> 178650 | L4: =SUM(Quarters!H4:K4) -> 184582 | M4: =$K4+M23*K4 -> 195814.61 | N4: =$K4+N23*L4 -> 191150.27
A5: Expenses | B5: =SUM('Data Sheet'!B18,'Data Sheet'!B20:B24, -1*'Data Sheet'!B19) -> 49880 | C5: =SUM('Data Sheet'!C18,'Data Sheet'!C20:C24, -1*'Data Sheet'!C19) -> 51700 | D5: =SUM('Data Sheet'!D18,'Data Sheet'!D20:D24, -1*'Data Sheet'!D19) -> 62505 | E5: =SUM('Data Sheet'!E18,'Data Sheet'!E20:E24, -1*'Data Sheet'!E19) -> 68524 | F5: =SUM('Data Sheet'!F18,'Data Sheet'!F20:F24, -1*'Data Sheet'!F19) -> 72583 | G5: =SUM('Data Sheet'!G18,'Data Sheet'!G20:G24, -1*'Data Sheet'!G19) -> 90150 | H5: =SUM('Data Sheet'!H18,'Data Sheet'!H20:H24, -1*'Data Sheet'!H19) -> 111637 | I5: =SUM('Data Sheet'!I18,'Data Sheet'!I20:I24, -1*'Data Sheet'!I19) -> 117245 | ... K5: =SUM('Data Sheet'!K18,'Data Sheet'!K20:K24, -1*'Data Sheet'!K19) -> 136370 | L5: =SUM(Quarters!H5:K5) -> 140837 | M5: =M4-M6 -> 149188.11 | N5: =N4-N6 -> 145848.62
A6: Operating Profit | B6: =B4-B5 -> 18604 | C6: =C4-C5 -> 18822 | D6: =D4-D5 -> 20170 | E6: =E4-E5 -> 22267 | F6: =F4-F5 -> 27889 | G6: =G4-G5 -> 31491 | H6: =H4-H5 -> 35130 | I6: =I4-I5 -> 36425 | ... K6: =K4-K5 -> 42280 | L6: =SUM(Quarters!H6:K6) -> 43745 | M6: =M4*M24 -> 46626.497 | N6: =N4*N24 -> 45301.646
A7: Other Income | B7: ='Data Sheet'!B25 -> 3050 | C7: ='Data Sheet'!C25 -> 3311 | D7: ='Data Sheet'!D25 -> 2882 | E7: ='Data Sheet'!E25 -> 2803 | F7: ='Data Sheet'!F25 -> 2201 | G7: ='Data Sheet'!G25 -> 2295 | H7: ='Data Sheet'!H25 -> 2701 | I7: ='Data Sheet'!I25 -> 4711 | ... K7: ='Data Sheet'!K25 -> 3033 | L7: =SUM(Quarters!H7:K7) -> 2975 | M7: 0 | N7: 0
A8: Depreciation | B8: ='Data Sheet'!B26 -> 1703 | C8: ='Data Sheet'!C26 -> 1863 | D8: ='Data Sheet'!D26 -> 2011 | E8: ='Data Sheet'!E26 -> 2893 | F8: ='Data Sheet'!F26 -> 3267 | G8: ='Data Sheet'!G26 -> 3476 | H8: ='Data Sheet'!H26 -> 4225 | I8: ='Data Sheet'!I26 -> 4678 | ... K8: ='Data Sheet'!K26 -> 4902 | L8: =SUM(Quarters!H8:K8) -> 5007 | M8: =+$L8 -> 5007 | N8: =+$L8 -> 5007
A9: Interest | B9: ='Data Sheet'!B27 -> 0 | C9: ='Data Sheet'!C27 -> 0 | D9: ='Data Sheet'!D27 -> 0 | E9: ='Data Sheet'!E27 -> 170 | F9: ='Data Sheet'!F27 -> 195 | G9: ='Data Sheet'!G27 -> 200 | H9: ='Data Sheet'!H27 -> 284 | I9: ='Data Sheet'!I27 -> 470 | ... K9: ='Data Sheet'!K27 -> 416 | L9: =SUM(Quarters!H9:K9) -> 430 | M9: =+$L9 -> 430 | N9: =+$L9 -> 430
A10: Profit before tax | B10: ='Data Sheet'!B28 -> 19951 | C10: ='Data Sheet'!C28 -> 20270 | D10: ='Data Sheet'!D28 -> 21041 | E10: ='Data Sheet'!E28 -> 22007 | F10: ='Data Sheet'!F28 -> 26628 | G10: ='Data Sheet'!G28 -> 30110 | H10: ='Data Sheet'!H28 -> 33322 | I10: ='Data Sheet'!I28 -> 35988 | ... K10: ='Data Sheet'!K28 -> 39995 | L10: =SUM(Quarters!H10:K10) -> 41283 | M10: =M6+M7-SUM(M8:M9) -> 41189.497 | N10: =N6+N7-SUM(N8:N9) -> 39864.646
A11: Tax | B11: ='Data Sheet'!B29 -> 5598 | C11: ='Data Sheet'!C29 -> 4241 | D11: ='Data Sheet'!D29 -> 5631 | E11: ='Data Sheet'!E29 -> 5368 | F11: ='Data Sheet'!F29 -> 7205 | G11: ='Data Sheet'!G29 -> 7964 | H11: ='Data Sheet'!H29 -> 9214 | I11: ='Data Sheet'!I29 -> 9740 | ... K11: ='Data Sheet'!K29 -> 10521 | L11: =SUM(Quarters!H11:K11) -> 10958 | M11: =IF($L10>0,$L11/$L10,0) -> 0.26543614 | N11: =IF($L10>0,$L11/$L10,0) -> 0.26543614
A12: Net profit | B12: ='Data Sheet'!B30 -> 14353 | C12: ='Data Sheet'!C30 -> 16029 | D12: ='Data Sheet'!D30 -> 15404 | E12: ='Data Sheet'!E30 -> 16594 | F12: ='Data Sheet'!F30 -> 19351 | G12: ='Data Sheet'!G30 -> 22110 | H12: ='Data Sheet'!H30 -> 24095 | I12: ='Data Sheet'!I30 -> 26233 | ... K12: ='Data Sheet'!K30 -> 29440 | L12: =SUM(Quarters!H12:K12) -> 30288 | M12: =M10-M11*M10 -> 30256.316 | N12: =N10-N11*N10 -> 29283.128
A13: EPS | B13: =IF('Data Sheet'!B93>0,B12/'Data Sheet'!B93,0) -> 31.243606 | C13: =IF('Data Sheet'!C93>0,C12/'Data Sheet'!C93,0) -> 36.694748 | D13: =IF('Data Sheet'!D93>0,D12/'Data Sheet'!D93,0) -> 35.258303 | E13: =IF('Data Sheet'!E93>0,E12/'Data Sheet'!E93,0) -> 38.962198 | F13: =IF('Data Sheet'!F93>0,F12/'Data Sheet'!F93,0) -> 45.41742 | G13: =IF('Data Sheet'!G93>0,G12/'Data Sheet'!G93,0) -> 52.559013 | H13: =IF('Data Sheet'!H93>0,H12/'Data Sheet'!H93,0) -> 58.079834 | I13: =IF('Data Sheet'!I93>0,I12/'Data Sheet'!I93,0) -> 63.198343 | ... K13: =IF('Data Sheet'!K93>0,K12/'Data Sheet'!K93,0) -> 72.590985 | L13: =IF('Data Sheet'!$B6>0,'Profit & Loss'!L12/'Data Sheet'!$B6,0) -> 74.635913 | M13: =IF('Data Sheet'!$B6>0,'Profit & Loss'!M12/'Data Sheet'!$B6,0) -> 74.557838 | N13: =IF('Data Sheet'!$B6>0,'Profit & Loss'!N12/'Data Sheet'!$B6,0) -> 72.159701
A14: Price to earning | B14: =IF(B15>0,B15/B13,"") -> 16.359507 | C14: =IF(C15>0,C15/C13,"") -> 15.421825 | D14: =IF(D15>0,D15/D13,"") -> 21.097158 | E14: =IF(E15>0,E15/E13,"") -> 16.464677 | F14: =IF(F15>0,F15/F13,"") -> 30.121702 | G14: =IF(G15>0,G15/G13,"") -> 36.280171 | H14: =IF(H15>0,H15/H13,"") -> 24.585986 | I14: =IF(I15>0,I15/I13,"") -> 23.703944 | ... K14: =IF(K15>0,K15/K13,"") -> 17.228035 | L14: =IF(L13>0,L15/L13,0) -> 15.019579 | M14: =M25 -> 20.092951 | N14: =N25 -> 15.019579
A15: Price | B15: ='Data Sheet'!B90 -> 511.13 | C15: ='Data Sheet'!C90 -> 565.9 | D15: ='Data Sheet'!D90 -> 743.85 | E15: ='Data Sheet'!E90 -> 641.5 | F15: ='Data Sheet'!F90 -> 1368.05 | G15: ='Data Sheet'!G90 -> 1906.85 | H15: ='Data Sheet'!H90 -> 1427.95 | I15: ='Data Sheet'!I90 -> 1498.05 | ... K15: ='Data Sheet'!K90 -> 1250.6 | L15: ='Data Sheet'!B8 -> 1121 | M15: =M13*M14 -> 1498.087 | N15: =N13*N14 -> 1083.8083
A17: RATIOS:
A18: Dividend Payout | B18: =IF('Data Sheet'!B30>0, 'Data Sheet'!B31/'Data Sheet'!B30, 0) -> 0.41047865 | C18: =IF('Data Sheet'!C30>0, 'Data Sheet'!C31/'Data Sheet'!C30, 0) -> 0.59052966 | D18: =IF('Data Sheet'!D30>0, 'Data Sheet'!D31/'Data Sheet'!D30, 0) -> 0.59870813 | E18: =IF('Data Sheet'!E30>0, 'Data Sheet'!E31/'Data Sheet'!E30, 0) -> 0.44757141 | F18: =IF('Data Sheet'!F30>0, 'Data Sheet'!F31/'Data Sheet'!F30, 0) -> 0.59271355 | G18: =IF('Data Sheet'!G30>0, 'Data Sheet'!G31/'Data Sheet'!G30, 0) -> 0.58831298 | H18: =IF('Data Sheet'!H30>0, 'Data Sheet'!H31/'Data Sheet'!H30, 0) -> 0.58390537 | I18: =IF('Data Sheet'!I30>0, 'Data Sheet'!I31/'Data Sheet'!I30, 0) -> 0.72630656 | ... K18: =IF('Data Sheet'!K30>0, 'Data Sheet'!K31/'Data Sheet'!K30, 0) -> 0.66
A19: OPM | B19: =IF(B6>0,B6/B4,0) -> 0.27165469 | C19: =IF(C6>0,C6/C4,0) -> 0.26689544 | D19: =IF(D6>0,D6/D4,0) -> 0.24396734 | E19: =IF(E6>0,E6/E4,0) -> 0.24525559 | F19: =IF(F6>0,F6/F4,0) -> 0.27757982 | G19: =IF(G6>0,G6/G4,0) -> 0.25888475 | H19: =IF(H6>0,H6/H4,0) -> 0.23935898 | I19: =IF(I6>0,I6/I4,0) -> 0.2370339 | ... L19: =IF(L6>0,L6/L4,0) -> 0.23699494
G22: TRENDS: | H22: 10 YEARS | I22: 7 YEARS | J22: 5 YEARS | K22: 3 YEARS | L22: RECENT | M22: BEST | N22: WORST
G23: Sales Growth | H23: =IF(B4=0,"",POWER($K4/B4,1/9)-1) -> 0.11241852 | I23: =IF(D4=0,"",POWER($K4/D4,1/7)-1) -> 0.11635961 | J23: =IF(F4=0,"",POWER($K4/F4,1/5)-1) -> 0.12199674 | K23: =IF(H4=0,"",POWER($K4/H4, 1/3)-1) -> 0.067722024 | L23: =IF(ISERROR(MAX(IF(J4=0,"",(K4-J4)/J4),IF(K4=0,"",(L4-K4)/K4))),"",MAX(IF(J4=0,"",(K4-J4)/J4),IF(K4=0,"",(L4-K4)/K4))) -> 0.096079514 | M23: =MAX(K23:L23) -> 0.096079514 | N23: =MIN(H23:L23) -> 0.067722024
G24: OPM | H24: =IF(SUM(B4:$K$4)=0,"",SUMPRODUCT(B19:$K$19,B4:$K$4)/SUM(B4:$K$4)) -> 0.24842648 | I24: =IF(SUM(E4:$K$4)=0,"",SUMPRODUCT(E19:$K$19,E4:$K$4)/SUM(E4:$K$4)) -> 0.2457829 | J24: =IF(SUM(G4:$K$4)=0,"",SUMPRODUCT(G19:$K$19,G4:$K$4)/SUM(G4:$K$4)) -> 0.2416625 | K24: =IF(SUM(I4:$K$4)=0, "", SUMPRODUCT(I19:$K$19,I4:$K$4)/SUM(I4:$K$4)) -> 0.23811552 | L24: =L19 -> 0.23699494 | M24: =MAX(K24:L24) -> 0.23811552 | N24: =MIN(H24:L24) -> 0.23699494
G25: Price to Earning | H25: =IF(ISERROR(AVERAGEIF(B14:$L14,">0")),"",AVERAGEIF(B14:$L14,">0")) -> 21.882076 | I25: =IF(ISERROR(AVERAGEIF(E14:$L14,">0")),"",AVERAGEIF(E14:$L14,">0")) -> 23.478043 | J25: =IF(ISERROR(AVERAGEIF(G14:$L14,">0")),"",AVERAGEIF(G14:$L14,">0")) -> 23.53966 | K25: =IF(ISERROR(AVERAGEIF(I14:$L14,">0")),"",AVERAGEIF(I14:$L14,">0")) -> 20.092951 | L25: =L14 -> 15.019579 | M25: =MAX(K25:L25) -> 20.092951 | N25: =MIN(H25:L25) -> 15.019579

Sheet Balance Sheet
A1: ='Profit & Loss'!A1 -> INFOSYS LTD | E1: UPDATE | J1: SCREENER.IN
A3: Narration | B3: ='Data Sheet'!B56 -> 42825 | C3: ='Data Sheet'!C56 -> 43190 | D3: ='Data Sheet'!D56 -> 43555 | E3: ='Data Sheet'!E56 -> 43921 | F3: ='Data Sheet'!F56 -> 44286 | G3: ='Data Sheet'!G56 -> 44651 | H3: ='Data Sheet'!H56 -> 45016 | I3: ='Data Sheet'!I56 -> 45382 | ... K3: ='Data Sheet'!K56 -> 46112
A4: Equity Share Capital | B4: ='Data Sheet'!B57 -> 1144 | C4: ='Data Sheet'!C57 -> 1088 | D4: ='Data Sheet'!D57 -> 2170 | E4: ='Data Sheet'!E57 -> 2122 | F4: ='Data Sheet'!F57 -> 2124 | G4: ='Data Sheet'!G57 -> 2098 | H4: ='Data Sheet'!H57 -> 2069 | I4: ='Data Sheet'!I57 -> 2071 | ... K4: ='Data Sheet'!K57 -> 2024
A5: Reserves | B5: ='Data Sheet'!B58 -> 67838 | C5: ='Data Sheet'!C58 -> 63835 | D5: ='Data Sheet'!D58 -> 62778 | E5: ='Data Sheet'!E58 -> 63328 | F5: ='Data Sheet'!F58 -> 74227 | G5: ='Data Sheet'!G58 -> 73252 | H5: ='Data Sheet'!H58 -> 73338 | I5: ='Data Sheet'!I58 -> 86045 | ... K5: ='Data Sheet'!K58 -> 90828
A6: Borrowings | B6: ='Data Sheet'!B59 -> 0 | C6: ='Data Sheet'!C59 -> 0 | D6: ='Data Sheet'!D59 -> 0 | E6: ='Data Sheet'!E59 -> 4633 | F6: ='Data Sheet'!F59 -> 5325 | G6: ='Data Sheet'!G59 -> 5474 | H6: ='Data Sheet'!H59 -> 8299 | I6: ='Data Sheet'!I59 -> 8359 | ... K6: ='Data Sheet'!K59 -> 9176
A7: Other Liabilities | B7: ='Data Sheet'!B60 -> 14166 | C7: ='Data Sheet'!C60 -> 14426 | D7: ='Data Sheet'!D60 -> 19118 | E7: ='Data Sheet'!E60 -> 21717 | F7: ='Data Sheet'!F60 -> 25835 | G7: ='Data Sheet'!G60 -> 35905 | H7: ='Data Sheet'!H60 -> 40890 | I7: ='Data Sheet'!I60 -> 39545 | ... K7: ='Data Sheet'!K60 -> 52260
A8: Total | B8: ='Data Sheet'!B61 -> 83148 | C8: ='Data Sheet'!C61 -> 79349 | D8: ='Data Sheet'!D61 -> 84066 | E8: ='Data Sheet'!E61 -> 91800 | F8: ='Data Sheet'!F61 -> 107511 | G8: ='Data Sheet'!G61 -> 116729 | H8: ='Data Sheet'!H61 -> 124596 | I8: ='Data Sheet'!I61 -> 136020 | ... K8: ='Data Sheet'!K61 -> 154288
A10: Net Block | B10: ='Data Sheet'!B62 -> 14179 | C10: ='Data Sheet'!C62 -> 12574 | D10: ='Data Sheet'!D62 -> 15710 | E10: ='Data Sheet'!E62 -> 23789 | F10: ='Data Sheet'!F62 -> 25505 | G10: ='Data Sheet'!G62 -> 25800 | H10: ='Data Sheet'!H62 -> 29225 | I10: ='Data Sheet'!I62 -> 27622 | ... K10: ='Data Sheet'!K62 -> 33770
A11: Capital Work in Progress | B11: ='Data Sheet'!B63 -> 1365 | C11: ='Data Sheet'!C63 -> 1606 | D11: ='Data Sheet'!D63 -> 1388 | E11: ='Data Sheet'!E63 -> 954 | F11: ='Data Sheet'!F63 -> 922 | G11: ='Data Sheet'!G63 -> 416 | H11: ='Data Sheet'!H63 -> 288 | I11: ='Data Sheet'!I63 -> 293 | ... K11: ='Data Sheet'!K63 -> 526
A12: Investments | B12: ='Data Sheet'!B64 -> 16423 | C12: ='Data Sheet'!C64 -> 12163 | D12: ='Data Sheet'!D64 -> 11261 | E12: ='Data Sheet'!E64 -> 8792 | F12: ='Data Sheet'!F64 -> 14205 | G12: ='Data Sheet'!G64 -> 20324 | H12: ='Data Sheet'!H64 -> 19478 | I12: ='Data Sheet'!I64 -> 24623 | ... K12: ='Data Sheet'!K64 -> 21880
A13: Other Assets | B13: ='Data Sheet'!B65 -> 51181 | C13: ='Data Sheet'!C65 -> 53006 | D13: ='Data Sheet'!D65 -> 55707 | E13: ='Data Sheet'!E65 -> 58265 | F13: ='Data Sheet'!F65 -> 66879 | G13: ='Data Sheet'!G65 -> 70189 | H13: ='Data Sheet'!H65 -> 75605 | I13: ='Data Sheet'!I65 -> 83482 | ... K13: ='Data Sheet'!K65 -> 98112
A14: Total | B14: ='Data Sheet'!B66 -> 83148 | C14: ='Data Sheet'!C66 -> 79349 | D14: ='Data Sheet'!D66 -> 84066 | E14: ='Data Sheet'!E66 -> 91800 | F14: ='Data Sheet'!F66 -> 107511 | G14: ='Data Sheet'!G66 -> 116729 | H14: ='Data Sheet'!H66 -> 124596 | I14: ='Data Sheet'!I66 -> 136020 | ... K14: ='Data Sheet'!K66 -> 154288
A16: Working Capital | B16: =B13-B7 -> 37015 | C16: =C13-C7 -> 38580 | D16: =D13-D7 -> 36589 | E16: =E13-E7 -> 36548 | F16: =F13-F7 -> 41044 | G16: =G13-G7 -> 34284 | H16: =H13-H7 -> 34715 | I16: =I13-I7 -> 43937 | ... K16: =K13-K7 -> 45852
A17: Debtors | B17: ='Data Sheet'!B67 -> 12322 | C17: ='Data Sheet'!C67 -> 13142 | D17: ='Data Sheet'!D67 -> 14827 | E17: ='Data Sheet'!E67 -> 18487 | F17: ='Data Sheet'!F67 -> 19294 | G17: ='Data Sheet'!G67 -> 22698 | H17: ='Data Sheet'!H67 -> 25424 | I17: ='Data Sheet'!I67 -> 30193 | ... K17: ='Data Sheet'!K67 -> 35234
A18: Inventory | B18: ='Data Sheet'!B68 -> 0 | C18: ='Data Sheet'!C68 -> 0 | D18: ='Data Sheet'!D68 -> 0 | E18: ='Data Sheet'!E68 -> 0 | F18: ='Data Sheet'!F68 -> 0 | G18: ='Data Sheet'!G68 -> 0 | H18: ='Data Sheet'!H68 -> 0 | I18: ='Data Sheet'!I68 -> 0 | ... K18: ='Data Sheet'!K68 -> 0
A20: Debtor Days | B20: =IF('Profit & Loss'!B4>0,'Balance Sheet'!B17/('Profit & Loss'!B4/365),0) -> 65.672712 | C20: =IF('Profit & Loss'!C4>0,'Balance Sheet'!C17/('Profit & Loss'!C4/365),0) -> 68.018916 | D20: =IF('Profit & Loss'!D4>0,'Balance Sheet'!D17/('Profit & Loss'!D4/365),0) -> 65.459389 | E20: =IF('Profit & Loss'!E4>0,'Balance Sheet'!E17/('Profit & Loss'!E4/365),0) -> 74.321849 | F20: =IF('Profit & Loss'!F4>0,'Balance Sheet'!F17/('Profit & Loss'!F4/365),0) -> 70.092265 | G20: =IF('Profit & Loss'!G4>0,'Balance Sheet'!G17/('Profit & Loss'!G4/365),0) -> 68.108368 | H20: =IF('Profit & Loss'!H4>0,'Balance Sheet'!H17/('Profit & Loss'!H4/365),0) -> 63.227837 | I20: =IF('Profit & Loss'!I4>0,'Balance Sheet'!I17/('Profit & Loss'!I4/365),0) -> 71.715006 | ... K20: =IF('Profit & Loss'!K4>0,'Balance Sheet'!K17/('Profit & Loss'!K4/365),0) -> 71.986622
A21: Inventory Turnover | B21: =IF('Balance Sheet'!B18>0,'Profit & Loss'!B4/'Balance Sheet'!B18,0) -> 0 | C21: =IF('Balance Sheet'!C18>0,'Profit & Loss'!C4/'Balance Sheet'!C18,0) -> 0 | D21: =IF('Balance Sheet'!D18>0,'Profit & Loss'!D4/'Balance Sheet'!D18,0) -> 0 | E21: =IF('Balance Sheet'!E18>0,'Profit & Loss'!E4/'Balance Sheet'!E18,0) -> 0 | F21: =IF('Balance Sheet'!F18>0,'Profit & Loss'!F4/'Balance Sheet'!F18,0) -> 0 | G21: =IF('Balance Sheet'!G18>0,'Profit & Loss'!G4/'Balance Sheet'!G18,0) -> 0 | H21: =IF('Balance Sheet'!H18>0,'Profit & Loss'!H4/'Balance Sheet'!H18,0) -> 0 | I21: =IF('Balance Sheet'!I18>0,'Profit & Loss'!I4/'Balance Sheet'!I18,0) -> 0 | ... K21: =IF('Balance Sheet'!K18>0,'Profit & Loss'!K4/'Balance Sheet'!K18,0) -> 0
A23: Return on Equity | B23: =IF(SUM('Balance Sheet'!B4:B5)>0,'Profit & Loss'!B12/SUM('Balance Sheet'!B4:B5),"") -> 0.20806877 | C23: =IF(SUM('Balance Sheet'!C4:C5)>0,'Profit & Loss'!C12/SUM('Balance Sheet'!C4:C5),"") -> 0.24689247 | D23: =IF(SUM('Balance Sheet'!D4:D5)>0,'Profit & Loss'!D12/SUM('Balance Sheet'!D4:D5),"") -> 0.23717435 | E23: =IF(SUM('Balance Sheet'!E4:E5)>0,'Profit & Loss'!E12/SUM('Balance Sheet'!E4:E5),"") -> 0.25353705 | F23: =IF(SUM('Balance Sheet'!F4:F5)>0,'Profit & Loss'!F12/SUM('Balance Sheet'!F4:F5),"") -> 0.25344789 | G23: =IF(SUM('Balance Sheet'!G4:G5)>0,'Profit & Loss'!G12/SUM('Balance Sheet'!G4:G5),"") -> 0.29343066 | H23: =IF(SUM('Balance Sheet'!H4:H5)>0,'Profit & Loss'!H12/SUM('Balance Sheet'!H4:H5),"") -> 0.31953267 | I23: =IF(SUM('Balance Sheet'!I4:I5)>0,'Profit & Loss'!I12/SUM('Balance Sheet'!I4:I5),"") -> 0.29770984 | ... K23: =IF(SUM('Balance Sheet'!K4:K5)>0,'Profit & Loss'!K12/SUM('Balance Sheet'!K4:K5),"") -> 0.31706371
A24: Return on Capital Emp | C24: =IF((B4+B5+B6+C4+C5+C6)>0,('Profit & Loss'!C10+'Profit & Loss'!C9)*2/(B4+B5+B6+C4+C5+C6),"") -> 0.30275195 | D24: =IF((C4+C5+C6+D4+D5+D6)>0,('Profit & Loss'!D10+'Profit & Loss'!D9)*2/(C4+C5+C6+D4+D5+D6),"") -> 0.32402923 | E24: =IF((D4+D5+D6+E4+E5+E6)>0,('Profit & Loss'!E10+'Profit & Loss'!E9)*2/(D4+D5+D6+E4+E5+E6),"") -> 0.32847272 | F24: =IF((E4+E5+E6+F4+F5+F6)>0,('Profit & Loss'!F10+'Profit & Loss'!F9)*2/(E4+E5+E6+F4+F5+F6),"") -> 0.35349469 | G24: =IF((F4+F5+F6+G4+G5+G6)>0,('Profit & Loss'!G10+'Profit & Loss'!G9)*2/(F4+F5+F6+G4+G5+G6),"") -> 0.37304615 | H24: =IF((G4+G5+G6+H4+H5+H6)>0,('Profit & Loss'!H10+'Profit & Loss'!H9)*2/(G4+G5+G6+H4+H5+H6),"") -> 0.40850909 | I24: =IF((H4+H5+H6+I4+I5+I6)>0,('Profit & Loss'!I10+'Profit & Loss'!I9)*2/(H4+H5+H6+I4+I5+I6),"") -> 0.40468196 | J24: =IF((I4+I5+I6+J4+J5+J6)>0,('Profit & Loss'!J10+'Profit & Loss'!J9)*2/(I4+I5+I6+J4+J5+J6),"") -> 0.37925394 | K24: =IF((J4+J5+J6+K4+K5+K6)>0,('Profit & Loss'!K10+'Profit & Loss'!K9)*2/(J4+J5+J6+K4+K5+K6),"") -> 0.39220082

Sheet Quarters
A1: ='Profit & Loss'!A1 -> INFOSYS LTD | E1: UPDATE | J1: SCREENER.IN
A3: Narration | B3: ='Data Sheet'!B41 -> 45382 | C3: ='Data Sheet'!C41 -> 45473 | D3: ='Data Sheet'!D41 -> 45565 | E3: ='Data Sheet'!E41 -> 45657 | F3: ='Data Sheet'!F41 -> 45747 | G3: ='Data Sheet'!G41 -> 45838 | H3: ='Data Sheet'!H41 -> 45930 | I3: ='Data Sheet'!I41 -> 46022 | ... K3: ='Data Sheet'!K41 -> 46203
A4: Sales | B4: ='Data Sheet'!B42 -> 37923 | C4: ='Data Sheet'!C42 -> 39315 | D4: ='Data Sheet'!D42 -> 40986 | E4: ='Data Sheet'!E42 -> 41764 | F4: ='Data Sheet'!F42 -> 40925 | G4: ='Data Sheet'!G42 -> 42279 | H4: ='Data Sheet'!H42 -> 44490 | I4: ='Data Sheet'!I42 -> 45479 | ... K4: ='Data Sheet'!K42 -> 48211
A5: Expenses | B5: ='Data Sheet'!B43 -> 29139 | C5: ='Data Sheet'!C43 -> 29878 | D5: ='Data Sheet'!D43 -> 31177 | E5: ='Data Sheet'!E43 -> 31649 | F5: ='Data Sheet'!F43 -> 31051 | G5: ='Data Sheet'!G43 -> 32336 | H5: ='Data Sheet'!H43 -> 33955 | I5: ='Data Sheet'!I43 -> 34845 | ... K5: ='Data Sheet'!K43 -> 36802
A6: Operating Profit | B6: ='Data Sheet'!B50 -> 8784 | C6: ='Data Sheet'!C50 -> 9437 | D6: ='Data Sheet'!D50 -> 9809 | E6: ='Data Sheet'!E50 -> 10115 | F6: ='Data Sheet'!F50 -> 9874 | G6: ='Data Sheet'!G50 -> 9943 | H6: ='Data Sheet'!H50 -> 10535 | I6: ='Data Sheet'!I50 -> 10634 | ... K6: ='Data Sheet'!K50 -> 11409
A7: Other Income | B7: ='Data Sheet'!B44 -> 2729 | C7: ='Data Sheet'!C44 -> 838 | D7: ='Data Sheet'!D44 -> 712 | E7: ='Data Sheet'!E44 -> 859 | F7: ='Data Sheet'!F44 -> 1190 | G7: ='Data Sheet'!G44 -> 1042 | H7: ='Data Sheet'!H44 -> 982 | I7: ='Data Sheet'!I44 -> -150 | ... K7: ='Data Sheet'!K44 -> 984
A8: Depreciation | B8: ='Data Sheet'!B45 -> 1163 | C8: ='Data Sheet'!C45 -> 1149 | D8: ='Data Sheet'!D45 -> 1160 | E8: ='Data Sheet'!E45 -> 1203 | F8: ='Data Sheet'!F45 -> 1299 | G8: ='Data Sheet'!G45 -> 1140 | H8: ='Data Sheet'!H45 -> 1182 | I8: ='Data Sheet'!I45 -> 1155 | ... K8: ='Data Sheet'!K45 -> 1246
A9: Interest | B9: ='Data Sheet'!B46 -> 110 | C9: ='Data Sheet'!C46 -> 105 | D9: ='Data Sheet'!D46 -> 108 | E9: ='Data Sheet'!E46 -> 101 | F9: ='Data Sheet'!F46 -> 102 | G9: ='Data Sheet'!G46 -> 105 | H9: ='Data Sheet'!H46 -> 106 | I9: ='Data Sheet'!I46 -> 100 | ... K9: ='Data Sheet'!K46 -> 119
A10: Profit before tax | B10: ='Data Sheet'!B47 -> 10240 | C10: ='Data Sheet'!C47 -> 9021 | D10: ='Data Sheet'!D47 -> 9253 | E10: ='Data Sheet'!E47 -> 9670 | F10: ='Data Sheet'!F47 -> 9663 | G10: ='Data Sheet'!G47 -> 9740 | H10: ='Data Sheet'!H47 -> 10229 | I10: ='Data Sheet'!I47 -> 9229 | ... K10: ='Data Sheet'!K47 -> 11028
A11: Tax | B11: ='Data Sheet'!B48 -> 2265 | C11: ='Data Sheet'!C48 -> 2647 | D11: ='Data Sheet'!D48 -> 2737 | E11: ='Data Sheet'!E48 -> 2848 | F11: ='Data Sheet'!F48 -> 2625 | G11: ='Data Sheet'!G48 -> 2816 | H11: ='Data Sheet'!H48 -> 2854 | I11: ='Data Sheet'!I48 -> 2563 | ... K11: ='Data Sheet'!K48 -> 3253
A12: Net profit | B12: ='Data Sheet'!B49 -> 7969 | C12: ='Data Sheet'!C49 -> 6368 | D12: ='Data Sheet'!D49 -> 6506 | E12: ='Data Sheet'!E49 -> 6806 | F12: ='Data Sheet'!F49 -> 7033 | G12: ='Data Sheet'!G49 -> 6921 | H12: ='Data Sheet'!H49 -> 7364 | I12: ='Data Sheet'!I49 -> 6654 | ... K12: ='Data Sheet'!K49 -> 7769
A14: OPM | B14: =IF(B4>0,B6/B4,"") -> 0.23162724 | C14: =IF(C4>0,C6/C4,"") -> 0.24003561 | D14: =IF(D4>0,D6/D4,"") -> 0.23932562 | E14: =IF(E4>0,E6/E4,"") -> 0.24219423 | F14: =IF(F4>0,F6/F4,"") -> 0.24127062 | G14: =IF(G4>0,G6/G4,"") -> 0.23517586 | H14: =IF(H4>0,H6/H4,"") -> 0.23679479 | I14: =IF(I4>0,I6/I4,"") -> 0.2338222 | ... K14: =IF(K4>0,K6/K4,"") -> 0.23664724

Sheet Common Size Statement
B7: ="Common Size Income Statement"&" "&"- "&'Data Sheet'!$B$1 -> Common Size Income Statement - INFOSYS LTD
B9: Particulars | C9: ='Data Sheet'!B16 -> 42825 | D9: ='Data Sheet'!C16 -> 43190 | E9: ='Data Sheet'!D16 -> 43555 | F9: ='Data Sheet'!E16 -> 43921 | G9: ='Data Sheet'!F16 -> 44286 | H9: ='Data Sheet'!G16 -> 44651 | I9: ='Data Sheet'!H16 -> 45016 | J9: ='Data Sheet'!I16 -> 45382 | ... L9: ='Data Sheet'!K16 -> 46112
B11: ='Data Sheet'!A17 -> Sales | C11: ='Data Sheet'!B17/'Data Sheet'!B$17 -> 1 | D11: ='Data Sheet'!C17/'Data Sheet'!C$17 -> 1 | E11: ='Data Sheet'!D17/'Data Sheet'!D$17 -> 1 | F11: ='Data Sheet'!E17/'Data Sheet'!E$17 -> 1 | G11: ='Data Sheet'!F17/'Data Sheet'!F$17 -> 1 | H11: ='Data Sheet'!G17/'Data Sheet'!G$17 -> 1 | I11: ='Data Sheet'!H17/'Data Sheet'!H$17 -> 1 | J11: ='Data Sheet'!I17/'Data Sheet'!I$17 -> 1 | ... L11: ='Data Sheet'!K17/'Data Sheet'!K$17 -> 1
B12: ='Data Sheet'!A18 -> Raw Material Cost | C12: ='Data Sheet'!B18/'Data Sheet'!B$17 -> 0 | D12: ='Data Sheet'!C18/'Data Sheet'!C$17 -> 0 | E12: ='Data Sheet'!D18/'Data Sheet'!D$17 -> 0 | F12: ='Data Sheet'!E18/'Data Sheet'!E$17 -> 0 | G12: ='Data Sheet'!F18/'Data Sheet'!F$17 -> 0 | H12: ='Data Sheet'!G18/'Data Sheet'!G$17 -> 0 | I12: ='Data Sheet'!H18/'Data Sheet'!H$17 -> 0 | J12: ='Data Sheet'!I18/'Data Sheet'!I$17 -> 0 | ... L12: ='Data Sheet'!K18/'Data Sheet'!K$17 -> 0
B13: ='Data Sheet'!A19 -> Change in Inventory | C13: ='Data Sheet'!B19/'Data Sheet'!B$17 -> 0 | D13: ='Data Sheet'!C19/'Data Sheet'!C$17 -> 0 | E13: ='Data Sheet'!D19/'Data Sheet'!D$17 -> 0 | F13: ='Data Sheet'!E19/'Data Sheet'!E$17 -> 0 | G13: ='Data Sheet'!F19/'Data Sheet'!F$17 -> 0 | H13: ='Data Sheet'!G19/'Data Sheet'!G$17 -> 0 | I13: ='Data Sheet'!H19/'Data Sheet'!H$17 -> 0 | J13: ='Data Sheet'!I19/'Data Sheet'!I$17 -> 0 | ... L13: ='Data Sheet'!K19/'Data Sheet'!K$17 -> 0
B14: ='Data Sheet'!A20 -> Power and Fuel | C14: ='Data Sheet'!B20/'Data Sheet'!B$17 -> 0.0033292448 | D14: ='Data Sheet'!C20/'Data Sheet'!C$17 -> 0.0029352542 | E14: ='Data Sheet'!D20/'Data Sheet'!D$17 -> 0.0026731176 | F14: ='Data Sheet'!E20/'Data Sheet'!E$17 -> 0.0025222764 | G14: ='Data Sheet'!F20/'Data Sheet'!F$17 -> 0.0014232821 | H14: ='Data Sheet'!G20/'Data Sheet'!G$17 -> 0.0010851604 | I14: ='Data Sheet'!H20/'Data Sheet'!H$17 -> 0.0011991797 | J14: ='Data Sheet'!I20/'Data Sheet'!I$17 -> 0.0012949828 | ... L14: ='Data Sheet'!K20/'Data Sheet'!K$17 -> 0.0012482508
B15: ='Data Sheet'!A21 -> Other Mfr. Exp | C15: ='Data Sheet'!B21/'Data Sheet'!B$17 -> 0.098008294 | D15: ='Data Sheet'!C21/'Data Sheet'!C$17 -> 0.10331528 | E15: ='Data Sheet'!D21/'Data Sheet'!D$17 -> 0.11977018 | F15: ='Data Sheet'!E21/'Data Sheet'!E$17 -> 0.12210461 | G15: ='Data Sheet'!F21/'Data Sheet'!F$17 -> 0.12739868 | H15: ='Data Sheet'!G21/'Data Sheet'!G$17 -> 0.17009068 | I15: ='Data Sheet'!H21/'Data Sheet'!H$17 -> 0.1794 | J15: ='Data Sheet'!I21/'Data Sheet'!I$17 -> 0.17697013 | ... L15: ='Data Sheet'!K21/'Data Sheet'!K$17 -> 0.18428212
B16: ='Data Sheet'!A22 -> Employee Cost | C16: ='Data Sheet'!B22/'Data Sheet'!B$17 -> 0.55004089 | D16: ='Data Sheet'!C22/'Data Sheet'!C$17 -> 0.55162928 | E16: ='Data Sheet'!D22/'Data Sheet'!D$17 -> 0.54820683 | F16: ='Data Sheet'!E22/'Data Sheet'!E$17 -> 0.56057318 | G16: ='Data Sheet'!F22/'Data Sheet'!F$17 -> 0.5528605 | H16: ='Data Sheet'!G22/'Data Sheet'!G$17 -> 0.52611373 | I16: ='Data Sheet'!H22/'Data Sheet'!H$17 -> 0.53400288 | J16: ='Data Sheet'!I22/'Data Sheet'!I$17 -> 0.53774972 | ... L16: ='Data Sheet'!K22/'Data Sheet'!K$17 -> 0.53239295
B17: ='Data Sheet'!A23 -> Selling and admin | C17: ='Data Sheet'!B23/'Data Sheet'!B$17 -> 0.066935343 | D17: ='Data Sheet'!C23/'Data Sheet'!C$17 -> 0.065015173 | E17: ='Data Sheet'!D23/'Data Sheet'!D$17 -> 0.067166616 | F17: ='Data Sheet'!E23/'Data Sheet'!E$17 -> 0.059201903 | G17: ='Data Sheet'!F23/'Data Sheet'!F$17 -> 0.031789951 | H17: ='Data Sheet'!G23/'Data Sheet'!G$17 -> 0.035391028 | I17: ='Data Sheet'!H23/'Data Sheet'!H$17 -> 0.03611166 | J17: ='Data Sheet'!I23/'Data Sheet'!I$17 -> 0.037125008 | ... L17: ='Data Sheet'!K23/'Data Sheet'!K$17 -> 0.037973692
B18: ='Data Sheet'!A24 -> Other Expenses | C18: ='Data Sheet'!B24/'Data Sheet'!B$17 -> 0.01003154 | D18: ='Data Sheet'!C24/'Data Sheet'!C$17 -> 0.01020958 | E18: ='Data Sheet'!D24/'Data Sheet'!D$17 -> 0.018215906 | F18: ='Data Sheet'!E24/'Data Sheet'!E$17 -> 0.010342435 | G18: ='Data Sheet'!F24/'Data Sheet'!F$17 -> 0.0089477665 | H18: ='Data Sheet'!G24/'Data Sheet'!G$17 -> 0.0084346561 | I18: ='Data Sheet'!H24/'Data Sheet'!H$17 -> 0.0099272997 | J18: ='Data Sheet'!I24/'Data Sheet'!I$17 -> 0.0098262511 | ... L18: ='Data Sheet'!K24/'Data Sheet'!K$17 -> 0.0074391268
B19: ='Data Sheet'!A25 -> Other Income | C19: ='Data Sheet'!B25/'Data Sheet'!B$17 -> 0.04453595 | D19: ='Data Sheet'!C25/'Data Sheet'!C$17 -> 0.046949888 | E19: ='Data Sheet'!D25/'Data Sheet'!D$17 -> 0.034859389 | F19: ='Data Sheet'!E25/'Data Sheet'!E$17 -> 0.030873104 | G19: ='Data Sheet'!F25/'Data Sheet'!F$17 -> 0.021906601 | H19: ='Data Sheet'!G25/'Data Sheet'!G$17 -> 0.018866994 | I19: ='Data Sheet'!H25/'Data Sheet'!H$17 -> 0.01840332 | J19: ='Data Sheet'!I25/'Data Sheet'!I$17 -> 0.030656602 | ... L19: ='Data Sheet'!K25/'Data Sheet'!K$17 -> 0.01697733
B20: ='Data Sheet'!A26 -> Depreciation | C20: ='Data Sheet'!B26/'Data Sheet'!B$17 -> 0.024867122 | D20: ='Data Sheet'!C26/'Data Sheet'!C$17 -> 0.026417288 | E20: ='Data Sheet'!D26/'Data Sheet'!D$17 -> 0.024324161 | F20: ='Data Sheet'!E26/'Data Sheet'!E$17 -> 0.031864392 | G20: ='Data Sheet'!F26/'Data Sheet'!F$17 -> 0.032516522 | H20: ='Data Sheet'!G26/'Data Sheet'!G$17 -> 0.028575891 | I20: ='Data Sheet'!H26/'Data Sheet'!H$17 -> 0.028787125 | J20: ='Data Sheet'!I26/'Data Sheet'!I$17 -> 0.030441856 | ... L20: ='Data Sheet'!K26/'Data Sheet'!K$17 -> 0.027439127
B21: ='Data Sheet'!A27 -> Interest | C21: ='Data Sheet'!B27/'Data Sheet'!B$17 -> 0 | D21: ='Data Sheet'!C27/'Data Sheet'!C$17 -> 0 | E21: ='Data Sheet'!D27/'Data Sheet'!D$17 -> 0 | F21: ='Data Sheet'!E27/'Data Sheet'!E$17 -> 0.0018724323 | G21: ='Data Sheet'!F27/'Data Sheet'!F$17 -> 0.0019408392 | H21: ='Data Sheet'!G27/'Data Sheet'!G$17 -> 0.0016441825 | I21: ='Data Sheet'!H27/'Data Sheet'!H$17 -> 0.0019350399 | J21: ='Data Sheet'!I27/'Data Sheet'!I$17 -> 0.003058502 | ... L21: ='Data Sheet'!K27/'Data Sheet'!K$17 -> 0.0023285754
B22: ='Data Sheet'!A28 -> Profit before tax | C22: ='Data Sheet'!B28/'Data Sheet'!B$17 -> 0.29132352 | D22: ='Data Sheet'!C28/'Data Sheet'!C$17 -> 0.28742804 | E22: ='Data Sheet'!D28/'Data Sheet'!D$17 -> 0.25450257 | F22: ='Data Sheet'!E28/'Data Sheet'!E$17 -> 0.24239187 | G22: ='Data Sheet'!F28/'Data Sheet'!F$17 -> 0.26502906 | H22: ='Data Sheet'!G28/'Data Sheet'!G$17 -> 0.24753167 | I22: ='Data Sheet'!H28/'Data Sheet'!H$17 -> 0.22704014 | J22: ='Data Sheet'!I28/'Data Sheet'!I$17 -> 0.23419015 | ... L22: ='Data Sheet'!K28/'Data Sheet'!K$17 -> 0.2238735
... B25: ='Data Sheet'!A31 -> Dividend Amount | C25: ='Data Sheet'!B31/'Data Sheet'!B$17 -> 0.086028853 | D25: ='Data Sheet'!C31/'Data Sheet'!C$17 -> 0.13422194 | E25: ='Data Sheet'!D31/'Data Sheet'!D$17 -> 0.11155125 | F25: ='Data Sheet'!E31/'Data Sheet'!E$17 -> 0.081803262 | G25: ='Data Sheet'!F31/'Data Sheet'!F$17 -> 0.11415718 | H25: ='Data Sheet'!G31/'Data Sheet'!G$17 -> 0.10693434 | I25: ='Data Sheet'!H31/'Data Sheet'!H$17 -> 0.095860786 | J25: ='Data Sheet'!I31/'Data Sheet'!I$17 -> 0.12398777 | ... L25: ='Data Sheet'!K31/'Data Sheet'!K$17 -> 0.10876238
B26: ='Data Sheet'!A34 -> EBITDA | C26: ='Data Sheet'!B34/'Data Sheet'!B$17 -> 0.31619064 | D26: ='Data Sheet'!C34/'Data Sheet'!C$17 -> 0.31384532 | E26: ='Data Sheet'!D34/'Data Sheet'!D$17 -> 0.27875416 | F26: ='Data Sheet'!E34/'Data Sheet'!E$17 -> 0.27563305 | G26: ='Data Sheet'!F34/'Data Sheet'!F$17 -> 0.29876981 | H26: ='Data Sheet'!G34/'Data Sheet'!G$17 -> 0.27745579 | I26: ='Data Sheet'!H34/'Data Sheet'!H$17 -> 0.25767373 | J26: ='Data Sheet'!I34/'Data Sheet'!I$17 -> 0.26759289 | ... L26: ='Data Sheet'!K34/'Data Sheet'!K$17 -> 0.25345088
B28: ="Common Size Income Statement"&" "&"- "&'Data Sheet'!$B$1 -> Common Size Income Statement - INFOSYS LTD
B30: Particulars | C30: ='Data Sheet'!B16 -> 42825 | D30: ='Data Sheet'!C16 -> 43190 | E30: ='Data Sheet'!D16 -> 43555 | F30: ='Data Sheet'!E16 -> 43921 | G30: ='Data Sheet'!F16 -> 44286 | H30: ='Data Sheet'!G16 -> 44651 | I30: ='Data Sheet'!H16 -> 45016 | J30: ='Data Sheet'!I16 -> 45382 | ... L30: ='Data Sheet'!K16 -> 46112
B32: Total Liabilities | C32: ='Data Sheet'!B61/'Data Sheet'!B$61 -> 1 | D32: ='Data Sheet'!C61/'Data Sheet'!C$61 -> 1 | E32: ='Data Sheet'!D61/'Data Sheet'!D$61 -> 1 | F32: ='Data Sheet'!E61/'Data Sheet'!E$61 -> 1 | G32: ='Data Sheet'!F61/'Data Sheet'!F$61 -> 1 | H32: ='Data Sheet'!G61/'Data Sheet'!G$61 -> 1 | I32: ='Data Sheet'!H61/'Data Sheet'!H$61 -> 1 | J32: ='Data Sheet'!I61/'Data Sheet'!I$61 -> 1 | ... L32: ='Data Sheet'!K61/'Data Sheet'!K$61 -> 1
B33: ='Data Sheet'!A57 -> Equity Share Capital | C33: ='Data Sheet'!B57/'Data Sheet'!B$61 -> 0.013758599 | D33: ='Data Sheet'!C57/'Data Sheet'!C$61 -> 0.013711578 | E33: ='Data Sheet'!D57/'Data Sheet'!D$61 -> 0.025813052 | F33: ='Data Sheet'!E57/'Data Sheet'!E$61 -> 0.023115468 | G33: ='Data Sheet'!F57/'Data Sheet'!F$61 -> 0.019756118 | H33: ='Data Sheet'!G57/'Data Sheet'!G$61 -> 0.017973254 | I33: ='Data Sheet'!H57/'Data Sheet'!H$61 -> 0.01660567 | J33: ='Data Sheet'!I57/'Data Sheet'!I$61 -> 0.015225702 | ... L33: ='Data Sheet'!K57/'Data Sheet'!K$61 -> 0.013118324
B34: ='Data Sheet'!A58 -> Reserves | C34: ='Data Sheet'!B58/'Data Sheet'!B$61 -> 0.8158705 | D34: ='Data Sheet'!C58/'Data Sheet'!C$61 -> 0.80448399 | E34: ='Data Sheet'!D58/'Data Sheet'!D$61 -> 0.74677039 | F34: ='Data Sheet'!E58/'Data Sheet'!E$61 -> 0.68984749 | G34: ='Data Sheet'!F58/'Data Sheet'!F$61 -> 0.69041307 | H34: ='Data Sheet'!G58/'Data Sheet'!G$61 -> 0.627539 | I34: ='Data Sheet'!H58/'Data Sheet'!H$61 -> 0.58860638 | J34: ='Data Sheet'!I58/'Data Sheet'!I$61 -> 0.6325908 | ... L34: ='Data Sheet'!K58/'Data Sheet'!K$61 -> 0.58869128
B35: ='Data Sheet'!A59 -> Borrowings | C35: ='Data Sheet'!B59/'Data Sheet'!B$61 -> 0 | D35: ='Data Sheet'!C59/'Data Sheet'!C$61 -> 0 | E35: ='Data Sheet'!D59/'Data Sheet'!D$61 -> 0 | F35: ='Data Sheet'!E59/'Data Sheet'!E$61 -> 0.05046841 | G35: ='Data Sheet'!F59/'Data Sheet'!F$61 -> 0.049529816 | H35: ='Data Sheet'!G59/'Data Sheet'!G$61 -> 0.046894945 | I35: ='Data Sheet'!H59/'Data Sheet'!H$61 -> 0.066607275 | J35: ='Data Sheet'!I59/'Data Sheet'!I$61 -> 0.061454198 | ... L35: ='Data Sheet'!K59/'Data Sheet'!K$61 -> 0.059473193
B36: ='Data Sheet'!A60 -> Other Liabilities | C36: ='Data Sheet'!B60/'Data Sheet'!B$61 -> 0.1703709 | D36: ='Data Sheet'!C60/'Data Sheet'!C$61 -> 0.18180443 | E36: ='Data Sheet'!D60/'Data Sheet'!D$61 -> 0.22741655 | F36: ='Data Sheet'!E60/'Data Sheet'!E$61 -> 0.23656863 | G36: ='Data Sheet'!F60/'Data Sheet'!F$61 -> 0.24030099 | H36: ='Data Sheet'!G60/'Data Sheet'!G$61 -> 0.3075928 | I36: ='Data Sheet'!H60/'Data Sheet'!H$61 -> 0.32818068 | J36: ='Data Sheet'!I60/'Data Sheet'!I$61 -> 0.2907293 | ... L36: ='Data Sheet'!K60/'Data Sheet'!K$61 -> 0.3387172
B38: Total Assets | C38: ='Data Sheet'!B76/'Data Sheet'!B$61 -> 1 | D38: ='Data Sheet'!C76/'Data Sheet'!C$61 -> 1 | E38: ='Data Sheet'!D76/'Data Sheet'!D$61 -> 1 | F38: ='Data Sheet'!E76/'Data Sheet'!E$61 -> 1 | G38: ='Data Sheet'!F76/'Data Sheet'!F$61 -> 1 | H38: ='Data Sheet'!G76/'Data Sheet'!G$61 -> 1 | I38: ='Data Sheet'!H76/'Data Sheet'!H$61 -> 1 | J38: ='Data Sheet'!I76/'Data Sheet'!I$61 -> 1 | ... L38: ='Data Sheet'!K76/'Data Sheet'!K$61 -> 1
B39: ='Data Sheet'!A62 -> Net Block | C39: ='Data Sheet'!B62/'Data Sheet'!B$76 -> 0.17052725 | D39: ='Data Sheet'!C62/'Data Sheet'!C$76 -> 0.1584645 | E39: ='Data Sheet'!D62/'Data Sheet'!D$76 -> 0.18687698 | F39: ='Data Sheet'!E62/'Data Sheet'!E$76 -> 0.25913943 | G39: ='Data Sheet'!F62/'Data Sheet'!F$76 -> 0.23723154 | H39: ='Data Sheet'!G62/'Data Sheet'!G$76 -> 0.22102477 | I39: ='Data Sheet'!H62/'Data Sheet'!H$76 -> 0.23455809 | J39: ='Data Sheet'!I62/'Data Sheet'!I$76 -> 0.20307308 | ... L39: ='Data Sheet'!K62/'Data Sheet'!K$76 -> 0.21887639
B40: ='Data Sheet'!A63 -> Capital Work in Progress | C40: ='Data Sheet'!B63/'Data Sheet'!B$76 -> 0.01641651 | D40: ='Data Sheet'!C63/'Data Sheet'!C$76 -> 0.020239701 | E40: ='Data Sheet'!D63/'Data Sheet'!D$76 -> 0.016510837 | F40: ='Data Sheet'!E63/'Data Sheet'!E$76 -> 0.010392157 | G40: ='Data Sheet'!F63/'Data Sheet'!F$76 -> 0.0085758667 | H40: ='Data Sheet'!G63/'Data Sheet'!G$76 -> 0.0035638102 | I40: ='Data Sheet'!H63/'Data Sheet'!H$76 -> 0.0023114707 | J40: ='Data Sheet'!I63/'Data Sheet'!I$76 -> 0.002154095 | ... L40: ='Data Sheet'!K63/'Data Sheet'!K$76 -> 0.0034092088
B41: ='Data Sheet'!A64 -> Investments | C41: ='Data Sheet'!B64/'Data Sheet'!B$76 -> 0.19751527 | D41: ='Data Sheet'!C64/'Data Sheet'!C$76 -> 0.15328486 | E41: ='Data Sheet'!D64/'Data Sheet'!D$76 -> 0.13395427 | F41: ='Data Sheet'!E64/'Data Sheet'!E$76 -> 0.09577342 | G41: ='Data Sheet'!F64/'Data Sheet'!F$76 -> 0.13212602 | H41: ='Data Sheet'!G64/'Data Sheet'!G$76 -> 0.17411269 | I41: ='Data Sheet'!H64/'Data Sheet'!H$76 -> 0.15632926 | J41: ='Data Sheet'!I64/'Data Sheet'!I$76 -> 0.18102485 | ... L41: ='Data Sheet'!K64/'Data Sheet'!K$76 -> 0.14181271
B42: ='Data Sheet'!A65 -> Other Assets | C42: ='Data Sheet'!B74/'Data Sheet'!B$76 -> 0.19524222 | D42: ='Data Sheet'!C74/'Data Sheet'!C$76 -> 0.25263078 | E42: ='Data Sheet'!D74/'Data Sheet'!D$76 -> 0.2535151 | F42: ='Data Sheet'!E74/'Data Sheet'!E$76 -> 0.2301634 | G42: ='Data Sheet'!F74/'Data Sheet'!F$76 -> 0.21273172 | H42: ='Data Sheet'!G74/'Data Sheet'!G$76 -> 0.25716831 | I42: ='Data Sheet'!H74/'Data Sheet'!H$76 -> 0.30504992 | J42: ='Data Sheet'!I74/'Data Sheet'!I$76 -> 0.28306867 | ... L42: ='Data Sheet'!K74/'Data Sheet'!K$76 -> 0.26364332
B43: ='Data Sheet'!A67 -> Receivables | C43: ='Data Sheet'!B67/'Data Sheet'!B$76 -> 0.14819358 | D43: ='Data Sheet'!C67/'Data Sheet'!C$76 -> 0.16562276 | E43: ='Data Sheet'!D67/'Data Sheet'!D$76 -> 0.17637333 | F43: ='Data Sheet'!E67/'Data Sheet'!E$76 -> 0.20138344 | G43: ='Data Sheet'!F67/'Data Sheet'!F$76 -> 0.17946071 | H43: ='Data Sheet'!G67/'Data Sheet'!G$76 -> 0.19445039 | I43: ='Data Sheet'!H67/'Data Sheet'!H$76 -> 0.20405149 | J43: ='Data Sheet'!I67/'Data Sheet'!I$76 -> 0.22197471 | ... L43: ='Data Sheet'!K67/'Data Sheet'!K$76 -> 0.22836514
B44: ='Data Sheet'!A68 -> Inventory | C44: ='Data Sheet'!B68/'Data Sheet'!B$76 -> 0 | D44: ='Data Sheet'!C68/'Data Sheet'!C$76 -> 0 | E44: ='Data Sheet'!D68/'Data Sheet'!D$76 -> 0 | F44: ='Data Sheet'!E68/'Data Sheet'!E$76 -> 0 | G44: ='Data Sheet'!F68/'Data Sheet'!F$76 -> 0 | H44: ='Data Sheet'!G68/'Data Sheet'!G$76 -> 0 | I44: ='Data Sheet'!H68/'Data Sheet'!H$76 -> 0 | J44: ='Data Sheet'!I68/'Data Sheet'!I$76 -> 0 | ... L44: ='Data Sheet'!K68/'Data Sheet'!K$76 -> 0
B45: ='Data Sheet'!A69 -> Cash & Bank | C45: ='Data Sheet'!B69/'Data Sheet'!B$76 -> 0.27210516 | D45: ='Data Sheet'!C69/'Data Sheet'!C$76 -> 0.2497574 | E45: ='Data Sheet'!D69/'Data Sheet'!D$76 -> 0.23276949 | F45: ='Data Sheet'!E69/'Data Sheet'!E$76 -> 0.20314815 | G45: ='Data Sheet'!F69/'Data Sheet'!F$76 -> 0.22987415 | H45: ='Data Sheet'!G69/'Data Sheet'!G$76 -> 0.14968003 | I45: ='Data Sheet'!H69/'Data Sheet'!H$76 -> 0.097699766 | J45: ='Data Sheet'!I69/'Data Sheet'!I$76 -> 0.1087046 | ... L45: ='Data Sheet'!K69/'Data Sheet'!K$76 -> 0.14389324

Sheet Ratio Analysis
B2: ="Ratio Analysis - "&'Data Sheet'!B1 -> Ratio Analysis - INFOSYS LTD
B3: Years | C3: ='Data Sheet'!B16 -> 42825 | D3: ='Data Sheet'!C16 -> 43190 | E3: ='Data Sheet'!D16 -> 43555 | F3: ='Data Sheet'!E16 -> 43921 | G3: ='Data Sheet'!F16 -> 44286 | H3: ='Data Sheet'!G16 -> 44651 | I3: ='Data Sheet'!H16 -> 45016 | J3: ='Data Sheet'!I16 -> 45382 | ... L3: ='Data Sheet'!K16 -> 46112 | N3: Trend | O3: Mean | P3: Median
B5: SalesGrowth | C5: =IFERROR(HistoricalFS!C7,0) -> - | D5: =IFERROR(HistoricalFS!D7,0) -> 0.029758776 | E5: =IFERROR(HistoricalFS!E7,0) -> 0.1723292 | F5: =IFERROR(HistoricalFS!F7,0) -> 0.098167523 | G5: =IFERROR(HistoricalFS!G7,0) -> 0.10662951 | H5: =IFERROR(HistoricalFS!H7,0) -> 0.21069552 | I5: =IFERROR(HistoricalFS!I7,0) -> 0.20655864 | J5: =IFERROR(HistoricalFS!J7,0) -> 0.047033734 | ... L5: =IFERROR(HistoricalFS!L7,0) -> 0.096079514 | O5: =IFERROR(AVERAGE(D5:L5),0) -> 0.11421132 | P5: =IFERROR(MEDIAN(C5:L5),0) -> 0.098167523
B6: EBITDA Growth | D6: =IFERROR(HistoricalFS!D18/HistoricalFS!C18-1,0) -> 0.01171791 | E6: =IFERROR(HistoricalFS!E18/HistoricalFS!D18-1,0) -> 0.071618319 | F6: =IFERROR(HistoricalFS!F18/HistoricalFS!E18-1,0) -> 0.10396629 | G6: =IFERROR(HistoricalFS!G18/HistoricalFS!F18-1,0) -> 0.25248125 | H6: =IFERROR(HistoricalFS!H18/HistoricalFS!G18-1,0) -> 0.12915486 | I6: =IFERROR(HistoricalFS!I18/HistoricalFS!H18-1,0) -> 0.11555683 | J6: =IFERROR(HistoricalFS!J18/HistoricalFS!I18-1,0) -> 0.03686308 | K6: =IFERROR(HistoricalFS!K18/HistoricalFS!J18-1,0) -> 0.077172272 | L6: =IFERROR(HistoricalFS!L18/HistoricalFS!K18-1,0) -> 0.077581813 | O6: =IFERROR(AVERAGE(D6:L6),0) -> 0.097345847 | P6: =IFERROR(MEDIAN(C6:L6),0) -> 0.077581813
B7: EBIT Growth | D7: =IFERROR(HistoricalFS!D27/HistoricalFS!C27-1,0) -> 0.0034317496 | E7: =IFERROR(HistoricalFS!E27/HistoricalFS!D27-1,0) -> 0.070758889 | F7: =IFERROR(HistoricalFS!F27/HistoricalFS!E27-1,0) -> 0.057547222 | G7: =IFERROR(HistoricalFS!G27/HistoricalFS!F27-1,0) -> 0.27197459 | H7: =IFERROR(HistoricalFS!H27/HistoricalFS!G27-1,0) -> 0.13869898 | I7: =IFERROR(HistoricalFS!I27/HistoricalFS!H27-1,0) -> 0.10088082 | J7: =IFERROR(HistoricalFS!J27/HistoricalFS!I27-1,0) -> 0.021423206 | K7: =IFERROR(HistoricalFS!K27/HistoricalFS!J27-1,0) -> 0.087316558 | L7: =IFERROR(HistoricalFS!L27/HistoricalFS!K27-1,0) -> 0.086861915 | O7: =IFERROR(AVERAGE(D7:L7),0) -> 0.093210437 | P7: =IFERROR(MEDIAN(C7:L7),0) -> 0.086861915
B8: Net Profit Growth | D8: =IFERROR((HistoricalFS!D33/ABS(HistoricalFS!C33))-1,0) -> 0.125188 | E8: =IFERROR(HistoricalFS!E33/HistoricalFS!D33-1,0) -> -0.014939456 | F8: =IFERROR(HistoricalFS!F33/HistoricalFS!E33-1,0) -> 0.10440613 | G8: =IFERROR(HistoricalFS!G33/HistoricalFS!F33-1,0) -> 0.24472391 | H8: =IFERROR(HistoricalFS!H33/HistoricalFS!G33-1,0) -> 0.15265358 | I8: =IFERROR(HistoricalFS!I33/HistoricalFS!H33-1,0) -> 0.078383961 | J8: =IFERROR(HistoricalFS!J33/HistoricalFS!I33-1,0) -> 0.0060727799 | K8: =IFERROR(HistoricalFS!K33/HistoricalFS!J33-1,0) -> 0.074894368 | L8: =IFERROR(HistoricalFS!L33/HistoricalFS!K33-1,0) -> 0.14215983 | O8: =IFERROR(AVERAGE(D8:L8),0) -> 0.10150479 | P8: =IFERROR(MEDIAN(C8:L8),0) -> 0.10440613
B9: Dividend Growth | D9: =IFERROR(HistoricalFS!D41/HistoricalFS!C41-1,0) -> 0.68963897 | E9: =IFERROR(HistoricalFS!E41/HistoricalFS!D41-1,0) -> -0.02583858 | F9: =IFERROR(HistoricalFS!F41/HistoricalFS!E41-1,0) -> -0.17390646 | G9: =IFERROR(HistoricalFS!G41/HistoricalFS!F41-1,0) -> 0.54369512 | H9: =IFERROR(HistoricalFS!H41/HistoricalFS!G41-1,0) -> 0.14865158 | I9: =IFERROR(HistoricalFS!I41/HistoricalFS!H41-1,0) -> 0.096761529 | J9: =IFERROR(HistoricalFS!J41/HistoricalFS!I41-1,0) -> 0.35349861 | K9: =IFERROR(HistoricalFS!K41/HistoricalFS!J41-1,0) -> -0.064855345 | L9: =IFERROR(HistoricalFS!L41/HistoricalFS!K41-1,0) -> 0.116149 | O9: =IFERROR(AVERAGE(D9:L9),0) -> 0.18708827 | P9: =IFERROR(MEDIAN(C9:L9),0) -> 0.116149
B11: Gross Margin | C11: =IFERROR(HistoricalFS!C13,0) -> 0.34862158 | D11: =IFERROR(HistoricalFS!D13,0) -> 0.34212019 | E11: =IFERROR(HistoricalFS!E13,0) -> 0.32934986 | F11: =IFERROR(HistoricalFS!F13,0) -> 0.31479993 | G11: =IFERROR(HistoricalFS!G13,0) -> 0.31831754 | H11: =IFERROR(HistoricalFS!H13,0) -> 0.30271043 | I11: =IFERROR(HistoricalFS!I13,0) -> 0.28539794 | J11: =IFERROR(HistoricalFS!J13,0) -> 0.28398516 | ... L11: =IFERROR(HistoricalFS!L13,0) -> 0.28207669 | O11: =IFERROR(AVERAGE(C11:L11),0) -> 0.309209 | P11: =IFERROR(MEDIAN(C11:L11),0) -> 0.30875518
B12: EBITDA Margin | C12: =IFERROR(HistoricalFS!C19,0) -> 0.27165469 | D12: =IFERROR(HistoricalFS!D19,0) -> 0.26689544 | E12: =IFERROR(HistoricalFS!E19,0) -> 0.24396734 | F12: =IFERROR(HistoricalFS!F19,0) -> 0.24525559 | G12: =IFERROR(HistoricalFS!G19,0) -> 0.27757982 | H12: =IFERROR(HistoricalFS!H19,0) -> 0.25888475 | I12: =IFERROR(HistoricalFS!I19,0) -> 0.23935898 | J12: =IFERROR(HistoricalFS!J19,0) -> 0.2370339 | ... L12: =IFERROR(HistoricalFS!L19,0) -> 0.23666387 | O12: =IFERROR(AVERAGE(C12:L12),0) -> 0.25180208 | P12: =IFERROR(MEDIAN(C12:L12),0) -> 0.24461146
B13: EBIT Margin | C13: =IFERROR((HistoricalFS!C18-HistoricalFS!C24)/HistoricalFS!C6,0) -> 0.24678757 | D13: =IFERROR((HistoricalFS!D18-HistoricalFS!D24)/HistoricalFS!D6,0) -> 0.24047815 | E13: =IFERROR((HistoricalFS!E18-HistoricalFS!E24)/HistoricalFS!E6,0) -> 0.21964318 | F13: =IFERROR((HistoricalFS!F18-HistoricalFS!F24)/HistoricalFS!F6,0) -> 0.2133912 | G13: =IFERROR((HistoricalFS!G18-HistoricalFS!G24)/HistoricalFS!G6,0) -> 0.2450633 | H13: =IFERROR((HistoricalFS!H18-HistoricalFS!H24)/HistoricalFS!H6,0) -> 0.23030886 | I13: =IFERROR((HistoricalFS!I18-HistoricalFS!I24)/HistoricalFS!I6,0) -> 0.21057186 | J13: =IFERROR((HistoricalFS!J18-HistoricalFS!J24)/HistoricalFS!J6,0) -> 0.20659205 | ... L13: =IFERROR((HistoricalFS!L18-HistoricalFS!L24)/HistoricalFS!L6,0) -> 0.20922474 | O13: =IFERROR(AVERAGE(C13:L13),0) -> 0.2233264 | P13: =IFERROR(MEDIAN(C13:L13),0) -> 0.21651719
B14: EBT Margin | C14: =IFERROR(HistoricalFS!C28,0) -> 0.24678757 | D14: =IFERROR(HistoricalFS!D28,0) -> 0.24047815 | E14: =IFERROR(HistoricalFS!E28,0) -> 0.21964318 | F14: =IFERROR(HistoricalFS!F28,0) -> 0.21151876 | G14: =IFERROR(HistoricalFS!G28,0) -> 0.24312246 | H14: =IFERROR(HistoricalFS!H28,0) -> 0.22866468 | I14: =IFERROR(HistoricalFS!I28,0) -> 0.20863682 | J14: =IFERROR(HistoricalFS!J28,0) -> 0.20353355 | ... L14: =IFERROR(HistoricalFS!L28,0) -> 0.20689617 | O14: =IFERROR(AVERAGE(C14:L14),0) -> 0.22179322 | P14: =IFERROR(MEDIAN(C14:L14),0) -> 0.21558097
B15: Net Profit Margin | C15: =IFERROR(HistoricalFS!C34,0) -> 0.16504585 | D15: =IFERROR(HistoricalFS!D34,0) -> 0.18034089 | E15: =IFERROR(HistoricalFS!E34,0) -> 0.15153311 | F15: =IFERROR(HistoricalFS!F34,0) -> 0.15239396 | G15: =IFERROR(HistoricalFS!G34,0) -> 0.17141094 | H15: =IFERROR(HistoricalFS!H34,0) -> 0.16319333 | I15: =IFERROR(HistoricalFS!I34,0) -> 0.14585704 | J15: =IFERROR(HistoricalFS!J34,0) -> 0.14015097 | ... L15: =IFERROR(HistoricalFS!L34,0) -> 0.14800448 | O15: =IFERROR(AVERAGE(C15:L15),0) -> 0.15599638 | P15: =IFERROR(MEDIAN(C15:L15),0) -> 0.15196354
B17: SalesExpenses%Sales | C17: =IFERROR(HistoricalFS!C16,0) -> 0.076966883 | D17: =IFERROR(HistoricalFS!D16,0) -> 0.075224753 | E17: =IFERROR(HistoricalFS!E16,0) -> 0.085382522 | F17: =IFERROR(HistoricalFS!F16,0) -> 0.069544338 | G17: =IFERROR(HistoricalFS!G16,0) -> 0.040737718 | H17: =IFERROR(HistoricalFS!H16,0) -> 0.043825684 | I17: =IFERROR(HistoricalFS!I16,0) -> 0.04603896 | J17: =IFERROR(HistoricalFS!J16,0) -> 0.046951259 | ... L17: =IFERROR(HistoricalFS!L16,0) -> 0.045412818 | O17: =IFERROR(AVERAGE(C17:L17),0) -> 0.057406923 | P17: =IFERROR(MEDIAN(C17:L17),0) -> 0.046495109
B18: Depreciation%Sales | C18: =IFERROR(HistoricalFS!C25,0) -> 0.024867122 | D18: =IFERROR(HistoricalFS!D25,0) -> 0.026417288 | E18: =IFERROR(HistoricalFS!E25,0) -> 0.024324161 | F18: =IFERROR(HistoricalFS!F25,0) -> 0.031864392 | G18: =IFERROR(HistoricalFS!G25,0) -> 0.032516522 | H18: =IFERROR(HistoricalFS!H25,0) -> 0.028575891 | I18: =IFERROR(HistoricalFS!I25,0) -> 0.028787125 | J18: =IFERROR(HistoricalFS!J25,0) -> 0.030441856 | ... L18: =IFERROR(HistoricalFS!L25,0) -> 0.027439127 | O18: =IFERROR(AVERAGE(C18:L18),0) -> 0.028475677 | P18: =IFERROR(MEDIAN(C18:L18),0) -> 0.028681508
B19: OperatingIncome%Sales | C19: =C13 -> 0.24678757 | D19: =D13 -> 0.24047815 | E19: =E13 -> 0.21964318 | F19: =F13 -> 0.2133912 | G19: =G13 -> 0.2450633 | H19: =H13 -> 0.23030886 | I19: =I13 -> 0.21057186 | J19: =J13 -> 0.20659205 | ... L19: =L13 -> 0.20922474 | O19: =IFERROR(AVERAGE(C19:L19),0) -> 0.2233264 | P19: =IFERROR(MEDIAN(C19:L19),0) -> 0.21651719
B21: Return on Capital Employed | C21: =IFERROR((HistoricalFS!C18-HistoricalFS!C24)/(SUM(HistoricalFS!C47:C49)),0) -> 0.24500594 | D21: =IFERROR((HistoricalFS!D18-HistoricalFS!D24)/(SUM(HistoricalFS!D47:D49)),0) -> 0.26121713 | E21: =IFERROR((HistoricalFS!E18-HistoricalFS!E24)/(SUM(HistoricalFS!E47:E49)),0) -> 0.27959291 | F21: =IFERROR((HistoricalFS!F18-HistoricalFS!F24)/(SUM(HistoricalFS!F47:F49)),0) -> 0.27644365 | G21: =IFERROR((HistoricalFS!G18-HistoricalFS!G24)/(SUM(HistoricalFS!G47:G49)),0) -> 0.30145943 | H21: =IFERROR((HistoricalFS!H18-HistoricalFS!H24)/(SUM(HistoricalFS!H47:H49)),0) -> 0.34661734 | I21: =IFERROR((HistoricalFS!I18-HistoricalFS!I24)/(SUM(HistoricalFS!I47:I49)),0) -> 0.3692089 | J21: =IFERROR((HistoricalFS!J18-HistoricalFS!J24)/(SUM(HistoricalFS!J47:J49)),0) -> 0.32906971 | ... L21: =IFERROR((HistoricalFS!L18-HistoricalFS!L24)/(SUM(HistoricalFS!L47:L49)),0) -> 0.36635041 | O21: =IFERROR(AVERAGE(C21:L21),0) -> 0.31058223 | P21: =IFERROR(MEDIAN(C21:L21),0) -> 0.31526457
B22: Retained Earnings% | C22: =IFERROR(HistoricalFS!C44,0) -> 0.47875785 | D22: =IFERROR(HistoricalFS!D44,0) -> 0.25573203 | E22: =IFERROR(HistoricalFS!E44,0) -> 0.26384898 | F22: =IFERROR(HistoricalFS!F44,0) -> 0.46321191 | G22: =IFERROR(HistoricalFS!G44,0) -> 0.33401463 | H22: =IFERROR(HistoricalFS!H44,0) -> 0.3447383 | I22: =IFERROR(HistoricalFS!I44,0) -> 0.34277573 | J22: =IFERROR(HistoricalFS!J44,0) -> 0.11532711 | ... L22: =IFERROR(HistoricalFS!L44,0) -> 0.26514126 | O22: =IFERROR(AVERAGE(C22:L22),0) -> 0.30934485 | P22: =IFERROR(MEDIAN(C22:L22),0) -> 0.29957795
B23: Return on Equity% | C23: =IFERROR(HistoricalFS!C33/SUM(HistoricalFS!C47:C48),0) -> 0.16385434 | D23: =IFERROR(HistoricalFS!D33/SUM(HistoricalFS!D47:D48),0) -> 0.1958936 | E23: =IFERROR(HistoricalFS!E33/SUM(HistoricalFS!E47:E48),0) -> 0.19289278 | F23: =IFERROR(HistoricalFS!F33/SUM(HistoricalFS!F47:F48),0) -> 0.21139801 | G23: =IFERROR(HistoricalFS!G33/SUM(HistoricalFS!G47:G48),0) -> 0.22556352 | H23: =IFERROR(HistoricalFS!H33/SUM(HistoricalFS!H47:H48),0) -> 0.26345056 | I23: =IFERROR(HistoricalFS!I33/SUM(HistoricalFS!I47:I48),0) -> 0.28388611 | J23: =IFERROR(HistoricalFS!J33/SUM(HistoricalFS!J47:J48),0) -> 0.24441645 | ... L23: =IFERROR(HistoricalFS!L33/SUM(HistoricalFS!L47:L48),0) -> 0.284765 | O23: =IFERROR(AVERAGE(C23:L23),0) -> 0.23077242 | P23: =IFERROR(MEDIAN(C23:L23),0) -> 0.23358369
B24: Self Sustained Growth Rate | C24: =IFERROR(C22*C23,0) -> 0.078446551 | D24: =IFERROR(D22*D23,0) -> 0.050096268 | E24: =IFERROR(E22*E23,0) -> 0.050894562 | F24: =IFERROR(F22*F23,0) -> 0.097922078 | G24: =IFERROR(G22*G23,0) -> 0.075341515 | H24: =IFERROR(H22*H23,0) -> 0.0908215 | I24: =IFERROR(I22*I23,0) -> 0.097309268 | J24: =IFERROR(J22*J23,0) -> 0.028187843 | ... L24: =IFERROR(L22*L23,0) -> 0.075502951 | O24: =IFERROR(AVERAGE(C24:L24),0) -> 0.070006742 | P24: =IFERROR(MEDIAN(C24:L24),0) -> 0.075422233
B25: Interest Coverage Ratio | C25: =IFERROR(((HistoricalFS!C18-HistoricalFS!C24)/HistoricalFS!C21),"NM") -> NM | D25: =IFERROR(((HistoricalFS!D18-HistoricalFS!D24)/HistoricalFS!D21),"NM") -> NM | E25: =IFERROR(((HistoricalFS!E18-HistoricalFS!E24)/HistoricalFS!E21),"NM") -> NM | F25: =((HistoricalFS!F18-HistoricalFS!F24)/HistoricalFS!F21) -> 113.96471 | G25: =((HistoricalFS!G18-HistoricalFS!G24)/HistoricalFS!G21) -> 126.26667 | H25: =((HistoricalFS!H18-HistoricalFS!H24)/HistoricalFS!H21) -> 140.075 | I25: =((HistoricalFS!I18-HistoricalFS!I24)/HistoricalFS!I21) -> 108.82042 | J25: =((HistoricalFS!J18-HistoricalFS!J24)/HistoricalFS!J21) -> 67.546809 | K25: =((HistoricalFS!K18-HistoricalFS!K24)/HistoricalFS!K21) -> 82.75 | L25: =((HistoricalFS!L18-HistoricalFS!L24)/HistoricalFS!L21) -> 89.850962 | O25: =IFERROR(AVERAGE(C25:L25),0) -> 104.18208 | P25: =IFERROR(MEDIAN(C25:L25),0) -> 108.82042
B27: Debtor Turnover Ratio | C27: =IFERROR(HistoricalFS!C6/HistoricalFS!C59,0) -> 5.557864 | D27: =IFERROR(HistoricalFS!D6/HistoricalFS!D59,0) -> 5.3661543 | E27: =IFERROR(HistoricalFS!E6/HistoricalFS!E59,0) -> 5.5759763 | F27: =IFERROR(HistoricalFS!F6/HistoricalFS!F59,0) -> 4.9110726 | G27: =IFERROR(HistoricalFS!G6/HistoricalFS!G59,0) -> 5.207422 | H27: =IFERROR(HistoricalFS!H6/HistoricalFS!H59,0) -> 5.3591065 | I27: =IFERROR(HistoricalFS!I6/HistoricalFS!I59,0) -> 5.7727738 | J27: =IFERROR(HistoricalFS!J6/HistoricalFS!J59,0) -> 5.0895903 | ... L27: =IFERROR(HistoricalFS!L6/HistoricalFS!L59,0) -> 5.0703866 | O27: =IFERROR(AVERAGE(C27:L27),0) -> 5.3141427 | P27: =IFERROR(MEDIAN(C27:L27),0) -> 5.2950934
B28: Creditor Turnover Ratio (Trade Payables) | C28: =IFERROR(HistoricalFS!C6/'Raw FS'!C10,0) -> 186.6049 | D28: =IFERROR(HistoricalFS!D6/'Raw FS'!D10,0) -> 101.61671 | E28: =IFERROR(HistoricalFS!E6/'Raw FS'!E10,0) -> 49.954683 | F28: =IFERROR(HistoricalFS!F6/'Raw FS'!F10,0) -> 31.834151 | G28: =IFERROR(HistoricalFS!G6/'Raw FS'!G10,0) -> 37.985633 | H28: =IFERROR(HistoricalFS!H6/'Raw FS'!H10,0) -> 29.424528 | I28: =IFERROR(HistoricalFS!I6/'Raw FS'!I10,0) -> 37.973351 | J28: =IFERROR(HistoricalFS!J6/'Raw FS'!J10,0) -> 38.844793 | ... L28: =IFERROR(HistoricalFS!L6/'Raw FS'!L10,0) -> 37.658094 | O28: =IFERROR(AVERAGE(C28:L28),0) -> 59.10395 | P28: =IFERROR(MEDIAN(C28:L28),0) -> 38.415213
B29: Inventory Turnover | C29: =IFERROR(HistoricalFS!C6/HistoricalFS!C60,0) -> 0 | D29: =IFERROR(HistoricalFS!D6/HistoricalFS!D60,0) -> 0 | E29: =IFERROR(HistoricalFS!E6/HistoricalFS!E60,0) -> 0 | F29: =IFERROR(HistoricalFS!F6/HistoricalFS!F60,0) -> 0 | G29: =IFERROR(HistoricalFS!G6/HistoricalFS!G60,0) -> 0 | H29: =IFERROR(HistoricalFS!H6/HistoricalFS!H60,0) -> 0 | I29: =IFERROR(HistoricalFS!I6/HistoricalFS!I60,0) -> 0 | J29: =IFERROR(HistoricalFS!J6/HistoricalFS!J60,0) -> 0 | ... L29: =IFERROR(HistoricalFS!L6/HistoricalFS!L60,0) -> 0 | O29: =IFERROR(AVERAGE(C29:L29),0) -> 0 | P29: =IFERROR(MEDIAN(C29:L29),0) -> 0
B30: Fixed Asset Turnover | C30: =IFERROR(HistoricalFS!C6/HistoricalFS!C53,0) -> 4.8299598 | D30: =IFERROR(HistoricalFS!D6/HistoricalFS!D53,0) -> 5.6085573 | E30: =IFERROR(HistoricalFS!E6/HistoricalFS!E53,0) -> 5.2625716 | F30: =IFERROR(HistoricalFS!F6/HistoricalFS!F53,0) -> 3.8165118 | G30: =IFERROR(HistoricalFS!G6/HistoricalFS!G53,0) -> 3.939306 | H30: =IFERROR(HistoricalFS!H6/HistoricalFS!H53,0) -> 4.7147674 | I30: =IFERROR(HistoricalFS!I6/HistoricalFS!I53,0) -> 5.0219675 | J30: =IFERROR(HistoricalFS!J6/HistoricalFS!J53,0) -> 5.5633191 | ... L30: =IFERROR(HistoricalFS!L6/HistoricalFS!L53,0) -> 5.2901984 | O30: =IFERROR(AVERAGE(C30:L30),0) -> 4.9311524 | P30: =IFERROR(MEDIAN(C30:L30),0) -> 5.1422696
B31: Equity Turnover Ratio | C31: =IFERROR(HistoricalFS!C6/SUM(HistoricalFS!C47:C48),0) -> 0.99278073 | D31: =IFERROR(HistoricalFS!D6/SUM(HistoricalFS!D47:D48),0) -> 1.0862406 | E31: =IFERROR(HistoricalFS!E6/SUM(HistoricalFS!E47:E48),0) -> 1.2729414 | F31: =IFERROR(HistoricalFS!F6/SUM(HistoricalFS!F47:F48),0) -> 1.3871811 | G31: =IFERROR(HistoricalFS!G6/SUM(HistoricalFS!G47:G48),0) -> 1.3159225 | H31: =IFERROR(HistoricalFS!H6/SUM(HistoricalFS!H47:H48),0) -> 1.6143464 | I31: =IFERROR(HistoricalFS!I6/SUM(HistoricalFS!I47:I48),0) -> 1.9463312 | J31: =IFERROR(HistoricalFS!J6/SUM(HistoricalFS!J47:J48),0) -> 1.7439512 | ... L31: =IFERROR(HistoricalFS!L6/SUM(HistoricalFS!L47:L48),0) -> 1.9240296 | O31: =IFERROR(AVERAGE(C31:L31),0) -> 1.4984762 | P31: =IFERROR(MEDIAN(C31:L31),0) -> 1.5007637
B33: (in days)
B34: Debtor Days | C34: =IFERROR(365/C27,0) -> 65.672712 | D34: =IFERROR(365/D27,0) -> 68.018916 | E34: =IFERROR(365/E27,0) -> 65.459389 | F34: =IFERROR(365/F27,0) -> 74.321849 | G34: =IFERROR(365/G27,0) -> 70.092265 | H34: =IFERROR(365/H27,0) -> 68.108368 | I34: =IFERROR(365/I27,0) -> 63.227837 | J34: =IFERROR(365/J27,0) -> 71.715006 | ... L34: =IFERROR(365/L27,0) -> 71.986622 | O34: =IFERROR(AVERAGE(C34:L34),0) -> 68.837823 | P34: =IFERROR(MEDIAN(C34:L34),0) -> 68.941815
B35: Payable Days (Trade Payables) | C35: =IFERROR(365/C28,0) -> 1.9560043 | D35: =IFERROR(365/D28,0) -> 3.5919288 | E35: =IFERROR(365/E28,0) -> 7.3066223 | F35: =IFERROR(365/F28,0) -> 11.465674 | G35: =IFERROR(365/G28,0) -> 9.608896 | H35: =IFERROR(365/H28,0) -> 12.404617 | I35: =IFERROR(365/I28,0) -> 9.6120041 | J35: =IFERROR(365/J28,0) -> 9.3963688 | ... L35: =IFERROR(365/L28,0) -> 9.6924713 | O35: =IFERROR(AVERAGE(C35:L35),0) -> 8.4359453 | P35: =IFERROR(MEDIAN(C35:L35),0) -> 9.5026324
B36: Inventory Days | C36: =IFERROR(365/C29,0) -> 0 | D36: =IFERROR(365/D29,0) -> 0 | E36: =IFERROR(365/E29,0) -> 0 | F36: =IFERROR(365/F29,0) -> 0 | G36: =IFERROR(365/G29,0) -> 0 | H36: =IFERROR(365/H29,0) -> 0 | I36: =IFERROR(365/I29,0) -> 0 | J36: =IFERROR(365/J29,0) -> 0 | ... L36: =IFERROR(365/L29,0) -> 0 | O36: =IFERROR(AVERAGE(C36:L36),0) -> 0 | P36: =IFERROR(MEDIAN(C36:L36),0) -> 0
B37: Cash Conversion Cycle (in days) | C37: =IFERROR(SUM(C34,C36)-C35,0) -> 63.716708 | D37: =IFERROR(SUM(D34,D36)-D35,0) -> 64.426987 | E37: =IFERROR(SUM(E34,E36)-E35,0) -> 58.152767 | F37: =IFERROR(SUM(F34,F36)-F35,0) -> 62.856175 | G37: =IFERROR(SUM(G34,G36)-G35,0) -> 60.483369 | H37: =IFERROR(SUM(H34,H36)-H35,0) -> 55.703751 | I37: =IFERROR(SUM(I34,I36)-I35,0) -> 53.615833 | J37: =IFERROR(SUM(J34,J36)-J35,0) -> 62.318637 | ... L37: =IFERROR(SUM(L34,L36)-L35,0) -> 62.294151 | O37: =IFERROR(AVERAGE(C37:L37),0) -> 60.401877 | P37: =IFERROR(MEDIAN(C37:L37),0) -> 61.38876
B39: CFO/Sales | C39: =IFERROR(HistoricalFS!C105/HistoricalFS!C6,0) -> 0.16837509 | D39: =IFERROR(HistoricalFS!D105/HistoricalFS!D6,0) -> 0.18743087 | E39: =IFERROR(HistoricalFS!E105/HistoricalFS!E6,0) -> 0.17951013 | F39: =IFERROR(HistoricalFS!F105/HistoricalFS!F6,0) -> 0.18727627 | G39: =IFERROR(HistoricalFS!G105/HistoricalFS!G6,0) -> 0.23114898 | H39: =IFERROR(HistoricalFS!H105/HistoricalFS!H6,0) -> 0.19635649 | I39: =IFERROR(HistoricalFS!I105/HistoricalFS!I6,0) -> 0.15307937 | J39: =IFERROR(HistoricalFS!J105/HistoricalFS!J6,0) -> 0.16405284 | ... L39: =IFERROR(HistoricalFS!L105/HistoricalFS!L6,0) -> 0.1902379 | O39: =IFERROR(AVERAGE(C39:L39),0) -> 0.1876463 | P39: =IFERROR(MEDIAN(C39:L39),0) -> 0.18735357
B40: CFO/Total Assets | C40: =IFERROR(HistoricalFS!C105/HistoricalFS!C64,0) -> 0.13868043 | D40: =IFERROR(HistoricalFS!D105/HistoricalFS!D64,0) -> 0.16658055 | E40: =IFERROR(HistoricalFS!E105/HistoricalFS!E64,0) -> 0.17653986 | F40: =IFERROR(HistoricalFS!F105/HistoricalFS!F64,0) -> 0.18521786 | G40: =IFERROR(HistoricalFS!G105/HistoricalFS!G64,0) -> 0.21601511 | H40: =IFERROR(HistoricalFS!H105/HistoricalFS!H64,0) -> 0.20461925 | I40: =IFERROR(HistoricalFS!I105/HistoricalFS!I64,0) -> 0.18031879 | J40: =IFERROR(HistoricalFS!J105/HistoricalFS!J64,0) -> 0.18534039 | ... L40: =IFERROR(HistoricalFS!L105/HistoricalFS!L64,0) -> 0.22027637 | O40: =IFERROR(AVERAGE(C40:L40),0) -> 0.19150988 | P40: =IFERROR(MEDIAN(C40:L40),0) -> 0.18527913
B41: CFO/Total Debt | C41: =IFERROR(HistoricalFS!C105/HistoricalFS!C49,0) -> 0 | D41: =IFERROR(HistoricalFS!D105/HistoricalFS!D49,0) -> 0 | E41: =IFERROR(HistoricalFS!E105/HistoricalFS!E49,0) -> 0 | F41: =IFERROR(HistoricalFS!F105/HistoricalFS!F49,0) -> 3.6699763 | G41: =IFERROR(HistoricalFS!G105/HistoricalFS!G49,0) -> 4.3613146 | H41: =IFERROR(HistoricalFS!H105/HistoricalFS!H49,0) -> 4.363354 | I41: =IFERROR(HistoricalFS!I105/HistoricalFS!I49,0) -> 2.7071936 | J41: =IFERROR(HistoricalFS!J105/HistoricalFS!J49,0) -> 3.015911 | ... L41: =IFERROR(HistoricalFS!L105/HistoricalFS!L49,0) -> 3.7037925 | O41: =IFERROR(AVERAGE(C41:L41),0) -> 2.6160183 | P41: =IFERROR(MEDIAN(C41:L41),0) -> 3.3429436

Sheet Dupont Analysis
B3: ='Data Sheet'!B1 -> INFOSYS LTD
B6: ( Infosys Ltd | BSE Code: 500209 )
B7: =CONCATENATE(" ","INR "&'Data Sheet'!B8) -> INR 1121
B8: 52 Week (High - INR 224 & Low - 153)
B10: About the company
B11: Infosys Limited is an Indian multinational information technology company headquartered in Bengaluru, providing next-generation digital services and consulting. Founded on 2 July 1981 by N.R. Narayana Murthy and six co-founders, it is India's second-largest IT services company by revenue after TCS, listed on the BSE, NSE and NYSE (as ADRs). As of March 2026, Infosys employed over 328,000 people and served clients across BFSI, retail, manufacturing, communications, energy/utilities and life sciences verticals worldwide.
B16: Financial Summary
B67: Return on Equity (ROE)
C68: =HistoricalFS!F3 -> 43921 | D68: =HistoricalFS!G3 -> 44286 | E68: =HistoricalFS!H3 -> 44651 | F68: =HistoricalFS!I3 -> 45016 | G68: =HistoricalFS!J3 -> 45382 | H68: =HistoricalFS!K3 -> 45747 | I68: =HistoricalFS!L3 -> 46112
B69: Net Profit | C69: ='Data Sheet'!E30 -> 16594 | D69: ='Data Sheet'!F30 -> 19351 | E69: ='Data Sheet'!G30 -> 22110 | F69: ='Data Sheet'!H30 -> 24095 | G69: ='Data Sheet'!I30 -> 26233 | H69: ='Data Sheet'!J30 -> 26713 | I69: ='Data Sheet'!K30 -> 29440
B70: Average Share Holder Equity | C70: =(('Data Sheet'!E57+'Data Sheet'!E58)+('Data Sheet'!D57+'Data Sheet'!D58))/2 -> 65199 | D70: =(('Data Sheet'!F57+'Data Sheet'!F58)+('Data Sheet'!E57+'Data Sheet'!E58))/2 -> 70900.5 | E70: =(('Data Sheet'!G57+'Data Sheet'!G58)+('Data Sheet'!F57+'Data Sheet'!F58))/2 -> 75850.5 | F70: =(('Data Sheet'!H57+'Data Sheet'!H58)+('Data Sheet'!G57+'Data Sheet'!G58))/2 -> 75378.5 | G70: =(('Data Sheet'!I57+'Data Sheet'!I58)+('Data Sheet'!H57+'Data Sheet'!H58))/2 -> 81761.5 | H70: =(('Data Sheet'!J57+'Data Sheet'!J58)+('Data Sheet'!I57+'Data Sheet'!I58))/2 -> 91967 | I70: =(('Data Sheet'!K57+'Data Sheet'!K58)+('Data Sheet'!J57+'Data Sheet'!J58))/2 -> 94335
B71: Return on Equity (ROE) | C71: =C69/C70 -> 0.25451311 | D71: =D69/D70 -> 0.27293178 | E71: =E69/E70 -> 0.29149445 | F71: =F69/F70 -> 0.31965348 | G71: =G69/G70 -> 0.32084783 | H71: =H69/H70 -> 0.29046288 | I71: =I69/I70 -> 0.31207929
B73: ROE - Dupont Equation
C74: =C68 -> 43921 | D74: =D68 -> 44286 | E74: =E68 -> 44651 | F74: =F68 -> 45016 | G74: =G68 -> 45382 | H74: =H68 -> 45747 | I74: =I68 -> 46112
B75: =B69 -> Net Profit | C75: =C69 -> 16594 | D75: =D69 -> 19351 | E75: =E69 -> 22110 | F75: =F69 -> 24095 | G75: =G69 -> 26233 | H75: =H69 -> 26713 | I75: =I69 -> 29440
B76: Revenue | C76: ='Data Sheet'!E17 -> 90791 | D76: ='Data Sheet'!F17 -> 100472 | E76: ='Data Sheet'!G17 -> 121641 | F76: ='Data Sheet'!H17 -> 146767 | G76: ='Data Sheet'!I17 -> 153670 | H76: ='Data Sheet'!J17 -> 162990 | I76: ='Data Sheet'!K17 -> 178650
B77: Net Profit Margin (A) | C77: =C75/C76 -> 0.18277142 | D77: =D75/D76 -> 0.19260092 | E77: =E75/E76 -> 0.18176437 | F77: =F75/F76 -> 0.16417178 | G77: =G75/G76 -> 0.17070996 | H77: =H75/H76 -> 0.16389349 | I77: =I75/I76 -> 0.16479149
B79: Revenue | C79: =C76 -> 90791 | D79: =D76 -> 100472 | E79: =E76 -> 121641 | F79: =F76 -> 146767 | G79: =G76 -> 153670 | H79: =H76 -> 162990 | I79: =I76 -> 178650
B80: Average Total Asset | C80: =('Data Sheet'!E66+'Data Sheet'!D66)/2 -> 87933 | D80: =('Data Sheet'!F66+'Data Sheet'!E66)/2 -> 99655.5 | E80: =('Data Sheet'!G66+'Data Sheet'!F66)/2 -> 112120 | F80: =('Data Sheet'!H66+'Data Sheet'!G66)/2 -> 120662.5 | G80: =('Data Sheet'!I66+'Data Sheet'!H66)/2 -> 130308 | H80: =('Data Sheet'!J66+'Data Sheet'!I66)/2 -> 141907.5 | I80: =('Data Sheet'!K66+'Data Sheet'!J66)/2 -> 151041.5
B81: Asset Turnover Ratio (B) | C81: =C79/C80 -> 1.032502 | D81: =D79/D80 -> 1.0081932 | E81: =E79/E80 -> 1.0849179 | F81: =F79/F80 -> 1.2163431 | G81: =G79/G80 -> 1.1792829 | H81: =H79/H80 -> 1.1485651 | I81: =I79/I80 -> 1.1827875
B83: Average Total Asset | C83: =C80 -> 87933 | D83: =D80 -> 99655.5 | E83: =E80 -> 112120 | F83: =F80 -> 120662.5 | G83: =G80 -> 130308 | H83: =H80 -> 141907.5 | I83: =I80 -> 151041.5
B84: =B70 -> Average Share Holder Equity | C84: =C70 -> 65199 | D84: =D70 -> 70900.5 | E84: =E70 -> 75850.5 | F84: =F70 -> 75378.5 | G84: =G70 -> 81761.5 | H84: =H70 -> 91967 | I84: =I70 -> 94335
B85: Equity Multiplier (C) | C85: =C83/C84 -> 1.3486863 | D85: =D83/D84 -> 1.4055684 | E85: =E83/E84 -> 1.4781709 | F85: =F83/F84 -> 1.6007549 | G85: =G83/G84 -> 1.5937575 | H85: =H83/H84 -> 1.5430263 | I85: =I83/I84 -> 1.6011184
B87: Return on Equity (A*B*C) | C87: =C77*C81*C85 -> 0.25451311 | D87: =D77*D81*D85 -> 0.27293178 | E87: =E77*E81*E85 -> 0.29149445 | F87: =F77*F81*F85 -> 0.31965348 | G87: =G77*G81*G85 -> 0.32084783 | H87: =H77*H81*H85 -> 0.29046288 | I87: =I77*I81*I85 -> 0.31207929
B89: Return on Asset (ROA)
C90: =C68 -> 43921 | D90: =D68 -> 44286 | E90: =E68 -> 44651 | F90: =F68 -> 45016 | G90: =G68 -> 45382 | H90: =H68 -> 45747 | I90: =I68 -> 46112
B91: Net Profit | C91: =C69 -> 16594 | D91: =D69 -> 19351 | E91: =E69 -> 22110 | F91: =F69 -> 24095 | G91: =G69 -> 26233 | H91: =H69 -> 26713 | I91: =I69 -> 29440
B92: =B80 -> Average Total Asset | C92: =C80 -> 87933 | D92: =D80 -> 99655.5 | E92: =E80 -> 112120 | F92: =F80 -> 120662.5 | G92: =G80 -> 130308 | H92: =H80 -> 141907.5 | I92: =I80 -> 151041.5
B93: Return on Asset (ROA) | C93: =C91/C92 -> 0.18871186 | D93: =D91/D92 -> 0.19417895 | E93: =E91/E92 -> 0.19719943 | F93: =F91/F92 -> 0.19968922 | G93: =G91/G92 -> 0.20131535 | H93: =H91/H92 -> 0.18824234 | I93: =I91/I92 -> 0.19491332
B95: ROA - Dupont Equation
C96: =C90 -> 43921 | D96: =D90 -> 44286 | E96: =E90 -> 44651 | F96: =F90 -> 45016 | G96: =G90 -> 45382 | H96: =H90 -> 45747 | I96: =I90 -> 46112
B97: =B91 -> Net Profit | C97: =C91 -> 16594 | D97: =D91 -> 19351 | E97: =E91 -> 22110 | F97: =F91 -> 24095 | G97: =G91 -> 26233 | H97: =H91 -> 26713 | I97: =I91 -> 29440
B98: Revenue | C98: =C79 -> 90791 | D98: =D79 -> 100472 | E98: =E79 -> 121641 | F98: =F79 -> 146767 | G98: =G79 -> 153670 | H98: =H79 -> 162990 | I98: =I79 -> 178650
B99: Net Profit Margin (A) | C99: =C97/C98 -> 0.18277142 | D99: =D97/D98 -> 0.19260092 | E99: =E97/E98 -> 0.18176437 | F99: =F97/F98 -> 0.16417178 | G99: =G97/G98 -> 0.17070996 | H99: =H97/H98 -> 0.16389349 | I99: =I97/I98 -> 0.16479149
B101: Revenue | C101: =C98 -> 90791 | D101: =D98 -> 100472 | E101: =E98 -> 121641 | F101: =F98 -> 146767 | G101: =G98 -> 153670 | H101: =H98 -> 162990 | I101: =I98 -> 178650
B102: Average Total Asset | C102: =C92 -> 87933 | D102: =D92 -> 99655.5 | E102: =E92 -> 112120 | F102: =F92 -> 120662.5 | G102: =G92 -> 130308 | H102: =H92 -> 141907.5 | I102: =I92 -> 151041.5
B103: Asset Turnover Ratio (B) | C103: =C101/C102 -> 1.032502 | D103: =D101/D102 -> 1.0081932 | E103: =E101/E102 -> 1.0849179 | F103: =F101/F102 -> 1.2163431 | G103: =G101/G102 -> 1.1792829 | H103: =H101/H102 -> 1.1485651 | I103: =I101/I102 -> 1.1827875
B105: Return on Asset (A*B) | C105: =C99*C103 -> 0.18871186 | D105: =D99*D103 -> 0.19417895 | E105: =E99*E103 -> 0.19719943 | F105: =F99*F103 -> 0.19968922 | G105: =G99*G103 -> 0.20131535 | H105: =H99*H103 -> 0.18824234 | I105: =I99*I103 -> 0.19491332

Sheet Altman Z Score
B3: ='Data Sheet'!B1 -> INFOSYS LTD
B6: ( Infosys Ltd | BSE Code: 500209 )
B7: =CONCATENATE(" ","INR "&'Data Sheet'!B8) -> INR 1121
B8: 52 Week (High - INR 1728 & Low - 982)
B10: Altman's Z Score Analysis
B11: Infosys Limited is an Indian multinational information technology company headquartered in Bengaluru, providing next-generation digital services and consulting. Founded on 2 July 1981 by N.R. Narayana Murthy and six co-founders, it is India's second-largest IT services company by revenue after TCS, listed on the BSE, NSE and NYSE (as ADRs). As of March 2026, Infosys employed over 328,000 people and served clients across BFSI, retail, manufacturing, communications, energy/utilities and life sciences verticals worldwide.
B16: Financial Summary
B67: Working Capital / Total Assets
C68: =HistoricalFS!F3 -> 43921 | D68: =HistoricalFS!G3 -> 44286 | E68: =HistoricalFS!H3 -> 44651 | F68: =HistoricalFS!I3 -> 45016 | G68: =HistoricalFS!J3 -> 45382 | H68: =HistoricalFS!K3 -> 45747 | I68: =HistoricalFS!L3 -> 46112
B69: Working Capital | C69: ='Data Sheet'!E65-'Data Sheet'!E60 -> 36548 | D69: ='Data Sheet'!F65-'Data Sheet'!F60 -> 41044 | E69: ='Data Sheet'!G65-'Data Sheet'!G60 -> 34284 | F69: ='Data Sheet'!H65-'Data Sheet'!H60 -> 34715 | G69: ='Data Sheet'!I65-'Data Sheet'!I60 -> 43937 | H69: ='Data Sheet'!J65-'Data Sheet'!J60 -> 48729 | I69: ='Data Sheet'!K65-'Data Sheet'!K60 -> 45852
B70: Total Asset | C70: ='Data Sheet'!E66 -> 91800 | D70: ='Data Sheet'!F66 -> 107511 | E70: ='Data Sheet'!G66 -> 116729 | F70: ='Data Sheet'!H66 -> 124596 | G70: ='Data Sheet'!I66 -> 136020 | H70: ='Data Sheet'!J66 -> 147795 | I70: ='Data Sheet'!K66 -> 154288
B71: Working Capital / Total Assets (A) | C71: =C69/C70 -> 0.39812636 | D71: =D69/D70 -> 0.38176559 | E71: =E69/E70 -> 0.29370593 | F71: =F69/F70 -> 0.2786205 | G71: =G69/G70 -> 0.32301867 | H71: =H69/H70 -> 0.32970669 | I71: =I69/I70 -> 0.29718449
B73: Retained Earnings / Total Assets (Proxy: Reserves)
C74: =C68 -> 43921 | D74: =D68 -> 44286 | E74: =E68 -> 44651 | F74: =F68 -> 45016 | G74: =G68 -> 45382 | H74: =H68 -> 45747 | I74: =I68 -> 46112
B75: Retained Earnings | C75: ='Data Sheet'!E78 -> 56309 | D75: ='Data Sheet'!F78 -> 62643 | E75: ='Data Sheet'!G78 -> 61313 | F75: ='Data Sheet'!H78 -> 58957 | G75: ='Data Sheet'!I78 -> 68405 | H75: ='Data Sheet'!J78 -> 78627 | I75: ='Data Sheet'!K78 -> 76503
B76: Total Assets | C76: =C70 -> 91800 | D76: =D70 -> 107511 | E76: =E70 -> 116729 | F76: =F70 -> 124596 | G76: =G70 -> 136020 | H76: =H70 -> 147795 | I76: =I70 -> 154288
B77: Retained Earnings / Total Assets (B) | C77: =C75/C76 -> 0.6133878 | D77: =D75/D76 -> 0.58266596 | E77: =E75/E76 -> 0.52525936 | F77: =F75/F76 -> 0.47318534 | G77: =G75/G76 -> 0.50290398 | H77: =H75/H76 -> 0.53200041 | I77: =I75/I76 -> 0.49584543
B79: EBIT / Total Assets
B80: EBIT | C80: =HistoricalFS!F18-HistoricalFS!F24 -> 19374 | D80: =HistoricalFS!G18-HistoricalFS!G24 -> 24622 | E80: =HistoricalFS!H18-HistoricalFS!H24 -> 28015 | F80: =HistoricalFS!I18-HistoricalFS!I24 -> 30905 | G80: =HistoricalFS!J18-HistoricalFS!J24 -> 31747 | H80: =HistoricalFS!K18-HistoricalFS!K24 -> 34424 | I80: =HistoricalFS!L18-HistoricalFS!L24 -> 37378
B81: Total Assets | C81: =C76 -> 91800 | D81: =D76 -> 107511 | E81: =E76 -> 116729 | F81: =F76 -> 124596 | G81: =G76 -> 136020 | H81: =H76 -> 147795 | I81: =I76 -> 154288
B82: EBIT / Total Assets (C) | C82: =C80/C81 -> 0.21104575 | D82: =D80/D81 -> 0.22901843 | E82: =E80/E81 -> 0.24000034 | F82: =F80/F81 -> 0.24804167 | G82: =G80/G81 -> 0.2333995 | H82: =H80/H81 -> 0.23291722 | I82: =I80/I81 -> 0.24226123
B84: Market Cap / Total Liabilities
B85: Market Cap | C85: ='Data Sheet'!E70*'Data Sheet'!E90/10000000 -> 272044.32 | D85: ='Data Sheet'!F70*'Data Sheet'!F90/10000000 -> 580757.21 | E85: ='Data Sheet'!G70*'Data Sheet'!G90/10000000 -> 799544.67 | F85: ='Data Sheet'!H70*'Data Sheet'!H90/10000000 -> 590655.51 | G85: ='Data Sheet'!I70*'Data Sheet'!I90/10000000 -> 620185.3 | H85: ='Data Sheet'!J70*'Data Sheet'!J90/10000000 -> 650815.72 | I85: ='Data Sheet'!K70*'Data Sheet'!K90/10000000 -> 506110.42
B86: Total Liabilities | C86: ='Data Sheet'!E61 -> 91800 | D86: ='Data Sheet'!F61 -> 107511 | E86: ='Data Sheet'!G61 -> 116729 | F86: ='Data Sheet'!H61 -> 124596 | G86: ='Data Sheet'!I61 -> 136020 | H86: ='Data Sheet'!J61 -> 147795 | I86: ='Data Sheet'!K61 -> 154288
B87: Market Cap / Total Liabilities (D) | C87: =C85/C86 -> 2.9634457 | D87: =D85/D86 -> 5.4018399 | E87: =E85/E86 -> 6.8495804 | F87: =F85/F86 -> 4.7405656 | G87: =G85/G86 -> 4.5595155 | H87: =H85/H86 -> 4.4035029 | I87: =I85/I86 -> 3.2802967
B89: Sales / Total Assets
C90: =C68 -> 43921 | D90: =D68 -> 44286 | E90: =E68 -> 44651 | F90: =F68 -> 45016 | G90: =G68 -> 45382 | H90: =H68 -> 45747 | I90: =I68 -> 46112
B91: Total Sales | C91: ='Data Sheet'!E17 -> 90791 | D91: ='Data Sheet'!F17 -> 100472 | E91: ='Data Sheet'!G17 -> 121641 | F91: ='Data Sheet'!H17 -> 146767 | G91: ='Data Sheet'!I17 -> 153670 | H91: ='Data Sheet'!J17 -> 162990 | I91: ='Data Sheet'!K17 -> 178650
B92: =B81 -> Total Assets | C92: =C81 -> 91800 | D92: =D81 -> 107511 | E92: =E81 -> 116729 | F92: =F81 -> 124596 | G92: =G81 -> 136020 | H92: =H81 -> 147795 | I92: =I81 -> 154288
B93: Sales / Total Assets (E) | C93: =C91/C92 -> 0.98900871 | D93: =D91/D92 -> 0.93452763 | E93: =E91/E92 -> 1.0420804 | F93: =F91/F92 -> 1.1779431 | G93: =G91/G92 -> 1.1297603 | H93: =H91/H92 -> 1.1028113 | I93: =I91/I92 -> 1.1578995
B95: Altman's Z Score
C96: =C90 -> 43921 | D96: =D90 -> 44286 | E96: =E90 -> 44651 | F96: =F90 -> 45016 | G96: =G90 -> 45382 | H96: =H90 -> 45747 | I96: =I90 -> 46112
B97: Altman Z-Score (proxy; see assumptions) | C97: =(C71*1.2)+(C77*1.4)+(C82*3.3)+(C87*0.6)+(C93*1) -> 4.8000217 | D97: =(D71*1.2)+(D77*1.4)+(D82*3.3)+(D87*0.6)+(D93*1) -> 6.2052434 | E97: =(E71*1.2)+(E77*1.4)+(E82*3.3)+(E87*0.6)+(E93*1) -> 7.03164 | F97: =(F71*1.2)+(F77*1.4)+(F82*3.3)+(F87*0.6)+(F93*1) -> 5.8376241 | G97: =(G71*1.2)+(G77*1.4)+(G82*3.3)+(G87*0.6)+(G93*1) -> 5.727376 | H97: =(H71*1.2)+(H77*1.4)+(H82*3.3)+(H87*0.6)+(H93*1) -> 5.6539885 | I97: =(I71*1.2)+(I77*1.4)+(I82*3.3)+(I87*0.6)+(I93*1) -> 4.9763446
B98: Financial Stability | C98: =IF(C97<1.81,"Distressed",IF(C97>3,"Strong","Grey Zone")) -> Strong | D98: =IF(D97<1.81,"Distressed",IF(D97>3,"Strong","Grey Zone")) -> Strong | E98: =IF(E97<1.81,"Distressed",IF(E97>3,"Strong","Grey Zone")) -> Strong | F98: =IF(F97<1.81,"Distressed",IF(F97>3,"Strong","Grey Zone")) -> Strong | G98: =IF(G97<1.81,"Distressed",IF(G97>3,"Strong","Grey Zone")) -> Strong | H98: =IF(H97<1.81,"Distressed",IF(H97>3,"Strong","Grey Zone")) -> Strong | I98: =IF(I97<1.81,"Distressed",IF(I97>3,"Strong","Grey Zone")) -> Strong
B99: Interpretation uses standard manufacturing Z-score bands; X2/X4 are proxies.

Sheet Operating Drivers
A1: INFOSYS LTD - Operating Drivers & Outlook
A2: Purpose: Convert current business evidence into explicit, auditable forecasting assumptions; all forward estimates are analyst assumptions unless explicitly marked as company guidance.
A4: Current Operating Context
A5: FY26 Revenue (₹ Cr) | B5: =HistoricalFS!L6 -> 178650 | C5: FY26 reported revenue; source: Infosys FY26 annual report
A6: FY26 Reported Operating Margin | B6: 0.203 | C6: Official FY26 reported operating margin
A7: FY26 Adjusted Operating Margin | B7: 0.21 | C7: Official FY26 adjusted operating margin
A8: FY26 Free Cash Flow (₹ Cr) | B8: 33097 | C8: Official FY26 FCF
A9: FY26 Large Deal TCV (US$ bn) | B9: 14.9 | C9: Official FY26 large-deal TCV
A10: FY26 Net-New TCV | B10: 0.55 | C10: Official FY26 net-new share of large-deal TCV
A11: Q1 FY27 Revenue (₹ Cr) | B11: 48211 | C11: Official Q1 FY27 revenue
A12: Q1 FY27 YoY Revenue Growth | B12: 0.14 | C12: Official Q1 FY27 reported YoY growth
A13: Q1 FY27 Operating Margin | B13: 0.211 | C13: Official Q1 FY27 operating margin
A14: FY27 Revenue Guidance - Low (CC) | B14: 0.015 | C14: Company guidance, constant currency
A15: FY27 Revenue Guidance - Midpoint (CC) | B15: 0.0225 | C15: Midpoint of the current 1.5%-3.0% company guidance (revised down from 1.5%-3.5% at Q1 FY27); used as a normalized starting point for the INR forecast, not as a direct CC-to-INR conversion
A16: FY27 Revenue Guidance - High (CC) | B16: 0.03 | C16: Company guidance, constant currency
A17: Long-run Mature Segment Growth | B17: 0.03 | C17: Analyst assumption used for segment-growth convergence; separate from terminal growth.
A19: FY26 Segment Context
A20: Segment | B20: FY25 Revenue (₹ Cr) | C20: FY26 Revenue (₹ Cr) | D20: FY26 YoY Growth | E20: Note | F20: FY27 segment growth assumptions are analyst inputs; FY26 actuals verified to Infosys FY26 Annual Report. Base-case DCF revenue growth is now driven by the segment forecast total.
A21: Financial Services | B21: 45175 | C21: 49908 | D21: 0.105 | E21: 0.023
A22: Manufacturing | B22: 25207 | C22: 29078 | D22: 0.154 | E22: 0.035
A23: Retail | B23: 21710 | C23: 23818 | D23: 0.097 | E23: 0.023
A24: Energy, Utilities, Resources & Services | B24: 22059 | C24: 23077 | D24: 0.046 | E24: 0.018
A25: Communication | B25: 19108 | C25: 21765 | D25: 0.139 | E25: 0.015
A26: Hi-Tech | B26: 13090 | C26: 13928 | D26: 0.064 | E26: 0.04
A27: Life Sciences | B27: 11831 | C27: 12267 | D27: 0.037 | E27: 0.025
A28: All Other Segments | B28: 4810 | C28: 4809 | D28: 0 | E28: 0.015
A29: Weighted FY27 segment growth | B29: =SUMPRODUCT(C21:C28,E21:E28)/SUM(C21:C28) -> 0.024580011 | C29: Cross-check vs. FY27 CC guidance midpoint | D29: =B29-B15 -> 0.0020800112
A32: Base-Case Explicit Forecast Assumptions
A33: Metric | B33: FY27 | C33: FY28 | D33: FY29 | E33: FY30 | F33: FY31
A34: Revenue Growth | B34: ='Segment Forecast'!D12 -> 0.024580011 | C34: ='Segment Forecast'!E12 -> 0.025976365 | D34: ='Segment Forecast'!F12 -> 0.027325024 | E34: ='Segment Forecast'!G12 -> 0.028669518 | F34: ='Segment Forecast'!H12 -> 0.03 | G34: Segment-driven base-case revenue growth
A35: Consolidated EBIT Margin (derived) | B35: ='Integrated Operating Model'!C9 -> 0.20970599 | C35: ='Integrated Operating Model'!D9 -> 0.21046476 | D35: ='Integrated Operating Model'!E9 -> 0.21148651 | E35: ='Integrated Operating Model'!F9 -> 0.21210499 | F35: ='Integrated Operating Model'!G9 -> 0.21227656
A36: Target ROIC | B36: 0.45 | C36: 0.44 | D36: 0.43 | E36: 0.42 | F36: 0.4
A37: Reinvestment Rate | B37: =B34/B36 -> 0.054622247 | C37: =C34/C36 -> 0.059037192 | D37: =D34/D36 -> 0.063546568 | E37: =E34/E36 -> 0.068260756 | F37: =F34/F36 -> 0.075
A38: Normalized Effective Tax Rate (DCF) | B38: 0.295 | C38: 0.295 | D38: 0.295 | E38: 0.295 | F38: 0.295 | G38: Normalized effective tax rate for FCFF forecast; WACC tax shield rate is separately defined below.
A39: WACC | B39: =WACC!$L$45 -> 0.11593086 | C39: =WACC!$L$45 -> 0.11593086 | D39: =WACC!$L$45 -> 0.11593086 | E39: =WACC!$L$45 -> 0.11593086 | F39: =WACC!$L$45 -> 0.11593086
A40: Mid-Year | B40: 0.5 | C40: 1.5 | D40: 2.5 | E40: 3.5 | F40: 4.5
A41: Corporate / Unallocated Cost % Revenue | B41: ='Normalization Bridge'!B12/'Segment Profitability'!B31 -> 0.027439127 | C41: =B41 -> 0.027439127 | D41: =B41 -> 0.027439127 | E41: =B41 -> 0.027439127 | F41: =B41 -> 0.027439127
A43: Terminal Assumptions
A44: Terminal Growth | B44: 0.03
A45: Terminal ROIC | B45: 0.4
A46: Terminal Reinvestment Rate | B46: =B44/B45 -> 0.075
A47: Terminal Growth Check | B47: =IF(B44<WACC!$L$45,"PASS","FAIL: g >= WACC") -> PASS
A48: WACC Tax Shield Rate | B48: =WACC!$E$28 -> 0.2517 | C48: Marginal/statutory rate used for debt tax shield.
A49: Methodology | B49: Explicit-period reinvestment = Revenue Growth / Target ROIC. Integrated EBIT = Segment Operating Income less normalized corporate/unallocated costs. FY26 corporate/unallocated costs are anchored to the gap between segment operating income and normalized consolidated EBIT. DCF uses 29.5% normalized effective tax; WACC uses a separate statutory/marginal tax rate.
A53: Sources | B53: Infosys FY26 Integrated Annual Report; Infosys Q1 FY27 financial snapshot/results. Segment figures are FY25/FY26 reported data; FY27 segment growth assumptions are analyst estimates and are not company guidance.
B54: https://www.infosys.com/investors/reports-filings/annual-report/annual-reports/ar-2025-26.html
B55: https://www.infosys.com/about/last-quarter.html

Sheet Forecasting
B1: Integrated operating forecast feeding DCF >. Historical trend exhibits remain on the left; the live DCF forecast is on the right. | Q1: Base case uses the Operating Drivers forecast: FY27 growth starts at the guidance midpoint, then normalizes toward 3.0% by FY31; EBIT margin recovers toward 21.5%; explicit reinvestment is growth / target ROIC; terminal growth is 3.0% with terminal reinvestment derived from terminal growth / terminal ROIC. | R1: Base case uses FY27 guidance midpoint as a starting point and normalizes growth toward 3.0% by FY31. EBIT margin gradually recovers toward 21.5%. Explicit-period reinvestment is derived from growth / target ROIC; terminal reinvestment is derived separately from terminal growth / terminal ROIC.
B2: ='Data Sheet'!$B$1&" - " &'Data Sheet'!A17& " Forecasting " -> INFOSYS LTD - Sales Forecasting | G2: ='Data Sheet'!$B$1&" - " & HistoricalFS!B18&" Forecasting " -> INFOSYS LTD - EBITDA Forecasting | L2: ='Data Sheet'!$B$1&" - " &HistoricalFS!B38&" Forecasting " -> INFOSYS LTD - EPS Forecasting | Q2: Integrated DCF Forecast
B3: Year Weight | C3: Year | D3: Sales | E3: Sales Growth | G3: Year Weight | H3: Year | I3: Sales | J3: Sales Growth | L3: Year Weight | M3: Year | N3: Sales | O3: Sales Growth | Q3: Metric | R3: FY2027 | S3: FY2028 | T3: FY2029 | U3: FY2030 | V3: FY2031
B4: 1 | C4: ='Data Sheet'!$B$16 -> 42825 | D4: {=TRANSPOSE('Data Sheet'!B17:K17)} -> 68484 | G4: 1 | H4: =C4 -> 42825 | I4: {=TRANSPOSE(HistoricalFS!C18:L18)} -> 18604 | L4: 1 | M4: =H4 -> 42825 | N4: {=TRANSPOSE(HistoricalFS!C38:L38)} -> 24.604367 | Q4: Revenue Growth | R4: ='Operating Drivers'!B34 -> 0.024580011 | S4: ='Operating Drivers'!C34 -> 0.025976365 | T4: ='Operating Drivers'!D34 -> 0.027325024 | U4: ='Operating Drivers'!E34 -> 0.028669518 | V4: ='Operating Drivers'!F34 -> 0.03
B5: =B4+1 -> 2 | C5: ='Data Sheet'!$C$16 -> 43190 | D5: 70522 | E5: =D5/D4-1 -> 0.029758776 | G5: =G4+1 -> 2 | H5: =C5 -> 43190 | I5: 18822 | J5: =I5/I4-1 -> 0.01171791 | L5: =L4+1 -> 2 | M5: =H5 -> 43190 | N5: 29.114967 | O5: =N5/N4-1 -> 0.18332521 | Q5: Revenue (₹ Cr) | R5: =HistoricalFS!$L$6*(1+R4) -> 183041.22 | S5: =R5*(1+S4) -> 187795.96 | T5: =S5*(1+T4) -> 192927.49 | U5: =T5*(1+U4) -> 198458.63 | V5: =U5*(1+V4) -> 204412.39
B6: =B5+1 -> 3 | C6: ='Data Sheet'!$D$16 -> 43555 | D6: 82675 | E6: =D6/D5-1 -> 0.1723292 | G6: =G5+1 -> 3 | H6: =C6 -> 43555 | I6: 20170 | J6: =I6/I5-1 -> 0.071618319 | L6: =L5+1 -> 3 | M6: =H6 -> 43555 | N6: 28.67541 | O6: =N6/N5-1 -> -0.015097286 | Q6: EBIT Margin | R6: ='Operating Drivers'!B35 -> 0.20970599 | S6: ='Operating Drivers'!C35 -> 0.21046476 | T6: ='Operating Drivers'!D35 -> 0.21148651 | U6: ='Operating Drivers'!E35 -> 0.21210499 | V6: ='Operating Drivers'!F35 -> 0.21227656
B7: =B6+1 -> 4 | C7: ='Data Sheet'!$E$16 -> 43921 | D7: 90791 | E7: =D7/D6-1 -> 0.098167523 | G7: =G6+1 -> 4 | H7: =C7 -> 43921 | I7: 22267 | J7: =I7/I6-1 -> 0.10396629 | L7: =L6+1 -> 4 | M7: =H7 -> 43921 | N7: 32.486499 | O7: =N7/N6-1 -> 0.13290442 | Q7: EBIT (₹ Cr) | R7: =R5*R6 -> 38384.84 | S7: =S5*S6 -> 39524.433 | T7: =T5*T6 -> 40801.562 | U7: =U5*U6 -> 42094.066 | V7: =V5*V6 -> 43391.96
B8: =B7+1 -> 5 | C8: ='Data Sheet'!$F$16 -> 44286 | D8: 100472 | E8: =D8/D7-1 -> 0.10662951 | G8: =G7+1 -> 5 | H8: =C8 -> 44286 | I8: 27889 | J8: =I8/I7-1 -> 0.25248125 | L8: =L7+1 -> 5 | M8: =H8 -> 44286 | N8: 40.420588 | O8: =N8/N7-1 -> 0.24422727 | Q8: Tax Rate | R8: ='Operating Drivers'!B38 -> 0.295 | S8: ='Operating Drivers'!C38 -> 0.295 | T8: ='Operating Drivers'!D38 -> 0.295 | U8: ='Operating Drivers'!E38 -> 0.295 | V8: ='Operating Drivers'!F38 -> 0.295
B9: =B8+1 -> 6 | C9: ='Data Sheet'!$G$16 -> 44651 | D9: 121641 | E9: =D9/D8-1 -> 0.21069552 | G9: =G8+1 -> 6 | H9: =C9 -> 44651 | I9: 31491 | J9: =I9/I8-1 -> 0.12915486 | L9: =L8+1 -> 6 | M9: =H9 -> 44651 | N9: 47.189008 | O9: =N9/N8-1 -> 0.16744981 | Q9: NOPAT (₹ Cr) | R9: =R7*(1-R8) -> 27061.312 | S9: =S7*(1-S8) -> 27864.725 | T9: =T7*(1-T8) -> 28765.101 | U9: =U7*(1-U8) -> 29676.317 | V9: =V7*(1-V8) -> 30591.332
B10: =B9+1 -> 7 | C10: ='Data Sheet'!$H$16 -> 45016 | D10: 146767 | E10: =D10/D9-1 -> 0.20655864 | G10: =G9+1 -> 7 | H10: =C10 -> 45016 | I10: 35130 | J10: =I10/I9-1 -> 0.11555683 | L10: =L9+1 -> 7 | M10: =H10 -> 45016 | N10: 51.60054 | O10: =N10/N9-1 -> 0.093486431 | Q10: Reinvestment Rate | R10: ='Operating Drivers'!B37 -> 0.054622247 | S10: ='Operating Drivers'!C37 -> 0.059037192 | T10: ='Operating Drivers'!D37 -> 0.063546568 | U10: ='Operating Drivers'!E37 -> 0.068260756 | V10: ='Operating Drivers'!F37 -> 0.075
B11: =B10+1 -> 8 | C11: ='Data Sheet'!$I$16 -> 45382 | D11: 153670 | E11: =D11/D10-1 -> 0.047033734 | G11: =G10+1 -> 8 | H11: =C11 -> 45382 | I11: 36425 | J11: =I11/I10-1 -> 0.03686308 | L11: =L10+1 -> 8 | M11: =H11 -> 45382 | N11: 51.885133 | O11: =N11/N10-1 -> 0.0055153183 | Q11: FCFF (₹ Cr) | R11: =R9*(1-R10) -> 25583.163 | S11: =S9*(1-S10) -> 26219.67 | T11: =T9*(1-T10) -> 26937.178 | U11: =U9*(1-U10) -> 27650.589 | V11: =V9*(1-V10) -> 28296.982
B12: =B11+1 -> 9 | C12: ='Data Sheet'!$J$16 -> 45747 | D12: 162990 | E12: =D12/D11-1 -> 0.060649444 | G12: =G11+1 -> 9 | H12: =C12 -> 45747 | I12: 39236 | J12: =I12/I11-1 -> 0.077172272 | L12: =L11+1 -> 9 | M12: =H12 -> 45747 | N12: 55.73881 | O12: =N12/N11-1 -> 0.074273236 | Q12: Mid-Year | R12: ='Operating Drivers'!B40 -> 0.5 | S12: ='Operating Drivers'!C40 -> 1.5 | T12: ='Operating Drivers'!D40 -> 2.5 | U12: ='Operating Drivers'!E40 -> 3.5 | V12: ='Operating Drivers'!F40 -> 4.5
B13: =B12+1 -> 10 | C13: ='Data Sheet'!$K$16 -> 46112 | D13: 178650 | E13: =D13/D12-1 -> 0.096079514 | G13: =G12+1 -> 10 | H13: =C13 -> 46112 | I13: 42280 | J13: =I13/I12-1 -> 0.077581813 | L13: =L12+1 -> 10 | M13: =H13 -> 46112 | N13: 65.196272 | O13: =N13/N12-1 -> 0.16967463 | Q13: WACC | R13: ='Operating Drivers'!B39 -> 0.11593086 | S13: ='Operating Drivers'!C39 -> 0.11593086 | T13: ='Operating Drivers'!D39 -> 0.11593086 | U13: ='Operating Drivers'!E39 -> 0.11593086 | V13: ='Operating Drivers'!F39 -> 0.11593086
B14: =B13+1 -> 11 | C14: =C13+365 -> 46477 | D14: =FORECAST(B14,$D$4:$D$13,$B$4:$B$13) -> 190427.6 | E14: =D14/D13-1 -> 0.065925553 | G14: =G13+1 -> 11 | H14: =C14 -> 46477 | I14: =FORECAST(G14,$I$4:$I$13,$G$4:$G$13) -> 45213 | J14: =I14/I13-1 -> 0.069370861 | L14: =L13+1 -> 11 | M14: =H14 -> 46477 | N14: =FORECAST(L14,$N$4:$N$13,$L$4:$L$13) -> 67.086266 | O14: =N14/N13-1 -> 0.028989303 | Q14: Discount Factor | R14: =1/(1+R13)^R12 -> 0.94663238 | S14: =1/(1+S13)^S12 -> 0.84828945 | T14: =1/(1+T13)^T12 -> 0.76016309 | U14: =1/(1+U13)^U12 -> 0.68119192 | V14: =1/(1+V13)^V12 -> 0.61042485
B15: =B14+1 -> 12 | C15: =C14+365 -> 46842 | D15: =FORECAST(B15,$D$4:$D$13,$B$4:$B$13) -> 203656.95 | E15: =D15/D14-1 -> 0.069471786 | G15: =G14+1 -> 12 | H15: =C15 -> 46842 | I15: =FORECAST(G15,$I$4:$I$13,$G$4:$G$13) -> 48118.745 | J15: =I15/I14-1 -> 0.06426792 | L15: =L14+1 -> 12 | M15: =H15 -> 46842 | N15: =FORECAST(L15,$N$4:$N$13,$L$4:$L$13) -> 71.52174 | O15: =N15/N14-1 -> 0.066115976 | Q15: PV of FCFF (₹ Cr) | R15: =R11*R14 -> 24217.85 | S15: =S11*S14 -> 22241.869 | T15: =T11*T14 -> 20476.648 | U15: =U11*U14 -> 18835.358 | V15: =V11*V14 -> 17273.181
B16: =B15+1 -> 13 | C16: =C15+365 -> 47207 | D16: =FORECAST(B16,$D$4:$D$13,$B$4:$B$13) -> 216886.29 | E16: =D16/D15-1 -> 0.06495897 | G16: =G15+1 -> 13 | H16: =C16 -> 47207 | I16: =FORECAST(G16,$I$4:$I$13,$G$4:$G$13) -> 51024.491 | J16: =I16/I15-1 -> 0.060386974 | L16: =L15+1 -> 13 | M16: =H16 -> 47207 | N16: =FORECAST(L16,$N$4:$N$13,$L$4:$L$13) -> 75.957214 | O16: =N16/N15-1 -> 0.062015744
B17: =B16+1 -> 14 | C17: =C16+365 -> 47572 | D17: =FORECAST(B17,$D$4:$D$13,$B$4:$B$13) -> 230115.64 | E17: =D17/D16-1 -> 0.060996688 | G17: =G16+1 -> 14 | H17: =C17 -> 47572 | I17: =FORECAST(G17,$I$4:$I$13,$G$4:$G$13) -> 53930.236 | J17: =I17/I16-1 -> 0.056948054 | L17: =L16+1 -> 14 | M17: =H17 -> 47572 | N17: =FORECAST(L17,$N$4:$N$13,$L$4:$L$13) -> 80.392688 | O17: =N17/N16-1 -> 0.058394374 | Q17: Terminal Growth | R17: ='Operating Drivers'!$B$44 -> 0.03
B18: =B17+1 -> 15 | C18: =C17+365 -> 47937 | D18: =FORECAST(B18,$D$4:$D$13,$B$4:$B$13) -> 243344.98 | E18: =D18/D17-1 -> 0.057489989 | G18: =G17+1 -> 15 | H18: =C18 -> 47937 | I18: =FORECAST(G18,$I$4:$I$13,$G$4:$G$13) -> 56835.982 | J18: =I18/I17-1 -> 0.053879709 | L18: =L17+1 -> 15 | M18: =H18 -> 47937 | N18: =FORECAST(L18,$N$4:$N$13,$L$4:$L$13) -> 84.828162 | O18: =N18/N17-1 -> 0.055172604 | Q18: Terminal Growth Check | R18: =IF(R17<MIN(R13:V13),"PASS","ERROR: g >= WACC") -> PASS
Q19: Forecast Horizon | R19: 5 years
Q20: Model Status | R20: =IF(R18="PASS","Integrated / linked to Operating Drivers and DCF","Review") -> Integrated / linked to Operating Drivers and DCF

Sheet Forecast Scenarios
A1: Infosys Operating Scenarios
A2: Assumption | B2: Bear | C2: Base | D2: Bull | E2: Rationale | F2: Model Link
A3: FY27 Revenue Growth | B3: 0.015 | C3: ='Operating Drivers'!B34 -> 0.024580011 | D3: 0.03 | E3: Brackets the current FY27 company guidance of 1.5%-3.0% CC (revised down from 1.5%-3.5% at Q1 FY27). | F3: Revenue
A4: FY28 Revenue Growth | B4: 0.015 | C4: ='Operating Drivers'!C34 -> 0.025976365 | D4: 0.045 | E4: Normalization after FY27. | F4: Revenue
A5: FY29 Revenue Growth | B5: 0.015 | C5: ='Operating Drivers'!D34 -> 0.027325024 | D5: 0.045 | E5: Medium-term normalization. | F5: Revenue
A6: FY30 Revenue Growth | B6: 0.015 | C6: ='Operating Drivers'!E34 -> 0.028669518 | D6: 0.04 | E6: Mature growth convergence. | F6: Revenue
A7: FY31 Revenue Growth | B7: 0.015 | C7: ='Operating Drivers'!F34 -> 0.03 | D7: 0.04 | E7: Long-run mature growth. | F7: Revenue
A8: FY27 EBIT Margin | B8: 0.205 | C8: ='Operating Drivers'!B35 -> 0.20970599 | D8: 0.218 | E8: Q1 FY27 operating margin was 21.1%. | F8: EBIT margin
A9: FY28 EBIT Margin | B9: 0.205 | C9: ='Operating Drivers'!C35 -> 0.21046476 | D9: 0.22 | E9: Operating leverage/productivity. | F9: EBIT margin
A10: FY29 EBIT Margin | B10: 0.205 | C10: ='Operating Drivers'!D35 -> 0.21148651 | D10: 0.222 | E10: AI/productivity outcomes. | F10: EBIT margin
A11: FY30 EBIT Margin | B11: 0.205 | C11: ='Operating Drivers'!E35 -> 0.21210499 | D11: 0.223 | E11: Mature margin path. | F11: EBIT margin
A12: FY31 EBIT Margin | B12: 0.205 | C12: ='Operating Drivers'!F35 -> 0.21227656 | D12: 0.224 | E12: Long-run operating outcome. | F12: EBIT margin
A13: Terminal Growth | B13: 0.025 | C13: ='Operating Drivers'!$B$44 -> 0.03 | D13: 0.035 | E13: Long-run mature-growth range. | F13: Terminal value
A14: Terminal ROIC | B14: 0.35 | C14: ='Operating Drivers'!$B$45 -> 0.4 | D14: 0.45 | E14: ROIC normalizes from current elevated levels. | F14: Terminal reinvestment
A15: Terminal Reinvestment | B15: =B13/B14 -> 0.071428571 | C15: =C13/C14 -> 0.075 | D15: =D13/D14 -> 0.077777778 | E15: Formula-driven: g / terminal ROIC. | F15: Terminal value
A16: Normalized Tax Rate | B16: 0.295 | C16: ='Operating Drivers'!$B$38 -> 0.295 | D16: 0.295 | E16: Normalized effective tax assumption for FCFF. | F16: DCF
A18: Scenario interpretation
A19: Bear | B19: AI benefits slower; pricing pressure and weak discretionary demand.
A20: Base | B20: AI supports demand and productivity while margins remain broadly stable.
A21: Bull | B21: AI monetization, deal conversion and productivity support stronger growth and margins.

Sheet Scenarios
A1: INFOSYS LTD - Operating & Valuation Scenarios | J1: Scenario Valuation Summary
A2: Scenario analysis changes operating assumptions first; valuation is an output. Bear/Base/Bull assumptions are analyst estimates, not company guidance except where explicitly noted. | J2: Scenario | K2: Value / Share | L2: Upside / (Downside) | M2: Terminal g | N2: Terminal ROIC
J3: Bear | K3: =B29 -> 715.09872 | L3: =B30 -> -0.36208857 | M3: =B21 -> 0.025 | N3: =B22 -> 0.35
J4: Base | K4: =B59 -> 796.21701 | L4: =B60 -> -0.28972613 | M4: =B51 -> 0.03 | N4: =B52 -> 0.4
A5: Bear Case | J5: Bull | K5: =B89 -> 910.32941 | L5: =B90 -> -0.18793094 | M5: =B81 -> 0.035 | N5: =B82 -> 0.45
A6: Metric | B6: FY27 | C6: FY28 | D6: FY29 | E6: FY30 | F6: FY31
A7: Revenue Growth | B7: ='Forecast Scenarios'!B3 -> 0.015 | C7: ='Forecast Scenarios'!B4 -> 0.015 | D7: ='Forecast Scenarios'!B5 -> 0.015 | E7: ='Forecast Scenarios'!B6 -> 0.015 | F7: ='Forecast Scenarios'!B7 -> 0.015 | J7: Interpretation
A8: EBIT Margin | B8: ='Forecast Scenarios'!B8 -> 0.205 | C8: ='Forecast Scenarios'!B9 -> 0.205 | D8: ='Forecast Scenarios'!B10 -> 0.205 | E8: ='Forecast Scenarios'!B11 -> 0.205 | F8: ='Forecast Scenarios'!B12 -> 0.205 | J8: Bear: slower growth, margin pressure and lower steady-state returns.
A9: Target ROIC | B9: 0.4 | C9: 0.39 | D9: 0.38 | E9: 0.37 | F9: 0.35
A10: Reinvestment Rate | B10: =B7/B9 -> 0.0375 | C10: =C7/C9 -> 0.038461538 | D10: =D7/D9 -> 0.039473684 | E10: =E7/E9 -> 0.040540541 | F10: =F7/F9 -> 0.042857143
A11: Tax Rate | B11: ='Operating Drivers'!$B$38 -> 0.295 | C11: ='Operating Drivers'!$B$38 -> 0.295 | D11: ='Operating Drivers'!$B$38 -> 0.295 | E11: ='Operating Drivers'!$B$38 -> 0.295 | F11: ='Operating Drivers'!$B$38 -> 0.295
A12: FCFF (₹ Cr)
A13: PV of FCFF (₹ Cr)
A15: Revenue (₹ Cr) | B15: =HistoricalFS!$L$6*(1+B7) -> 181329.75 | C15: =B15*(1+C7) -> 184049.7 | D15: =C15*(1+D7) -> 186810.44 | E15: =D15*(1+E7) -> 189612.6 | F15: =E15*(1+F7) -> 192456.79
A16: EBIT (₹ Cr) | B16: =B15*B8 -> 37172.599 | C16: =C15*C8 -> 37730.188 | D16: =D15*D8 -> 38296.141 | E16: =E15*E8 -> 38870.583 | F16: =F15*F8 -> 39453.641
A17: NOPAT (₹ Cr) | B17: =B16*(1-B11) -> 26206.682 | C17: =C16*(1-C11) -> 26599.782 | D17: =D16*(1-D11) -> 26998.779 | E17: =E16*(1-E11) -> 27403.761 | F17: =F16*(1-F11) -> 27814.817
A18: Discount Factor | B18: =1/(1+WACC!$L$45)^0.5 -> 0.94663238 | C18: =1/(1+WACC!$L$45)^1.5 -> 0.84828945 | D18: =1/(1+WACC!$L$45)^2.5 -> 0.76016309 | E18: =1/(1+WACC!$L$45)^3.5 -> 0.68119192 | F18: =1/(1+WACC!$L$45)^4.5 -> 0.61042485
A19: PV of FCFF (₹ Cr) | B19: =B17*(1-B10)*B18 -> 23877.79 | C19: =C17*(1-C10)*C18 -> 21696.457 | D19: =D17*(1-D10)*D18 -> 19713.338 | E19: =E17*(1-E10)*E18 -> 17910.441 | F19: =F17*(1-F10)*F18 -> 16251.19
A21: Terminal Growth | B21: ='Forecast Scenarios'!B13 -> 0.025
A22: Terminal ROIC | B22: ='Forecast Scenarios'!B14 -> 0.35
A23: Terminal Reinvestment | B23: =B21/B22 -> 0.071428571
A24: Terminal FCFF | B24: =F17*(1-B23)*(1+B21) -> 26473.746
A25: Terminal Value | B25: =B24/(WACC!$L$45-B21) -> 291141.48
A26: PV Terminal Value | B26: =B25/(1+WACC!$L$45)^4.5 -> 177719.99
A27: PV Explicit FCFF | B27: =SUM(B19:F19) -> 99449.217
A28: Equity Value | B28: =B26+B27-'DCF>'!$D$43 -> 290194.21
A29: Value Per Share | B29: =B28/'DCF>'!$D$46 -> 715.09872
A30: Upside / (Downside) vs Current | B30: =B29/'DCF>'!$D$50-1 -> -0.36208857
A35: Base Case
A36: Metric | B36: FY27 | C36: FY28 | D36: FY29 | E36: FY30 | F36: FY31
A37: Revenue Growth | B37: ='Operating Drivers'!B34 -> 0.024580011 | C37: ='Operating Drivers'!C34 -> 0.025976365 | D37: ='Operating Drivers'!D34 -> 0.027325024 | E37: ='Operating Drivers'!E34 -> 0.028669518 | F37: ='Operating Drivers'!F34 -> 0.03
A38: EBIT Margin | B38: ='Operating Drivers'!B35 -> 0.20970599 | C38: ='Operating Drivers'!C35 -> 0.21046476 | D38: ='Operating Drivers'!D35 -> 0.21148651 | E38: ='Operating Drivers'!E35 -> 0.21210499 | F38: ='Operating Drivers'!F35 -> 0.21227656
A39: Target ROIC | B39: ='Operating Drivers'!B36 -> 0.45 | C39: ='Operating Drivers'!C36 -> 0.44 | D39: ='Operating Drivers'!D36 -> 0.43 | E39: ='Operating Drivers'!E36 -> 0.42 | F39: ='Operating Drivers'!F36 -> 0.4
A40: Reinvestment Rate | B40: =B37/B39 -> 0.054622247 | C40: =C37/C39 -> 0.059037192 | D40: =D37/D39 -> 0.063546568 | E40: =E37/E39 -> 0.068260756 | F40: =F37/F39 -> 0.075
A41: Tax Rate | B41: ='Operating Drivers'!$B$38 -> 0.295 | C41: ='Operating Drivers'!$B$38 -> 0.295 | D41: ='Operating Drivers'!$B$38 -> 0.295 | E41: ='Operating Drivers'!$B$38 -> 0.295 | F41: ='Operating Drivers'!$B$38 -> 0.295
A42: FCFF (₹ Cr)
A43: PV of FCFF (₹ Cr)
A45: Revenue (₹ Cr) | B45: =HistoricalFS!$L$6*(1+B37) -> 183041.22 | C45: =B45*(1+C37) -> 187795.96 | D45: =C45*(1+D37) -> 192927.49 | E45: =D45*(1+E37) -> 198458.63 | F45: =E45*(1+F37) -> 204412.39
A46: EBIT (₹ Cr) | B46: =B45*B38 -> 38384.84 | C46: =C45*C38 -> 39524.433 | D46: =D45*D38 -> 40801.562 | E46: =E45*E38 -> 42094.066 | F46: =F45*F38 -> 43391.96
A47: NOPAT (₹ Cr) | B47: =B46*(1-B41) -> 27061.312 | C47: =C46*(1-C41) -> 27864.725 | D47: =D46*(1-D41) -> 28765.101 | E47: =E46*(1-E41) -> 29676.317 | F47: =F46*(1-F41) -> 30591.332
A48: Discount Factor | B48: =1/(1+WACC!$L$45)^0.5 -> 0.94663238 | C48: =1/(1+WACC!$L$45)^1.5 -> 0.84828945 | D48: =1/(1+WACC!$L$45)^2.5 -> 0.76016309 | E48: =1/(1+WACC!$L$45)^3.5 -> 0.68119192 | F48: =1/(1+WACC!$L$45)^4.5 -> 0.61042485
A49: PV of FCFF (₹ Cr) | B49: =B47*(1-B40)*B48 -> 24217.85 | C49: =C47*(1-C40)*C48 -> 22241.869 | D49: =D47*(1-D40)*D48 -> 20476.648 | E49: =E47*(1-E40)*E48 -> 18835.358 | F49: =F47*(1-F40)*F48 -> 17273.181
A51: Terminal Growth | B51: ='Operating Drivers'!$B$44 -> 0.03
A52: Terminal ROIC | B52: ='Operating Drivers'!$B$45 -> 0.4
A53: Terminal Reinvestment | B53: =B51/B52 -> 0.075
A54: Terminal FCFF | B54: =F47*(1-B53)*(1+B51) -> 29145.891
A55: Terminal Value | B55: =B54/(WACC!$L$45-B51) -> 339178.39
A56: PV Terminal Value | B56: =B55/(1+WACC!$L$45)^4.5 -> 207042.92
A57: PV Explicit FCFF | B57: =SUM(B49:F49) -> 103044.91
A58: Equity Value | B58: =B56+B57-'DCF>'!$D$43 -> 323112.82
A59: Value Per Share | B59: =B58/'DCF>'!$D$46 -> 796.21701
A60: Upside / (Downside) vs Current | B60: =B59/'DCF>'!$D$50-1 -> -0.28972613
A65: Bull Case
A66: Metric | B66: FY27 | C66: FY28 | D66: FY29 | E66: FY30 | F66: FY31
A67: Revenue Growth | B67: ='Forecast Scenarios'!D3 -> 0.03 | C67: ='Forecast Scenarios'!D4 -> 0.045 | D67: ='Forecast Scenarios'!D5 -> 0.045 | E67: ='Forecast Scenarios'!D6 -> 0.04 | F67: ='Forecast Scenarios'!D7 -> 0.04
A68: EBIT Margin | B68: ='Forecast Scenarios'!D8 -> 0.218 | C68: ='Forecast Scenarios'!D9 -> 0.22 | D68: ='Forecast Scenarios'!D10 -> 0.222 | E68: ='Forecast Scenarios'!D11 -> 0.223 | F68: ='Forecast Scenarios'!D12 -> 0.224
A69: Target ROIC | B69: 0.49 | C69: 0.49 | D69: 0.48 | E69: 0.46 | F69: 0.45
A70: Reinvestment Rate | B70: =B67/B69 -> 0.06122449 | C70: =C67/C69 -> 0.091836735 | D70: =D67/D69 -> 0.09375 | E70: =E67/E69 -> 0.086956522 | F70: =F67/F69 -> 0.088888889
A71: Tax Rate | B71: ='Operating Drivers'!$B$38 -> 0.295 | C71: ='Operating Drivers'!$B$38 -> 0.295 | D71: ='Operating Drivers'!$B$38 -> 0.295 | E71: ='Operating Drivers'!$B$38 -> 0.295 | F71: ='Operating Drivers'!$B$38 -> 0.295
A72: FCFF (₹ Cr)
A73: PV of FCFF (₹ Cr)
A75: Revenue (₹ Cr) | B75: =HistoricalFS!$L$6*(1+B67) -> 184009.5 | C75: =B75*(1+C67) -> 192289.93 | D75: =C75*(1+D67) -> 200942.97 | E75: =D75*(1+E67) -> 208980.69 | F75: =E75*(1+F67) -> 217339.92
A76: EBIT (₹ Cr) | B76: =B75*B68 -> 40114.071 | C76: =C75*C68 -> 42303.784 | D76: =D75*D68 -> 44609.34 | E76: =E75*E68 -> 46602.695 | F76: =F75*F68 -> 48684.142
A77: NOPAT (₹ Cr) | B77: =B76*(1-B71) -> 28280.42 | C77: =C76*(1-C71) -> 29824.168 | D77: =D76*(1-D71) -> 31449.585 | E77: =E76*(1-E71) -> 32854.9 | F77: =F76*(1-F71) -> 34322.32
A78: Discount Factor | B78: =1/(1+WACC!$L$45)^0.5 -> 0.94663238 | C78: =1/(1+WACC!$L$45)^1.5 -> 0.84828945 | D78: =1/(1+WACC!$L$45)^2.5 -> 0.76016309 | E78: =1/(1+WACC!$L$45)^3.5 -> 0.68119192 | F78: =1/(1+WACC!$L$45)^4.5 -> 0.61042485
A79: PV of FCFF (₹ Cr) | B79: =B77*(1-B70)*B78 -> 25132.111 | C79: =C77*(1-C70)*C78 -> 22976.101 | D79: =D77*(1-D70)*D78 -> 21665.55 | E79: =E77*(1-E70)*E78 -> 20434.363 | F79: =F77*(1-F70)*F78 -> 19088.868
A81: Terminal Growth | B81: ='Forecast Scenarios'!D13 -> 0.035
A82: Terminal ROIC | B82: ='Forecast Scenarios'!D14 -> 0.45
A83: Terminal Reinvestment | B83: =B81/B82 -> 0.077777778
A84: Terminal FCFF | B84: =F77*(1-B83)*(1+B81) -> 32760.655
A85: Terminal Value | B85: =B84/(WACC!$L$45-B81) -> 404798.05
A86: PV Terminal Value | B86: =B85/(1+WACC!$L$45)^4.5 -> 247098.79
A87: PV Explicit FCFF | B87: =SUM(B79:F79) -> 109296.99
A88: Equity Value | B88: =B86+B87-'DCF>'!$D$43 -> 369420.78
A89: Value Per Share | B89: =B88/'DCF>'!$D$46 -> 910.32941
A90: Upside / (Downside) vs Current | B90: =B89/'DCF>'!$D$50-1 -> -0.18793094

Sheet Segment Forecast
A1: Infosys Segment Forecast
A2: ₹ crore | B2: FY25A | C2: FY26A | D2: FY27E | E2: FY28E | F2: FY29E | G2: FY30E | H2: FY31E
A3: Financial Services | B3: 45175 | C3: 49908 | D3: =C3*(1+'Operating Drivers'!E21) -> 51055.884 | E3: =D3*(1+((D3/C3-1)*75%+'Operating Drivers'!$B$17*25%)) -> 52319.517 | F3: =E3*(1+((E3/D3-1)*67%+'Operating Drivers'!$B$17*33%)) -> 53705.069 | G3: =F3*(1+((F3/E3-1)*50%+'Operating Drivers'!$B$17*50%)) -> 55221.767 | H3: =G3*(1+'Operating Drivers'!$B$17) -> 56878.42
A4: Manufacturing | B4: 25207 | C4: 29078 | D4: =C4*(1+'Operating Drivers'!E22) -> 30095.73 | E4: =D4*(1+((D4/C4-1)*75%+'Operating Drivers'!$B$17*25%)) -> 31111.461 | F4: =E4*(1+((E4/D4-1)*67%+'Operating Drivers'!$B$17*33%)) -> 32122.972 | G4: =F4*(1+((F4/E4-1)*50%+'Operating Drivers'!$B$17*50%)) -> 33127.016 | H4: =G4*(1+'Operating Drivers'!$B$17) -> 34120.826
A5: Retail | B5: 21710 | C5: 23818 | D5: =C5*(1+'Operating Drivers'!E23) -> 24365.814 | E5: =D5*(1+((D5/C5-1)*75%+'Operating Drivers'!$B$17*25%)) -> 24968.868 | F5: =E5*(1+((E5/D5-1)*67%+'Operating Drivers'!$B$17*33%)) -> 25630.106 | G5: =F5*(1+((F5/E5-1)*50%+'Operating Drivers'!$B$17*50%)) -> 26353.932 | H5: =G5*(1+'Operating Drivers'!$B$17) -> 27144.55
A6: Energy, Utilities, Resources & Services | B6: 22059 | C6: 23077 | D6: =C6*(1+'Operating Drivers'!E24) -> 23492.386 | E6: =D6*(1+((D6/C6-1)*75%+'Operating Drivers'!$B$17*25%)) -> 23985.726 | F6: =E6*(1+((E6/D6-1)*67%+'Operating Drivers'!$B$17*33%)) -> 24560.664 | G6: =F6*(1+((F6/E6-1)*50%+'Operating Drivers'!$B$17*50%)) -> 25223.433 | H6: =G6*(1+'Operating Drivers'!$B$17) -> 25980.136
A7: Communication | B7: 19108 | C7: 21765 | D7: =C7*(1+'Operating Drivers'!E25) -> 22091.475 | E7: =D7*(1+((D7/C7-1)*75%+'Operating Drivers'!$B$17*25%)) -> 22505.69 | F7: =E7*(1+((E7/D7-1)*67%+'Operating Drivers'!$B$17*33%)) -> 23011.224 | G7: =F7*(1+((F7/E7-1)*50%+'Operating Drivers'!$B$17*50%)) -> 23614.837 | H7: =G7*(1+'Operating Drivers'!$B$17) -> 24323.283
A8: Hi-Tech | B8: 13090 | C8: 13928 | D8: =C8*(1+'Operating Drivers'!E26) -> 14485.12 | E8: =D8*(1+((D8/C8-1)*75%+'Operating Drivers'!$B$17*25%)) -> 15028.312 | F8: =E8*(1+((E8/D8-1)*67%+'Operating Drivers'!$B$17*33%)) -> 15554.679 | G8: =F8*(1+((F8/E8-1)*50%+'Operating Drivers'!$B$17*50%)) -> 16060.4 | H8: =G8*(1+'Operating Drivers'!$B$17) -> 16542.212
A9: Life Sciences | B9: 11831 | C9: 12267 | D9: =C9*(1+'Operating Drivers'!E27) -> 12573.675 | E9: =D9*(1+((D9/C9-1)*75%+'Operating Drivers'!$B$17*25%)) -> 12903.734 | F9: =E9*(1+((E9/D9-1)*67%+'Operating Drivers'!$B$17*33%)) -> 13258.425 | G9: =F9*(1+((F9/E9-1)*50%+'Operating Drivers'!$B$17*50%)) -> 13639.522 | H9: =G9*(1+'Operating Drivers'!$B$17) -> 14048.708
A10: All other segments | B10: 4810 | C10: 4809 | D10: =C10*(1+'Operating Drivers'!E28) -> 4881.135 | E10: =D10*(1+((D10/C10-1)*75%+'Operating Drivers'!$B$17*25%)) -> 4972.6563 | F10: =E10*(1+((E10/D10-1)*67%+'Operating Drivers'!$B$17*33%)) -> 5084.3546 | G10: =F10*(1+((F10/E10-1)*50%+'Operating Drivers'!$B$17*50%)) -> 5217.7235 | H10: =G10*(1+'Operating Drivers'!$B$17) -> 5374.2553
A11: Total Revenue | B11: =SUM(B3:B10) -> 162990 | C11: =SUM(C3:C10) -> 178650 | D11: =SUM(D3:D10) -> 183041.22 | E11: =SUM(E3:E10) -> 187795.96 | F11: =SUM(F3:F10) -> 192927.49 | G11: =SUM(G3:G10) -> 198458.63 | H11: =SUM(H3:H10) -> 204412.39
A12: YoY Growth | C12: =C11/B11-1 -> 0.096079514 | D12: =D11/C11-1 -> 0.024580011 | E12: =E11/D11-1 -> 0.025976365 | F12: =F11/E11-1 -> 0.027325024 | G12: =G11/F11-1 -> 0.028669518 | H12: =H11/G11-1 -> 0.03
A14: Integrated Forecast Revenue | D14: =Forecasting!R5 -> 183041.22 | E14: =Forecasting!S5 -> 187795.96 | F14: =Forecasting!T5 -> 192927.49 | G14: =Forecasting!U5 -> 198458.63 | H14: =Forecasting!V5 -> 204412.39
A15: Segment / Integrated Difference | D15: =D11-D14 -> 0 | E15: =E11-E14 -> 0 | F15: =F11-F14 -> 0 | G15: =G11-G14 -> 0 | H15: =H11-H14 -> 0
A17: Methodology / Source | B17: FY25/FY26 segment revenue is sourced from Infosys FY26 Integrated Annual Report, Business segments (p. 387). FY27 segment growth assumptions are analyst inputs from Operating Drivers. FY28-FY31 normalize each segment toward 3.0% mature growth using a transparent convergence formula.

Sheet Segment Profitability
A1: Infosys Segment Profitability Forecast
A2: ₹ crore | B2: FY26A | C2: FY27E | D2: FY28E | E2: FY29E | F2: FY30E | G2: FY31E
A3: Financial Services | B3: ='Segment Forecast'!C3 -> 49908 | C3: ='Segment Forecast'!D3 -> 51055.884 | D3: ='Segment Forecast'!E3 -> 52319.517 | E3: ='Segment Forecast'!F3 -> 53705.069 | F3: ='Segment Forecast'!G3 -> 55221.767 | G3: ='Segment Forecast'!H3 -> 56878.42
A4: Manufacturing | B4: ='Segment Forecast'!C4 -> 29078 | C4: ='Segment Forecast'!D4 -> 30095.73 | D4: ='Segment Forecast'!E4 -> 31111.461 | E4: ='Segment Forecast'!F4 -> 32122.972 | F4: ='Segment Forecast'!G4 -> 33127.016 | G4: ='Segment Forecast'!H4 -> 34120.826
A5: Retail | B5: ='Segment Forecast'!C5 -> 23818 | C5: ='Segment Forecast'!D5 -> 24365.814 | D5: ='Segment Forecast'!E5 -> 24968.868 | E5: ='Segment Forecast'!F5 -> 25630.106 | F5: ='Segment Forecast'!G5 -> 26353.932 | G5: ='Segment Forecast'!H5 -> 27144.55
A6: Energy, Utilities, Resources & Services | B6: ='Segment Forecast'!C6 -> 23077 | C6: ='Segment Forecast'!D6 -> 23492.386 | D6: ='Segment Forecast'!E6 -> 23985.726 | E6: ='Segment Forecast'!F6 -> 24560.664 | F6: ='Segment Forecast'!G6 -> 25223.433 | G6: ='Segment Forecast'!H6 -> 25980.136
A7: Communication | B7: ='Segment Forecast'!C7 -> 21765 | C7: ='Segment Forecast'!D7 -> 22091.475 | D7: ='Segment Forecast'!E7 -> 22505.69 | E7: ='Segment Forecast'!F7 -> 23011.224 | F7: ='Segment Forecast'!G7 -> 23614.837 | G7: ='Segment Forecast'!H7 -> 24323.283
A8: Hi-Tech | B8: ='Segment Forecast'!C8 -> 13928 | C8: ='Segment Forecast'!D8 -> 14485.12 | D8: ='Segment Forecast'!E8 -> 15028.312 | E8: ='Segment Forecast'!F8 -> 15554.679 | F8: ='Segment Forecast'!G8 -> 16060.4 | G8: ='Segment Forecast'!H8 -> 16542.212
A9: Life Sciences | B9: ='Segment Forecast'!C9 -> 12267 | C9: ='Segment Forecast'!D9 -> 12573.675 | D9: ='Segment Forecast'!E9 -> 12903.734 | E9: ='Segment Forecast'!F9 -> 13258.425 | F9: ='Segment Forecast'!G9 -> 13639.522 | G9: ='Segment Forecast'!H9 -> 14048.708
A10: All Other | B10: ='Segment Forecast'!C10 -> 4809 | C10: ='Segment Forecast'!D10 -> 4881.135 | D10: ='Segment Forecast'!E10 -> 4972.6563 | E10: ='Segment Forecast'!F10 -> 5084.3546 | F10: ='Segment Forecast'!G10 -> 5217.7235 | G10: ='Segment Forecast'!H10 -> 5374.2553
A13: Financial Services Margin | B13: 0.253 | C13: 0.253 | D13: 0.254 | E13: 0.255 | F13: 0.255 | G13: 0.255
A14: Manufacturing Margin | B14: 0.221 | C14: 0.222 | D14: 0.223 | E14: 0.224 | F14: 0.225 | G14: 0.225
A15: Retail Margin | B15: 0.251 | C15: 0.25 | D15: 0.25 | E15: 0.251 | F15: 0.252 | G15: 0.252
A16: Energy, Utilities, Resources & Services Margin | B16: 0.307 | C16: 0.305 | D16: 0.305 | E16: 0.306 | F16: 0.306 | G16: 0.306
A17: Communication Margin | B17: 0.177 | C17: 0.178 | D17: 0.179 | E17: 0.18 | F17: 0.181 | G17: 0.182
A18: Hi-Tech Margin | B18: 0.231 | C18: 0.232 | D18: 0.233 | E18: 0.234 | F18: 0.235 | G18: 0.235
A19: Life Sciences Margin | B19: 0.2 | C19: 0.201 | D19: 0.202 | E19: 0.203 | F19: 0.204 | G19: 0.204
A20: All Other Margin | B20: 0.148 | C20: 0.15 | D20: 0.152 | E20: 0.154 | F20: 0.156 | G20: 0.158
A22: Segment Operating Income
A23: Financial Services | B23: 12678 | C23: =C3*C13 -> 12917.139 | D23: =D3*D13 -> 13289.157 | E23: =E3*E13 -> 13694.793 | F23: =F3*F13 -> 14081.551 | G23: =G3*G13 -> 14503.997
A24: Manufacturing | B24: 6444 | C24: =C4*C14 -> 6681.2521 | D24: =D4*D14 -> 6937.8558 | E24: =E4*E14 -> 7195.5458 | F24: =F4*F14 -> 7453.5786 | G24: =G4*G14 -> 7677.1859
A25: Retail | B25: 5984 | C25: =C5*C15 -> 6091.4535 | D25: =D5*D15 -> 6242.217 | E25: =E5*E15 -> 6433.1566 | F25: =F5*F15 -> 6641.1909 | G25: =G5*G15 -> 6840.4266
A26: Energy, Utilities, Resources & Services | B26: 7089 | C26: =C6*C16 -> 7165.1777 | D26: =D6*D16 -> 7315.6465 | E26: =E6*E16 -> 7515.5632 | F26: =F6*F16 -> 7718.3706 | G26: =G6*G16 -> 7949.9218
A27: Communication | B27: 3861 | C27: =C7*C17 -> 3932.2825 | D27: =D7*D17 -> 4028.5185 | E27: =E7*E17 -> 4142.0204 | F27: =F7*F17 -> 4274.2856 | G27: =G7*G17 -> 4426.8374
A28: Hi-Tech | B28: 3228 | C28: =C8*C18 -> 3360.5478 | D28: =D8*D18 -> 3501.5967 | E28: =E8*E18 -> 3639.7948 | F28: =F8*F18 -> 3774.194 | G28: =G8*G18 -> 3887.4198
A29: Life Sciences | B29: 2444 | C29: =C9*C19 -> 2527.3087 | D29: =D9*D19 -> 2606.5543 | E29: =E9*E19 -> 2691.4603 | F29: =F9*F19 -> 2782.4625 | G29: =G9*G19 -> 2865.9364
A30: All Other | B30: 717 | C30: =C10*C20 -> 732.17025 | D30: =D10*D20 -> 755.84375 | E30: =E10*E20 -> 782.9906 | F30: =F10*F20 -> 813.96487 | G30: =G10*G20 -> 849.13233
A31: Total Segment Revenue | B31: =SUM(B3:B10) -> 178650 | C31: =SUM(C3:C10) -> 183041.22 | D31: =SUM(D3:D10) -> 187795.96 | E31: =SUM(E3:E10) -> 192927.49 | F31: =SUM(F3:F10) -> 198458.63 | G31: =SUM(G3:G10) -> 204412.39
A32: Total Segment Operating Income | B32: =SUM(B23:B30) -> 42445 | C32: =SUM(C23:C30) -> 43407.331 | D32: =SUM(D23:D30) -> 44677.39 | E32: =SUM(E23:E30) -> 46095.324 | F32: =SUM(F23:F30) -> 47539.598 | G32: =SUM(G23:G30) -> 49000.857
A33: Implied Segment Operating Margin | B33: =B32/B31 -> 0.23758746 | C33: =C32/C31 -> 0.23714512 | D33: =D32/D31 -> 0.23790389 | E33: =E32/E31 -> 0.23892564 | F33: =F32/F31 -> 0.23954412 | G33: =G32/G31 -> 0.23971569

Sheet AI & Business Outlook
A1: Infosys AI & Business Outlook
A2: Theme | B2: Base-case implication | C2: Bear-case implication | D2: Bull-case implication
A3: AI monetization | B3: Supports demand for AI/data/cloud services | C3: AI adoption creates pricing pressure before new revenue scales | D3: Accelerated AI services adoption adds incremental growth
A4: Productivity | B4: Supports operating leverage over time | C4: Productivity benefits accrue mainly to clients | D4: Productivity plus pricing discipline supports margin expansion
A5: Large deals | B5: Sustains medium-term visibility | C5: Slower discretionary IT spending delays conversion | D5: Strong large-deal conversion accelerates revenue
A6: Margins | B6: Stable to modestly improving | C6: Pricing and utilization pressure | D6: Higher utilization and productivity expand EBIT margin
A7: Key risks | B7: Client concentration, FX, macro IT spending | C7: AI cannibalization, pricing pressure, weak demand | D7: Execution capacity and talent constraints
A8: Model linkage | B8: Revenue growth and EBIT margin assumptions | C8: Lower revenue growth + lower margin | D8: Higher revenue growth + higher margin
A10: Research framing | B10: AI is treated as an operating driver, not as a standalone valuation premium.
A11: Model linkage | B11: These qualitative cases are translated into explicit segment growth and EBIT-margin assumptions in Forecast Scenarios and Segment Profitability.

Sheet Normalization Bridge
A1: FY26 EBIT Normalization Bridge
A2: Item | B2: ₹ crore
A3: Reported FY26 operating profit | B3: 36254
A4: Labour-code provision | B4: 1289
A5: Implied pre-provision operating profit | B5: =B3+B4 -> 37543
A6: Reported operating margin | B6: =B3/'Operating Drivers'!B5 -> 0.20293311
A7: Adjusted operating margin (company-reported) | B7: =B5/'Operating Drivers'!B5 -> 0.21014833
A8: Analytical implication | B8: Use the reported operating profit plus the identified one-off labour-code provision to normalize FY26 consolidated EBIT.
A9: Current model treatment | B9: FY27E onward is built bottom-up from segment operating income less normalized corporate/unallocated costs.
A10: Reason | B10: The corporate/unallocated cost bridge is anchored to FY26 normalized EBIT and held as a percentage of revenue unless explicitly changed.
A11: Reported FY26 Unallocable Expenses | B11: 6191
A12: Normalized FY26 Unallocable Expenses | B12: =B11-B4 -> 4902
A13: Source | B13: Infosys FY26 Integrated Annual Report, Business Segments, p.387

Sheet WACC
A1: ='Data Sheet'!B1&" - WACC" -> INFOSYS LTD - WACC
B6: Weighted Average Cost of Capital
B8: All figures are in INR unless stated otherwise
B10: Peer Comps
G11: Debt / | H11: Debt / | I11: Levered | J11: Unlevered
B12: Name of the Comp | C12: Country | D12: Total Debt | E12: Total Equity | F12: Tax Rate 1 | G12: Equity | H12: Capital | I12: Beta 2 | J12: Beta 3
B14: Infosys | C14: India | D14: ='Data Sheet'!$K$59 -> 9176 | E14: ='Data Sheet'!$B$9 -> 454908.14 | F14: 0.25 | G14: =D14/E14 -> 0.020171105 | H14: =D14/(D14+E14) -> 0.019772277 | I14: ='Beta - Regression'!N11 -> 0.72659478 | J14: =I14/(1+(1-F14)*G14) -> 0.71576643
B15: TCS | C15: India | D15: 11283 | E15: 832883.75 | F15: 0.3 | G15: =D15/E15 -> 0.013546909 | H15: =D15/(D15+E15) -> 0.013365843 | I15: ='Peer - Beta Regression'!E116 -> 0.88127552 | J15: =I15/(1+(1-F15)*G15) -> 0.87299703
B16: HCL Technologies | C16: India | D16: 5215 | E16: 353454.88 | F16: 0.3 | G16: =D16/E16 -> 0.014754358 | H16: =D16/(D16+E16) -> 0.014539833 | I16: ='Peer - Beta Regression'!H116 -> 0.81276296 | J16: =I16/(1+(1-F16)*G16) -> 0.80445451
B17: Wipro | C17: India | D17: 20291 | E17: 179064.13 | F17: 0.3 | G17: =D17/E17 -> 0.11331694 | H17: =D17/(D17+E17) -> 0.10178318 | I17: ='Peer - Beta Regression'!K116 -> 0.744671 | J17: =I17/(1+(1-F17)*G17) -> 0.68994341
B18: Tech Mahindra | C18: India | D18: 2186.2 | E18: 155245.43 | F18: 0.3 | G18: =D18/E18 -> 0.014082218 | H18: =D18/(D18+E18) -> 0.013886663 | I18: ='Peer - Beta Regression'!N116 -> 0.71337806 | J18: =I18/(1+(1-F18)*G18) -> 0.70641454
B19: LTM | C19: India | D19: 2310 | E19: 133117.72 | F19: 0.3 | G19: =D19/E19 -> 0.017353062 | H19: =D19/(D19+E19) -> 0.017057069 | I19: ='Peer - Beta Regression'!Q116 -> 1.1723379 | J19: =I19/(1+(1-F19)*G19) -> 1.1582682
E21: Average | F21: =AVERAGE(F15:F19) -> 0.3 | G21: =AVERAGE(G15:G19) -> 0.034610698 | H21: =AVERAGE(H15:H19) -> 0.032126518 | I21: =AVERAGE(I15:I19) -> 0.86488508 | J21: =AVERAGE(J15:J19) -> 0.84641554
E22: Median | F22: =MEDIAN(F15:F19) -> 0.3 | G22: =MEDIAN(G15:G19) -> 0.014754358 | H22: =MEDIAN(H15:H19) -> 0.014539833 | I22: =MEDIAN(I15:I19) -> 0.81276296 | J22: =MEDIAN(J15:J19) -> 0.80445451
B25: Cost of Debt | H25: Cost of Equity
B27: Pre-Tax Cost of Debt | E27: =HistoricalFS!L21/D14 -> 0.045335658 | H27: Risk Free Rate | K27: 0.0677 | L27: Source: India benchmark 10Y G-Sec yield; 6.768% on 6 Aug 2026, rounded to 6.77%.
B28: Tax Rate (Target Company) | E28: 0.2517 | H28: Equity Risk Premium | K28: =Rm!F11-WACC!K27 -> 0.061803341 | L28: Calculated from Rm!F11 less the 6.77% risk-free rate.
B29: Post Tax Cost of Debt | E29: =E27*(1-E28) -> 0.033924673 | H29: Levered Beta 4 | K29: =K38 -> 0.82443575 | L29: Peer-relevered beta from WACC K38.
H30: Cost of Equity | K30: =K27+K28*K29 -> 0.11865288 | L30: CAPM: Rf + Beta × ERP.
B33: Capital Structure | H33: Levered Beta
D35: Current | E35: Target | H35: Comps Median Unlevered Beta | K35: =J22 -> 0.80445451
B36: Total Debt | C36: =D14 -> 9176 | D36: =C36/$C$38 -> 0.019772277 | E36: =H21 -> 0.032126518 | F36: Peer average (ex-Infosys) | H36: Target Debt / Equity | K36: =E40 -> 0.03319289
B37: Market Capitalization | C37: =E14 -> 454908.14 | D37: =C37/$C$38 -> 0.98022772 | E37: =E38-E36 -> 0.96787348 | H37: Tax Rate | K37: =E28 -> 0.2517
B38: Total Capital | C38: =SUM(C36:C37) -> 464084.14 | D38: =C38/$C$38 -> 1 | E38: =D38 -> 1 | H38: Levered Beta | K38: =K35*(1+(1-K37)*K36) -> 0.82443575
B40: Debt / Equity | D40: =D36/D37 -> 0.020171105 | E40: =E36/E37 -> 0.03319289 | H40: Weighted Average Cost of Capital
B42: Notes: | K42: Total Cost | L42: Total Weight
B43: 1. Tax Rates considered as Marginal Tax Rate for the country | H43: Debt | K43: =E29 -> 0.033924673 | L43: =E36 -> 0.032126518
B44: 2. Beta is bottom-up: peer regression betas (TCS, HCL Tech, Wipro, Tech Mahindra, LTIMindtree) are unlevered, the median (0.804) is taken, and re-levered at Infosys's capital structure to 0.824 (see K35-K38). The own-stock 2-year weekly regression on 'Beta - Regression' (R^2 ~ 0.14) is shown for reference only and is deliberately NOT used in the WACC. | H44: Equity | K44: =K30 -> 0.11865288 | L44: =E37 -> 0.96787348
B45: 3. Unlevered Beta = Levered Beta / (1+(1 - Tax Rate)*Debt/Equity | H45: Weighted Average Cost of Capital | L45: =SUMPRODUCT(K43:K44,L43:L44) -> 0.11593086
B46: 4. Levered Beta = Unlevered Beta * (1+(1 - Tax Rate)*Debt/Equity

Sheet Beta - Regression
B5: Regression Beta — 2 Years Weekly (through valuation date)
B7: Infosys Weekly Returns | F7: NIFTY Returns | J7: Beta Drifiting | M7: Beta 1 | N7: =SLOPE(D11:D114,H11:H114) -> 0.72659478
M8: Beta 2 | N8: =_xlfn.COVARIANCE.S(D11:D114,H11:H114)/_xlfn.VAR.S(H11:H114) -> 0.72659478
B9: Date | C9: Price | D9: Return | F9: Date | G9: Closing Price | H9: Return | J9: Levered Raw Beta | K9: =N11 -> 0.72659478
B10: 45522 | C10: 1862.1 | F10: 45522 | G10: 24823.15 | J10: Raw Beta Weight | K10: 0.75
B11: 45529 | C11: 1943.7 | D11: =C11/C10-1 -> 0.043821492 | F11: 45529 | G11: 25235.9 | H11: =G11/G10-1 -> 0.016627624 | M11: Beta 3 | N11: =N32 -> 0.72659478
B12: 45536 | C12: 1901.85 | D12: =C12/C11-1 -> -0.0215311 | F12: 45536 | G12: 24852.15 | H12: =G12/G11-1 -> -0.015206511 | J12: Market Beta | K12: 1
B13: 45543 | C13: 1944.1 | D13: =C13/C12-1 -> 0.022215212 | F13: 45543 | G13: 25356.5 | H13: =G13/G12-1 -> 0.020294019 | J13: Market Beta Weight | K13: 0.25
B14: 45550 | C14: 1905.75 | D14: =C14/C13-1 -> -0.019726352 | F14: 45550 | G14: 25790.95 | H14: =G14/G13-1 -> 0.017133674
B15: 45557 | C15: 1906.75 | D15: =C15/C14-1 -> 0.0005247278 | F15: 45557 | G15: 26178.95 | H15: =G15/G14-1 -> 0.015044037 | J15: Adjusted Beta | K15: =(K9*K10)+(K12*K13) -> 0.79494608 | M15: SUMMARY OUTPUT
B16: 45564 | C16: 1918.15 | D16: =C16/C15-1 -> 0.0059787597 | F16: 45564 | G16: 25014.6 | H16: =G16/G15-1 -> -0.044476574
B17: 45571 | C17: 1935.1 | D17: =C17/C16-1 -> 0.0088366395 | F17: 45571 | G17: 24964.25 | H17: =G17/G16-1 -> -0.0020128245 | M17: Regression Statistics
B18: 45578 | C18: 1879.6 | D18: =C18/C17-1 -> -0.028680688 | F18: 45578 | G18: 24854.05 | H18: =G18/G17-1 -> -0.0044143125 | M18: Multiple R | N18: =CORREL(D11:D114,H11:H114) -> 0.36601952
B19: 45585 | C19: 1862.05 | D19: =C19/C18-1 -> -0.009337093 | F19: 45585 | G19: 24180.8 | H19: =G19/G18-1 -> -0.027088141 | M19: R Square | N19: =N18^2 -> 0.13397029
B20: 45592 | C20: 1760.85 | D20: =C20/C19-1 -> -0.054348702 | F20: 45592 | G20: 24304.35 | H20: =G20/G19-1 -> 0.0051094257 | M20: Adjusted R Square | N20: =1-(1-N19)*(COUNT(D11:D114)-1)/(COUNT(D11:D114)-2) -> 0.1254798
B21: 45599 | C21: 1829.95 | D21: =C21/C20-1 -> 0.039242411 | F21: 45599 | G21: 24148.2 | H21: =G21/G20-1 -> -0.0064247758 | M21: Standard Error | N21: =STEYX(D11:D114,H11:H114) -> 0.034050939
B22: 45606 | C22: 1864.55 | D22: =C22/C21-1 -> 0.01890762 | F22: 45606 | G22: 23532.7 | H22: =G22/G21-1 -> -0.025488442 | M22: Observations | N22: =COUNT(D11:D114) -> 104
B23: 45613 | C23: 1902.25 | D23: =C23/C22-1 -> 0.020219356 | F23: 45613 | G23: 23907.25 | H23: =G23/G22-1 -> 0.015916151
B24: 45620 | C24: 1857.85 | D24: =C24/C23-1 -> -0.023340781 | F24: 45620 | G24: 24131.1 | H24: =G24/G23-1 -> 0.0093632685 | M24: ANOVA
B25: 45627 | C25: 1922.4 | D25: =C25/C24-1 -> 0.034744463 | F25: 45627 | G25: 24677.8 | H25: =G25/G24-1 -> 0.022655411 | N25: df | O25: SS | P25: MS | Q25: F | R25: Significance F
B26: 45634 | C26: 1999.7 | D26: =C26/C25-1 -> 0.040210154 | F26: 45634 | G26: 24768.3 | H26: =G26/G25-1 -> 0.0036672637 | M26: Regression | N26: 1 | O26: 0.020205569 | P26: 0.020205569 | Q26: 19.859216 | R26: 2.143059e-05
B27: 45641 | C27: 1922.15 | D27: =C27/C26-1 -> -0.038780817 | F27: 45641 | G27: 23587.5 | H27: =G27/G26-1 -> -0.047673841 | M27: Residual | N27: 102 | O27: 0.10377892 | P27: 0.0010174404
B28: 45648 | C28: 1916.75 | D28: =C28/C27-1 -> -0.0028093541 | F28: 45648 | G28: 23813.4 | H28: =G28/G27-1 -> 0.0095771065 | M28: Total | N28: 103 | O28: 0.12398449
B29: 45655 | C29: 1938.75 | D29: =C29/C28-1 -> 0.011477762 | F29: 45655 | G29: 24004.75 | H29: =G29/G28-1 -> 0.0080353918
B30: 45662 | C30: 1966.95 | D30: =C30/C29-1 -> 0.014545455 | F30: 45662 | G30: 23431.5 | H30: =G30/G29-1 -> -0.02388069 | N30: Coefficients | O30: Standard Error | P30: t Stat | Q30: P-value | R30: Lower 95% | S30: Upper 95% | T30: Lower 95.0% | U30: Upper 95.0%
B31: 45669 | C31: 1815.45 | D31: =C31/C30-1 -> -0.077022802 | F31: 45669 | G31: 23203.2 | H31: =G31/G30-1 -> -0.0097432943 | M31: Intercept | N31: -0.0021516804 | O31: 0.0031326441 | P31: -0.6868576 | Q31: 0.49373109 | R31: -0.008365265 | S31: 0.0040619043 | T31: -0.008365265 | U31: 0.0040619043
B32: 45676 | C32: 1875.45 | D32: =C32/C31-1 -> 0.033049657 | F32: 45676 | G32: 23092.2 | H32: =G32/G31-1 -> -0.0047838229 | M32: X Variable 1 | N32: =O32 -> 0.72659478 | O32: =SLOPE(D11:D114,H11:H114) -> 0.72659478 | P32: 4.4563681 | Q32: 2.143059e-05 | R32: 0.4550535 | S32: 1.1850518 | T32: 0.4550535 | U32: 1.1850518
B33: 45683 | C33: 1879.8 | D33: =C33/C32-1 -> 0.0023194433 | F33: 45683 | G33: 23508.4 | H33: =G33/G32-1 -> 0.018023402
B34: 45690 | C34: 1903.65 | D34: =C34/C33-1 -> 0.01268752 | F34: 45690 | G34: 23559.95 | H34: =G34/G33-1 -> 0.0021928332
B35: 45697 | C35: 1856.4 | D35: =C35/C34-1 -> -0.024820739 | F35: 45697 | G35: 22929.25 | H35: =G35/G34-1 -> -0.026770006
B36: 45704 | C36: 1815 | D36: =C36/C35-1 -> -0.022301228 | F36: 45704 | G36: 22795.9 | H36: =G36/G35-1 -> -0.0058157157
B37: 45711 | C37: 1687.7 | D37: =C37/C36-1 -> -0.070137741 | F37: 45711 | G37: 22124.7 | H37: =G37/G36-1 -> -0.029443891
B38: 45718 | C38: 1686 | D38: =C38/C37-1 -> -0.001007288 | F38: 45718 | G38: 22552.5 | H38: =G38/G37-1 -> 0.019335855
B39: 45725 | C39: 1579.85 | D39: =C39/C38-1 -> -0.062959668 | F39: 45725 | G39: 22397.2 | H39: =G39/G38-1 -> -0.0068861545
B40: 45732 | C40: 1592.55 | D40: =C40/C39-1 -> 0.0080387379 | F40: 45732 | G40: 23350.4 | H40: =G40/G39-1 -> 0.042558891
B41: 45739 | C41: 1570.65 | D41: =C41/C40-1 -> -0.013751531 | F41: 45739 | G41: 23519.35 | H41: =G41/G40-1 -> 0.0072354221
B42: 45746 | C42: 1451.65 | D42: =C42/C41-1 -> -0.075764811 | F42: 45746 | G42: 22904.45 | H42: =G42/G41-1 -> -0.02614443
B43: 45753 | C43: 1409.45 | D43: =C43/C42-1 -> -0.029070368 | F43: 45753 | G43: 22828.55 | H43: =G43/G42-1 -> -0.0033137665
B44: 45760 | C44: 1419.5 | D44: =C44/C43-1 -> 0.007130441 | F44: 45760 | G44: 23851.65 | H44: =G44/G43-1 -> 0.044816688
... B114: 46250 | C114: 1121 | D114: =C114/C113-1 -> -0.041224769 | F114: 46250 | G114: 24252 | H114: =G114/G113-1 -> -0.0046786506

Sheet Peer - Beta Regression
B5: Regression Beta - 2 Years Weekly
D7: TCS Weekly Returns | G7: HCL Tech Weekly Returns | J7: Wipro Weekly Returns | M7: Tech Mahindra Weekly Returns | P7: LTM Weekly Returns | S7: NIFTY Returns
B8: Date | D8: Price | E8: Return | G8: Price | H8: Return | J8: Price | K8: Return | M8: Price | N8: Return | P8: Price | Q8: Return | S8: Date | T8: Closing Price | U8: Return
B10: 45522 | D10: 4393.86 | G10: 1655.89 | J10: 256.2 | M10: 1598.4 | P10: 5641.6 | S10: 45522 | T10: 24823.15
B11: 45529 | D11: 4482.3 | E11: =D11/D10-1 -> 0.020128088 | G11: 1747.38 | H11: =G11/G10-1 -> 0.055251255 | J11: 269.2 | K11: =J11/J10-1 -> 0.050741608 | M11: 1636.5 | N11: =M11/M10-1 -> 0.023836336 | P11: 6156.05 | Q11: =P11/P10-1 -> 0.09118867 | S11: 45529 | T11: 25235.9 | U11: =T11/T10-1 -> 0.016627624
B12: 45536 | D12: 4386.82 | E12: =D12/D11-1 -> -0.021301564 | G12: 1750.22 | H12: =G12/G11-1 -> 0.0016252904 | J12: 260.3 | K12: =J12/J11-1 -> -0.033060921 | M12: 1623.25 | N12: =M12/M11-1 -> -0.0080965475 | P12: 6165.4 | Q12: =P12/P11-1 -> 0.0015188311 | S12: 45536 | T12: 24852.15 | U12: =T12/T11-1 -> -0.015206511
B13: 45543 | D13: 4451.64 | E13: =D13/D12-1 -> 0.014776079 | G13: 1806.73 | H13: =G13/G12-1 -> 0.03228737 | J13: 275.3 | K13: =J13/J12-1 -> 0.057625816 | M13: 1656.05 | N13: =M13/M12-1 -> 0.020206376 | P13: 6416.2 | Q13: =P13/P12-1 -> 0.040678626 | S13: 45543 | T13: 25356.5 | U13: =T13/T12-1 -> 0.020294019
B14: 45550 | D14: 4217.67 | E14: =D14/D13-1 -> -0.052558158 | G14: 1754.16 | H14: =G14/G13-1 -> -0.029096766 | J14: 269.55 | K14: =J14/J13-1 -> -0.020886306 | M14: 1622.05 | N14: =M14/M13-1 -> -0.020530781 | P14: 6373.1 | Q14: =P14/P13-1 -> -0.0067173717 | S14: 45550 | T14: 25790.95 | U14: =T14/T13-1 -> 0.017133674
B15: 45557 | D15: 4241.09 | E15: =D15/D14-1 -> 0.0055528289 | G15: 1802.34 | H15: =G15/G14-1 -> 0.027466138 | J15: 270.9 | K15: =J15/J14-1 -> 0.0050083472 | M15: 1609.25 | N15: =M15/M14-1 -> -0.0078912487 | P15: 6136.1 | Q15: =P15/P14-1 -> -0.037187554 | S15: 45557 | T15: 26178.95 | U15: =T15/T14-1 -> 0.015044037
B16: 45564 | D16: 4185.53 | E16: =D16/D15-1 -> -0.013100406 | G16: 1770.65 | H16: =G16/G15-1 -> -0.017582698 | J16: 266.77 | K16: =J16/J15-1 -> -0.015245478 | M16: 1616.45 | N16: =M16/M15-1 -> 0.0044741339 | P16: 6114.1 | Q16: =P16/P15-1 -> -0.0035853392 | S16: 45564 | T16: 25014.6 | U16: =T16/T15-1 -> -0.044476574
B17: 45571 | D17: 4084.09 | E17: =D17/D16-1 -> -0.024235879 | G17: 1833.49 | H17: =G17/G16-1 -> 0.035489792 | J17: 264.15 | K17: =J17/J16-1 -> -0.0098211943 | M17: 1647.05 | N17: =M17/M16-1 -> 0.018930372 | P17: 6410.95 | Q17: =P17/P16-1 -> 0.048551708 | S17: 45571 | T17: 24964.25 | U17: =T17/T16-1 -> -0.0020128245
B18: 45578 | D18: 4058.35 | E18: =D18/D17-1 -> -0.0063025056 | G18: 1851.48 | H18: =G18/G17-1 -> 0.0098118888 | J18: 274.33 | K18: =J18/J17-1 -> 0.038538709 | M18: 1687.9 | N18: =M18/M17-1 -> 0.024801919 | P18: 5991.7 | Q18: =P18/P17-1 -> -0.065395924 | S18: 45578 | T18: 24854.05 | U18: =T18/T17-1 -> -0.0044143125
B19: 45585 | D19: 3993.88 | E19: =D19/D18-1 -> -0.015885766 | G19: 1846.15 | H19: =G19/G18-1 -> -0.0028787781 | J19: 271.73 | K19: =J19/J18-1 -> -0.0094776364 | M19: 1716.45 | N19: =M19/M18-1 -> 0.016914509 | P19: 5903.2 | Q19: =P19/P18-1 -> -0.014770432 | S19: 45585 | T19: 24180.8 | U19: =T19/T18-1 -> -0.027088141
B20: 45592 | D20: 3921.68 | E20: =D20/D19-1 -> -0.018077659 | G20: 1751.52 | H20: =G20/G19-1 -> -0.051258023 | J20: 275.67 | K20: =J20/J19-1 -> 0.014499687 | M20: 1603.65 | N20: =M20/M19-1 -> -0.065717032 | P20: 5731.6 | Q20: =P20/P19-1 -> -0.02906898 | S20: 45592 | T20: 24304.35 | U20: =T20/T19-1 -> 0.0051094257
B21: 45599 | D21: 4081.93 | E21: =D21/D20-1 -> 0.04086259 | G21: 1831.35 | H21: =G21/G20-1 -> 0.045577555 | J21: 284.5 | K21: =J21/J20-1 -> 0.032031052 | M21: 1681.35 | N21: =M21/M20-1 -> 0.048451969 | P21: 5926.95 | Q21: =P21/P20-1 -> 0.034082979 | S21: 45599 | T21: 24148.2 | U21: =T21/T20-1 -> -0.0064247758
B22: 45606 | D22: 4080.85 | E22: =D22/D21-1 -> -0.00026458073 | G22: 1852.73 | H22: =G22/G21-1 -> 0.011674448 | J22: 283.35 | K22: =J22/J21-1 -> -0.0040421793 | M22: 1687.5 | N22: =M22/M21-1 -> 0.003657775 | P22: 5994.65 | Q22: =P22/P21-1 -> 0.011422401 | S22: 45606 | T22: 23532.7 | U22: =T22/T21-1 -> -0.025488442
... B114: 46250 | D114: 2302 | E114: =D114/D113-1 -> -0.024989411 | G114: 1302.5 | H114: =G114/G113-1 -> -0.042279412 | J114: 180.79 | K114: =J114/J113-1 -> -0.017445652 | M114: 1584 | N114: =M114/M113-1 -> -0.02988731 | P114: 4487.8 | Q114: =P114/P113-1 -> -0.048186638 | S114: 46250 | T114: 24252 | U114: =T114/T113-1 -> -0.0046786506
D116: TCS Beta | E116: =C135 -> 0.88127552 | G116: HCL Tech Beta | H116: =C154 -> 0.81276296 | J116: Wipro Beta | K116: =C173 -> 0.744671 | M116: Tech Mahindra Beta | N116: =N135 -> 0.71337806 | P116: LTM Beta | Q116: =N154 -> 1.1723379
B118: SUMMARY OUTPUT (TCS) | M118: SUMMARY OUTPUT (Tech Mahindra)
B120: Regression Statistics | M120: Regression Statistics
B121: Multiple R | C121: 0.50947481 | M121: Multiple R | N121: 0.33992016
B122: R Square | C122: 0.25956458 | M122: R Square | N122: 0.11554571
B123: Adjusted R Square | C123: 0.25230541 | M123: Adjusted R Square | N123: 0.10687459
B124: Standard Error | C124: 0.027435145 | M124: Standard Error | N124: 0.036379372
B125: Observations | C125: 104 | M125: Observations | N125: 104
B127: ANOVA | M127: ANOVA
C128: df | D128: SS | E128: MS | F128: F | G128: Significance F | N128: df | O128: SS | P128: MS | Q128: F | R128: Significance F
B129: Regression | C129: 1 | D129: 0.02691367 | E129: 0.02691367 | F129: 35.756782 | G129: 3.327341e-08 | M129: Regression | N129: 1 | O129: 0.01763555 | P129: 0.01763555 | Q129: 13.32535 | R129: 0.00041500366
B130: Residual | C130: 102 | D130: 0.07677409 | E130: 0.00075268716 | M130: Residual | N130: 102 | O130: 0.13499279 | P130: 0.0013234587
B131: Total | C131: 103 | D131: 0.10368776 | M131: Total | N131: 103 | O131: 0.15262834
C133: Coefficients | D133: Standard Error | E133: t Stat | F133: P-value | G133: Lower 95% | H133: Upper 95% | I133: Lower 95.0% | J133: Upper 95.0% | N133: Coefficients | O133: Standard Error | P133: t Stat | Q133: P-value | R133: Lower 95% | S133: Upper 95% | T133: Lower 95.0% | U133: Upper 95.0%
B134: Intercept | C134: -0.005641835 | D134: 0.0026902504 | E134: -2.0971412 | F134: 0.038453588 | G134: -0.010977934 | H134: -0.00030573607 | I134: -0.010977934 | J134: -0.00030573607 | M134: Intercept | N134: 0.00069086661 | O134: 0.0035673084 | P134: 0.19366608 | Q134: 0.8468225 | R134: -0.0063848726 | S134: 0.0077666058 | T134: -0.0063848726 | U134: 0.0077666058
B135: X Variable 1 | C135: 0.88127552 | D135: 0.14737794 | E135: 5.9796975 | F135: 3.327341e-08 | G135: 0.58895206 | H135: 1.173599 | I135: 0.58895206 | J135: 1.173599 | M135: X Variable 1 | N135: 0.71337806 | O135: 0.19542514 | P135: 3.6503904 | Q135: 0.00041500366 | R135: 0.32575322 | S135: 1.1010029 | T135: 0.32575322 | U135: 1.1010029
B137: SUMMARY OUTPUT (HCL) | M137: SUMMARY OUTPUT (LTM)
B139: Regression Statistics | M139: Regression Statistics
B140: Multiple R | C140: 0.38928755 | M140: Multiple R | N140: 0.49530311
B141: R Square | C141: 0.1515448 | M141: R Square | N141: 0.24532517
B142: Adjusted R Square | C142: 0.14322661 | M142: Adjusted R Square | N142: 0.2379264
B143: Standard Error | C143: 0.035447247 | M143: Standard Error | N143: 0.03789975
B144: Observations | C144: 104 | M144: Observations | N144: 104
B146: ANOVA | M146: ANOVA
C147: df | D147: SS | E147: MS | F147: F | G147: Significance F | N147: df | O147: SS | P147: MS | Q147: F | R147: Significance F
B148: Regression | C148: 1 | D148: 0.022891662 | E148: 0.022891662 | F148: 18.218487 | G148: 4.4206919e-05 | M148: Regression | N148: 1 | O148: 0.047627206 | P148: 0.047627206 | Q148: 33.157549 | R148: 9.0246609e-08
B149: Residual | C149: 102 | D149: 0.12816375 | E149: 0.0012565074 | M149: Residual | N149: 102 | O149: 0.14651189 | P149: 0.001436391
B150: Total | C150: 103 | D150: 0.15105541 | M150: Total | N150: 103 | O150: 0.19413909
C152: Coefficients | D152: Standard Error | E152: t Stat | F152: P-value | G152: Lower 95% | H152: Upper 95% | I152: Lower 95.0% | J152: Upper 95.0% | N152: Coefficients | O152: Standard Error | P152: t Stat | Q152: P-value | R152: Lower 95% | S152: Upper 95% | T152: Lower 95.0% | U152: Upper 95.0%
B153: Intercept | C153: -0.0015107663 | D153: 0.0034759056 | E153: -0.43463963 | F153: 0.66474217 | G153: -0.0084052085 | H153: 0.0053836759 | I153: -0.0084052085 | J153: 0.0053836759 | M153: Intercept | N153: -0.0011791717 | O153: 0.0037163944 | P153: -0.31728917 | Q153: 0.75167276 | R153: -0.0085506223 | S153: 0.0061922789 | T153: -0.0085506223 | U153: 0.0061922789
B154: X Variable 1 | C154: 0.81276296 | D154: 0.19041789 | E154: 4.2683119 | F154: 4.4206919e-05 | G154: 0.43506997 | H154: 1.190456 | I154: 0.43506997 | J154: 1.190456 | M154: X Variable 1 | N154: 1.1723379 | O154: 0.20359241 | P154: 5.7582592 | Q154: 9.0246609e-08 | R154: 0.76851328 | S154: 1.5761624 | T154: 0.76851328 | U154: 1.5761624
B156: SUMMARY OUTPUT (Wipro)
B158: Regression Statistics
B159: Multiple R | C159: 0.375421
B160: R Square | C160: 0.14094093
B161: Adjusted R Square | C161: 0.13251878
B162: Standard Error | C162: 0.033886918
B163: Observations | C163: 104
B165: ANOVA
C166: df | D166: SS | E166: MS | F166: F | G166: Significance F
B167: Regression | C167: 1 | D167: 0.019216682 | E167: 0.019216682 | F167: 16.734559 | G167: 8.6036788e-05
B168: Residual | C168: 102 | D168: 0.11712896 | E168: 0.0011483232
B169: Total | C169: 103 | D169: 0.13634565
C171: Coefficients | D171: Standard Error | E171: t Stat | F171: P-value | G171: Lower 95% | H171: Upper 95% | I171: Lower 95.0% | J171: Upper 95.0%
B172: Intercept | C172: -0.0026437417 | D172: 0.0033229019 | E172: -0.79561234 | F172: 0.42810503 | G172: -0.0092347018 | H172: 0.0039472184 | I172: -0.0092347018 | J172: 0.0039472184
B173: X Variable 1 | C173: 0.744671 | D173: 0.18203601 | E173: 4.0907895 | F173: 8.6036788e-05 | G173: 0.38360344 | H173: 1.1057386 | I173: 0.38360344 | J173: 1.1057386

Sheet Beta - Comps
A1: ='Data Sheet'!B1&" - Beta (Comparable Companies)" -> INFOSYS LTD - Beta (Comparable Companies)
B7: S.No. | C7: Name | D7: CMP Rs. | E7: No. Eq. Shares Cr. | F7: Debt Rs.Cr. | G7: Cash End Rs.Cr. | H7: EV Rs.Cr. | I7: Sales Rs.Cr. | J7: NP 12M Rs.Cr. | K7: EBIT 12M Rs.Cr. | L7: Dep 12M Rs.Cr.
B8: 1 | C8: TCS | D8: 2302 | E8: 361.81 | F8: 11283 | G8: 12908 | H8: 831258.75 | I8: 275859 | J8: 50055 | K8: 72951 | L8: 5438
B9: 2 | C9: Infosys | D9: 1121 | E9: 405.81 | F9: ='Data Sheet'!$K$59 -> 9176 | G9: ='Data Sheet'!$K$69 -> 22201 | H9: =D9*E9+F9-G9 -> 441888.01 | I9: 184582 | J9: Capital structure bridge aligned to Data Sheet / WACC | K9: 43002 | L9: 5007
B10: 3 | C10: HCL Technologies | D10: 1302.5 | E10: 271.37 | F10: 5215 | G10: 23425 | H10: 335244.88 | I10: 134374 | J10: 17434 | K10: 24721 | L10: 4301
B11: 4 | C11: Wipro | D11: 180.79 | E11: 990.45 | F11: 20291 | G11: 10555.5 | H11: 188799.63 | I11: 94968 | J11: 13285.3 | K11: 18988.1 | L11: 3029.6
B12: 5 | C12: Tech Mahindra | D12: 1584 | E12: 98.01 | F12: 2186.2 | G12: 5105.4 | H12: 152326.23 | I12: 59176.1 | J12: 5163 | K12: 7640.2 | L12: 1902.1
B13: 6 | C13: LTM | D13: 4487.8 | E13: 29.66 | F13: 2310 | G13: 2812.4 | H13: 132615.32 | I13: 44075 | J13: 5196.7 | K13: 7851.6 | L13: 1072.5
B14: 7 | C14: Persistent Systems | D14: 5667.5 | E14: 15.78 | F14: 477.45 | G14: 1218.25 | H14: 88664.01 | I14: 15718.1 | J14: 1923.22 | K14: 2652.69 | L14: 424.46
B15: Median: 72 Co. | C15: 213.15 | D15: 5.98 | E15: 37.48 | F15: 55.17 | G15: 1068.97 | H15: 288.96 | I15: 31.86 | J15: 45.55 | K15: 6.5
A17: Note: This comps-based (peer unlevered -> re-levered) beta IS the beta used in the WACC (see WACC!K35-K38). The own-stock 2-year weekly regression on 'Beta - Regression' has a low explanatory power (R^2 ~ 0.14), so it is kept for reference/transparency only and is not used in the WACC.

Sheet Rm
B6: Returns on Markets
B8: Year | C8: Annual | D8: Gross Return (1+r)
B9: 2000 | C9: -0.1465 | D9: =1+C9 -> 0.8535 | E9: Average Return | F9: =AVERAGE(C9:C34) -> 0.15149231
B10: 2001 | C10: -0.1618 | D10: =1+C10 -> 0.8382 | E10: Dividend Yield | F10: 0.013
B11: 2002 | C11: 0.0325 | D11: =1+C11 -> 1.0325 | E11: Total Market Return | F11: =F15+F10 -> 0.12950334
B12: 2003 | C12: 0.719 | D12: =1+C12 -> 1.719
B13: 2004 | C13: 0.1068 | D13: =1+C13 -> 1.1068 | E13: Arithmetic Mean Return (original) | F13: =F9 -> 0.15149231
B14: 2005 | C14: 0.3634 | D14: =1+C14 -> 1.3634
B15: 2006 | C15: 0.3983 | D15: =1+C15 -> 1.3983 | E15: Geometric Mean / CAGR Return | F15: =PRODUCT(D9:D34)^(1/COUNT(C9:C34))-1 -> 0.11650334
B16: 2007 | C16: 0.5477 | D16: =1+C16 -> 1.5477
B17: 2008 | C17: -0.5179 | D17: =1+C17 -> 0.4821
B18: 2009 | C18: 0.7576 | D18: =1+C18 -> 1.7576
B19: 2010 | C19: 0.1795 | D19: =1+C19 -> 1.1795
B20: 2011 | C20: -0.2462 | D20: =1+C20 -> 0.7538
B21: 2012 | C21: 0.277 | D21: =1+C21 -> 1.277
B22: 2013 | C22: 0.0676 | D22: =1+C22 -> 1.0676
B23: 2014 | C23: 0.3139 | D23: =1+C23 -> 1.3139
B24: 2015 | C24: -0.0406 | D24: =1+C24 -> 0.9594
B25: 2016 | C25: 0.0301 | D25: =1+C25 -> 1.0301
B26: 2017 | C26: 0.2865 | D26: =1+C26 -> 1.2865
B27: 2018 | C27: 0.0315 | D27: =1+C27 -> 1.0315
... B34: 2025 | C34: 0.1051 | D34: =1+C34 -> 1.1051
B47: Methodology: Nifty 50 annual PRICE returns for calendar years 2000–2025; geometric mean/CAGR is used as the base market price-return measure, then current Nifty 50 dividend yield is added to estimate total market return.
B48: Market return source: NSE Indices / Nifty 50 historical index data; annual price-return series cross-checked against published Nifty 50 annual return history.
B49: Dividend yield source: Nifty 50 dividend-yield data (1.30%, rounded; early-August 2026 observation).
B50: Total market return = geometric mean/CAGR price return (11.65%) + dividend yield (1.30%) = 12.95%; ERP = 12.95% − 6.77% risk-free rate = 6.18%.
B51: Risk-free source: India benchmark 10-year Government Security yield; 6.768% observed 6 Aug 2026 and rounded to 6.77% for the model (Moneycontrol market report; benchmark yield data cross-checked against G-Sec market sources).
B52: WACC valuation-date convention: inputs are point-in-time assumptions for the 22 Aug 2026 valuation date; the beta window is refreshed through 21 Aug 2026.

Sheet Intrinsic Growth
B6: Calculation of ROIC | G6: ='Raw FS'!H2 -> 44621 | H6: ='Raw FS'!I2 -> 44986 | I6: ='Raw FS'!J2 -> 45352 | J6: ='Raw FS'!K2 -> 45717 | K6: ='Raw FS'!L2 -> 46082
B8: Current Assets
B9: ='Raw FS'!B33 -> Trade receivables | G9: ='Raw FS'!H33 -> 22698 | H9: ='Raw FS'!I33 -> 25424 | I9: ='Raw FS'!J33 -> 30193 | J9: ='Raw FS'!K33 -> 31158 | K9: ='Raw FS'!L33 -> 35234
B10: ='Raw FS'!B35 -> Loans n Advances | G10: ='Raw FS'!H35 -> 2491 | H10: ='Raw FS'!I35 -> 3242 | I10: ='Raw FS'!J35 -> 10330 | J10: ='Raw FS'!K35 -> 6717 | K10: ='Raw FS'!L35 -> 6808
B11: ='Raw FS'!B36 -> Other asset items | G11: ='Raw FS'!H36 -> 27528 | H11: ='Raw FS'!I36 -> 34766 | I11: ='Raw FS'!J36 -> 28173 | J11: ='Raw FS'!K36 -> 30149 | K11: ='Raw FS'!L36 -> 33869
B12: Total Current Assets | G12: =SUM(G9:G11) -> 52717 | H12: =SUM(H9:H11) -> 63432 | I12: =SUM(I9:I11) -> 68696 | J12: =SUM(J9:J11) -> 68024 | K12: =SUM(K9:K11) -> 75911
B14: Current Liabilities
B15: ='Raw FS'!B10 -> Trade Payables | G15: ='Raw FS'!H10 -> 4134 | H15: ='Raw FS'!I10 -> 3865 | I15: ='Raw FS'!J10 -> 3956 | J15: ='Raw FS'!K10 -> 4164 | K15: ='Raw FS'!L10 -> 4744
B16: ='Raw FS'!B11 -> Advance from Customers | G16: ='Raw FS'!H11 -> 0 | H16: ='Raw FS'!I11 -> 0 | I16: ='Raw FS'!J11 -> 0 | J16: ='Raw FS'!K11 -> 0 | K16: ='Raw FS'!L11 -> 0
B17: ='Raw FS'!B12 -> Other liability items | G17: ='Raw FS'!H12 -> 31385 | H17: ='Raw FS'!I12 -> 36637 | I17: ='Raw FS'!J12 -> 35244 | J17: ='Raw FS'!K12 -> 39201 | K17: ='Raw FS'!L12 -> 47071
B18: Total Current Liabilities | G18: =SUM(G15:G17) -> 35519 | H18: =SUM(H15:H17) -> 40502 | I18: =SUM(I15:I17) -> 39200 | J18: =SUM(J15:J17) -> 43365 | K18: =SUM(K15:K17) -> 51815
A20: # | B20: Net Working Capital | G20: =G12-G18 -> 17198 | H20: =H12-H18 -> 22930 | I20: =I12-I18 -> 29496 | J20: =J12-J18 -> 24659 | K20: =K12-K18 -> 24096
B22: Non - Current Assets
B23: ='Raw FS'!B16 -> Land | G23: ='Raw FS'!H16 -> 2066 | H23: ='Raw FS'!I16 -> 2054 | I23: ='Raw FS'!J16 -> 2037 | J23: ='Raw FS'!K16 -> 2079 | K23: ='Raw FS'!L16 -> 1990
B24: ='Raw FS'!B17 -> Building | G24: ='Raw FS'!H17 -> 16760 | H24: ='Raw FS'!I17 -> 16903 | I24: ='Raw FS'!J17 -> 16515 | J24: ='Raw FS'!K17 -> 16376 | K24: ='Raw FS'!L17 -> 17193
B25: ='Raw FS'!B18 -> Plant Machinery | G25: ='Raw FS'!H18 -> 3210 | H25: ='Raw FS'!I18 -> 3302 | I25: ='Raw FS'!J18 -> 3428 | J25: ='Raw FS'!K18 -> 3461 | K25: ='Raw FS'!L18 -> 3714
B26: ='Raw FS'!B19 -> Equipments | G26: ='Raw FS'!H19 -> 1427 | H26: ='Raw FS'!I19 -> 1482 | I26: ='Raw FS'!J19 -> 1528 | J26: ='Raw FS'!K19 -> 1628 | K26: ='Raw FS'!L19 -> 1732
B27: ='Raw FS'!B20 -> Computers | G27: ='Raw FS'!H20 -> 9936 | H27: ='Raw FS'!I20 -> 11898 | I27: ='Raw FS'!J20 -> 12353 | J27: ='Raw FS'!K20 -> 12925 | K27: ='Raw FS'!L20 -> 13600
B28: ='Raw FS'!B21 -> Furniture n fittings | G28: ='Raw FS'!H21 -> 2278 | H28: ='Raw FS'!I21 -> 2303 | I28: ='Raw FS'!J21 -> 2326 | J28: ='Raw FS'!K21 -> 2340 | K28: ='Raw FS'!L21 -> 2438
B29: ='Raw FS'!B22 -> Vehicles | G29: ='Raw FS'!H22 -> 71 | H29: ='Raw FS'!I22 -> 60 | I29: ='Raw FS'!J22 -> 62 | J29: ='Raw FS'!K22 -> 72 | K29: ='Raw FS'!L22 -> 70
B30: ='Raw FS'!B23 -> Intangible Assets | G30: ='Raw FS'!H23 -> 6495 | H30: ='Raw FS'!I23 -> 7594 | I30: ='Raw FS'!J23 -> 7652 | J30: ='Raw FS'!K23 -> 10626 | K30: ='Raw FS'!L23 -> 12729
B31: ='Raw FS'!B24 -> Other fixed assets | G31: ='Raw FS'!H24 -> 2766 | H31: ='Raw FS'!I24 -> 3281 | I31: ='Raw FS'!J24 -> 3294 | J31: ='Raw FS'!K24 -> 5184 | K31: ='Raw FS'!L24 -> 6296
B32: Gross Block | G32: =SUM(G23:G31) -> 45009 | H32: =SUM(H23:H31) -> 48877 | I32: =SUM(I23:I31) -> 49195 | J32: =SUM(J23:J31) -> 54691 | K32: =SUM(K23:K31) -> 59762
B33: Accumulated Depreciation | G33: =-'Raw FS'!H26 -> -19209 | H33: =-'Raw FS'!I26 -> -19652 | I33: =-'Raw FS'!J26 -> -21573 | J33: =-'Raw FS'!K26 -> -23730 | K33: =-'Raw FS'!L26 -> -25992
A34: # | B34: Net Non Current Assets | G34: =SUM(G32:G33) -> 25800 | H34: =SUM(H32:H33) -> 29225 | I34: =SUM(I32:I33) -> 27622 | J34: =SUM(J32:J33) -> 30961 | K34: =SUM(K32:K33) -> 33770
A36: # | B36: Invested Capital | G36: =SUM(G34,G20) -> 42998 | H36: =SUM(H34,H20) -> 52155 | I36: =SUM(I34,I20) -> 57118 | J36: =SUM(J34,J20) -> 55620 | K36: =SUM(K34,K20) -> 57866
B37: EBIT | G37: =(HistoricalFS!H27+HistoricalFS!H21) -> 28015 | H37: =(HistoricalFS!I27+HistoricalFS!I21) -> 30905 | I37: =(HistoricalFS!J27+HistoricalFS!J21) -> 31747 | J37: =(HistoricalFS!K27+HistoricalFS!K21) -> 34424 | K37: =(HistoricalFS!L27+HistoricalFS!L21) -> 37378
A39: # | B39: ROIC | G39: =G37*(1-G48)/G36 -> 0.48754883 | H39: =H37*(1-H48)/H36 -> 0.44341312 | I39: =I37*(1-I48)/I36 -> 0.41591583 | J39: =J37*(1-J48)/J36 -> 0.46313339 | K39: =K37*(1-K48)/K36 -> 0.48335737
B42: Calculation of Reinvestment Rate | G42: =G6 -> 44621 | H42: =H6 -> 44986 | I42: =I6 -> 45352 | J42: =J6 -> 45717 | K42: =K6 -> 46082
B44: Net Capex (Capex - Depreciation) | G44: =-SUM('Cash Flow Data'!H12)-HistoricalFS!H24 -> -1315 | H44: =-SUM('Cash Flow Data'!I12)-HistoricalFS!I24 -> -1646 | I44: =-SUM('Cash Flow Data'!J12)-HistoricalFS!J24 -> -2477 | J44: =-SUM('Cash Flow Data'!K12)-HistoricalFS!K24 -> -2575 | K44: =-SUM('Cash Flow Data'!L12)-HistoricalFS!L24 -> -2175
B45: Change in Working Capital | H45: =H20-G20 -> 5732 | I45: =I20-H20 -> 6566 | J45: =J20-I20 -> -4837 | K45: =K20-J20 -> -563
B47: EBIT | G47: =G37 -> 28015 | H47: =H37 -> 30905 | I47: =I37 -> 31747 | J47: =J37 -> 34424 | K47: =K37 -> 37378
B48: Marginal Tax Rate | G48: =WACC!$E$28 -> 0.2517 | H48: =WACC!$E$28 -> 0.2517 | I48: =WACC!$E$28 -> 0.2517 | J48: =WACC!$E$28 -> 0.2517 | K48: =WACC!$E$28 -> 0.2517
B49: EBIT(1-T) | G49: =G47*(1-G48) -> 20963.624 | H49: =H47*(1-H48) -> 23126.211 | I49: =I47*(1-I48) -> 23756.28 | J49: =J47*(1-J48) -> 25759.479 | K49: =K47*(1-K48) -> 27969.957
B51: Reinvestment | H51: =SUM(H44:H45) -> 4086 | I51: =SUM(I44:I45) -> 4089 | J51: =SUM(J44:J45) -> -7412 | K51: =SUM(K44:K45) -> -2738
B53: Reinvestment Rate | H53: =H51/H49 -> 0.17668264 | I53: =I51/I49 -> 0.17212291 | J53: =J51/J49 -> -0.28773874 | K53: =K51/K49 -> -0.097890746
J55: 4 Year Average | K55: =AVERAGE(H53:K53) -> -0.0092059849
J56: 4 Year Median | K56: =MEDIAN(H53:K53) -> 0.037116081
B58: Calculation of Growth Rate | G58: =G42 -> 44621 | H58: =H42 -> 44986 | I58: =I42 -> 45352 | J58: =J42 -> 45717 | K58: =K42 -> 46082
B60: Reinvestment Rate | H60: =H53 -> 0.17668264 | I60: =I53 -> 0.17212291 | J60: =J53 -> -0.28773874 | K60: =K53 -> -0.097890746
B61: ROIC | H61: =H39 -> 0.44341312 | I61: =I39 -> 0.41591583 | J61: =J39 -> 0.46313339 | K61: =K39 -> 0.48335737
B63: Intrinsic Growth | H63: =H60*H61 -> 0.078343399 | I63: =I60*I61 -> 0.071588641 | J63: =J60*J61 -> -0.13326142 | K63: =K60*K61 -> -0.047316213
J65: 4 Year Average | K65: =AVERAGE(H63:K63) -> -0.0076613974
J66: 4 Year Median | K66: =MEDIAN(H63:K63) -> 0.012136214

Sheet DCF>
A1: ='Data Sheet'!B1&" - DCF Valuation" -> INFOSYS LTD - DCF Valuation
B6: Calculation of PV of FCFF | F6: =HistoricalFS!$L$3 -> 46112 | G6: =F6+365 -> 46477 | H6: =G6+365 -> 46842 | I6: =H6+365 -> 47207 | J6: =I6+365 -> 47572 | K6: =J6+365 -> 47937
B7: (All figures in ₹ Crore unless stated otherwise)
B8: EBIT | F8: ='Normalization Bridge'!B5 -> 37543 | G8: =Forecasting!$R$7 -> 38384.84 | H8: =Forecasting!$S$7 -> 39524.433 | I8: =Forecasting!$T$7 -> 40801.562 | J8: =Forecasting!$U$7 -> 42094.066 | K8: =Forecasting!$V$7 -> 43391.96
B10: Normalized Tax Rate | F10: ='Operating Drivers'!$B$38 -> 0.295 | G10: =F10 -> 0.295 | H10: =G10 -> 0.295 | I10: =H10 -> 0.295 | J10: =I10 -> 0.295 | K10: =J10 -> 0.295
B12: EBIT(1-T) | F12: =F8*(1-F10) -> 26467.815 | G12: =G8*(1-G10) -> 27061.312 | H12: =H8*(1-H10) -> 27864.725 | I12: =I8*(1-I10) -> 28765.101 | J12: =J8*(1-J10) -> 29676.317 | K12: =K8*(1-K10) -> 30591.332
B14: Less: Reinvestment Rate | F14: 0 | G14: =Forecasting!$R$10 -> 0.054622247 | H14: =Forecasting!$S$10 -> 0.059037192 | I14: =Forecasting!$T$10 -> 0.063546568 | J14: =Forecasting!$U$10 -> 0.068260756 | K14: =Forecasting!$V$10 -> 0.075
B16: Free Cash Flow to Firm (FCFF) | F16: =F12*(1-F14) -> 26467.815 | G16: =G12*(1-G14) -> 25583.163 | H16: =H12*(1-H14) -> 26219.67 | I16: =I12*(1-I14) -> 26937.178 | J16: =J12*(1-J14) -> 27650.589 | K16: =K12*(1-K14) -> 28296.982
B18: Mid-Year Convention | G18: =Forecasting!$R$12 -> 0.5 | H18: =Forecasting!$S$12 -> 1.5 | I18: =Forecasting!$T$12 -> 2.5 | J18: =Forecasting!$U$12 -> 3.5 | K18: =Forecasting!$V$12 -> 4.5
B20: Discounting Factor | G20: =Forecasting!$R$14 -> 0.94663238 | H20: =Forecasting!$S$14 -> 0.84828945 | I20: =Forecasting!$T$14 -> 0.76016309 | J20: =Forecasting!$U$14 -> 0.68119192 | K20: =Forecasting!$V$14 -> 0.61042485
B22: PV of FCFF | G22: =Forecasting!$R$15 -> 24217.85 | H22: =Forecasting!$S$15 -> 22241.869 | I22: =Forecasting!$T$15 -> 20476.648 | J22: =Forecasting!$U$15 -> 18835.358 | K22: =Forecasting!$V$15 -> 17273.181
B24: FY27 Revenue Growth (Base Case) | F24: ='Operating Drivers'!$B$34 -> 0.024580011
B25: Terminal Growth | F25: ='Operating Drivers'!$B$44 -> 0.03
B26: WACC | F26: =WACC!L45 -> 0.11593086
B28: Calculation of Terminal Value | G28: Sensitivity Analysis
G29: Terminal g / WACC | H29: =$J$29-0.02 -> 0.095930862 | I29: =$J$29-0.01 -> 0.10593086 | J29: =$F$26 -> 0.11593086 | K29: =$J$29+0.01 -> 0.12593086 | L29: =$J$29+0.02 -> 0.13593086
B30: FCFF(N+1) | D30: =K16*(1+F25) -> 29145.891 | G30: 0.02 | H30: =(SUMPRODUCT($G$16:$K$16,1/(1+H$29)^$G$18:$K$18)+($K$16*(1+$G30)/(H$29-$G30))/(1+H$29)^($K$18)-$D$43)/$D$46 -> 917.3067 | I30: =(SUMPRODUCT($G$16:$K$16,1/(1+I$29)^$G$18:$K$18)+($K$16*(1+$G30)/(I$29-$G30))/(1+I$29)^($K$18)-$D$43)/$D$46 -> 817.55739 | J30: =(SUMPRODUCT($G$16:$K$16,1/(1+J$29)^$G$18:$K$18)+($K$16*(1+$G30)/(J$29-$G30))/(1+J$29)^($K$18)-$D$43)/$D$46 -> 738.5962 | K30: =(SUMPRODUCT($G$16:$K$16,1/(1+K$29)^$G$18:$K$18)+($K$16*(1+$G30)/(K$29-$G30))/(1+K$29)^($K$18)-$D$43)/$D$46 -> 674.5358 | L30: =(SUMPRODUCT($G$16:$K$16,1/(1+L$29)^$G$18:$K$18)+($K$16*(1+$G30)/(L$29-$G30))/(1+L$29)^($K$18)-$D$43)/$D$46 -> 621.52021
B31: WACC | D31: =F26 -> 0.11593086 | G31: 0.025 | H31: =(SUMPRODUCT($G$16:$K$16,1/(1+H$29)^$G$18:$K$18)+($K$16*(1+$G31)/(H$29-$G31))/(1+H$29)^($K$18)-$D$43)/$D$46 -> 964.28451 | I31: =(SUMPRODUCT($G$16:$K$16,1/(1+I$29)^$G$18:$K$18)+($K$16*(1+$G31)/(I$29-$G31))/(1+I$29)^($K$18)-$D$43)/$D$46 -> 852.80065 | J31: =(SUMPRODUCT($G$16:$K$16,1/(1+J$29)^$G$18:$K$18)+($K$16*(1+$G31)/(J$29-$G31))/(1+J$29)^($K$18)-$D$43)/$D$46 -> 765.82241 | K31: =(SUMPRODUCT($G$16:$K$16,1/(1+K$29)^$G$18:$K$18)+($K$16*(1+$G31)/(K$29-$G31))/(1+K$29)^($K$18)-$D$43)/$D$46 -> 696.06609 | L31: =(SUMPRODUCT($G$16:$K$16,1/(1+L$29)^$G$18:$K$18)+($K$16*(1+$G31)/(L$29-$G31))/(1+L$29)^($K$18)-$D$43)/$D$46 -> 638.8744
B32: Terminal Growth Rate | D32: =F25 -> 0.03 | G32: 0.03 | H32: =(SUMPRODUCT($G$16:$K$16,1/(1+H$29)^$G$18:$K$18)+($K$16*(1+$G32)/(H$29-$G32))/(1+H$29)^($K$18)-$D$43)/$D$46 -> 1018.3876 | I32: =(SUMPRODUCT($G$16:$K$16,1/(1+I$29)^$G$18:$K$18)+($K$16*(1+$G32)/(I$29-$G32))/(1+I$29)^($K$18)-$D$43)/$D$46 -> 892.68541 | J32: =(SUMPRODUCT($G$16:$K$16,1/(1+J$29)^$G$18:$K$18)+($K$16*(1+$G32)/(J$29-$G32))/(1+J$29)^($K$18)-$D$43)/$D$46 -> 796.21701 | K32: =(SUMPRODUCT($G$16:$K$16,1/(1+K$29)^$G$18:$K$18)+($K$16*(1+$G32)/(K$29-$G32))/(1+K$29)^($K$18)-$D$43)/$D$46 -> 719.84074 | L32: =(SUMPRODUCT($G$16:$K$16,1/(1+L$29)^$G$18:$K$18)+($K$16*(1+$G32)/(L$29-$G32))/(1+L$29)^($K$18)-$D$43)/$D$46 -> 657.86684
G33: 0.035 | H33: =(SUMPRODUCT($G$16:$K$16,1/(1+H$29)^$G$18:$K$18)+($K$16*(1+$G33)/(H$29-$G33))/(1+H$29)^($K$18)-$D$43)/$D$46 -> 1081.3702 | I33: =(SUMPRODUCT($G$16:$K$16,1/(1+I$29)^$G$18:$K$18)+($K$16*(1+$G33)/(I$29-$G33))/(1+I$29)^($K$18)-$D$43)/$D$46 -> 938.19322 | J33: =(SUMPRODUCT($G$16:$K$16,1/(1+J$29)^$G$18:$K$18)+($K$16*(1+$G33)/(J$29-$G33))/(1+J$29)^($K$18)-$D$43)/$D$46 -> 830.36723 | K33: =(SUMPRODUCT($G$16:$K$16,1/(1+K$29)^$G$18:$K$18)+($K$16*(1+$G33)/(K$29-$G33))/(1+K$29)^($K$18)-$D$43)/$D$46 -> 746.22996 | L33: =(SUMPRODUCT($G$16:$K$16,1/(1+L$29)^$G$18:$K$18)+($K$16*(1+$G33)/(L$29-$G33))/(1+L$29)^($K$18)-$D$43)/$D$46 -> 678.74101
B34: Terminal Value | D34: =D30/(D31-D32) -> 339178.39 | G34: 0.04 | H34: =(SUMPRODUCT($G$16:$K$16,1/(1+H$29)^$G$18:$K$18)+($K$16*(1+$G34)/(H$29-$G34))/(1+H$29)^($K$18)-$D$43)/$D$46 -> 1155.6135 | I34: =(SUMPRODUCT($G$16:$K$16,1/(1+I$29)^$G$18:$K$18)+($K$16*(1+$G34)/(I$29-$G34))/(1+I$29)^($K$18)-$D$43)/$D$46 -> 990.60337 | J34: =(SUMPRODUCT($G$16:$K$16,1/(1+J$29)^$G$18:$K$18)+($K$16*(1+$G34)/(J$29-$G34))/(1+J$29)^($K$18)-$D$43)/$D$46 -> 869.01499 | K34: =(SUMPRODUCT($G$16:$K$16,1/(1+K$29)^$G$18:$K$18)+($K$16*(1+$G34)/(K$29-$G34))/(1+K$29)^($K$18)-$D$43)/$D$46 -> 775.69018 | L34: =(SUMPRODUCT($G$16:$K$16,1/(1+L$29)^$G$18:$K$18)+($K$16*(1+$G34)/(L$29-$G34))/(1+L$29)^($K$18)-$D$43)/$D$46 -> 701.79114
B37: Calculation of Equity Value per Share
B39: PV of FCFF | D39: =SUM(G22:K22) -> 103044.91
B40: PV of Terminal Value | D40: =D34/(1+$F$26)^$K$18 -> 207042.92
B41: Value of Operating Assets | D41: =SUM(D39:D40) -> 310087.82
B43: Less: Net Debt (Total Debt incl. lease liabilities, less Cash; sourced consistently from the model debt/cash bridge) | D43: ='Data>'!I3 -> -13025
B45: Value of Equity | D45: =D41-D43 -> 323112.82
B46: No. of Shares | D46: ='Data Sheet'!B6 -> 405.81
B48: Equity Value per Share | D48: =D45/D46 -> 796.21701
B50: Share Price | D50: ='Data Sheet'!B8 -> 1121
B51: Premium / (Discount) to DCF Value | D51: =D50/D48-1 -> 0.40790763
B53: Cross-Checks & Assumption Reconciliation (Audit Addition)
B55: Historical Reinvestment Rate (4-Yr Avg, FY23-26) | F55: ='Intrinsic Growth'!K55 -> -0.0092059849
B56: Historical Reinvestment Rate (4-Yr Median) | F56: ='Intrinsic Growth'!K56 -> 0.037116081
B57: Latest ROIC (FY26) | F57: ='Intrinsic Growth'!K39 -> 0.48335737
B58: FY27 Implied Growth = Reinvestment Rate × Target ROIC | F58: ='Operating Drivers'!B37*'Operating Drivers'!B36 -> 0.024580011
B59: FY27 Revenue Growth Assumed in Model | F59: =F24 -> 0.024580011
B60: Terminal ROIC = Terminal Growth / Terminal Reinvestment | F60: ='Operating Drivers'!B45 -> 0.4
B61: Terminal Value Sanity Check: Implied Exit Multiple vs. Peer Trading Multiples
B63: Terminal Value (D34) | D63: =D34 -> 339178.39
B64: FY31 EBITDA proxy = FY31 Revenue × (EBIT Margin + FY26 D&A % Revenue) | D64: =Forecasting!V5*(Forecasting!V6+HistoricalFS!L25) -> 49000.857
B65: Implied Terminal EV/EBITDA (Terminal Value / FY31 EBITDA proxy) | D65: =D63/D64 -> 6.9218868
B66: Peer Group Median EV/EBITDA (from 'Comps Val' tab) | D66: ='Comps Val'!P28 -> 11.551562
B67: Terminal multiple interpretation (diagnostic only) | D67: =IF(D65<D66*0.75,"INFO: implied TV multiple "&TEXT(D65,"0.0x")&" below core-peer median "&TEXT(D66,"0.0x")&"; reflects conservative terminal economics, not an exit-multiple input.",IF(D65>D66*1.25,"INFO: implied TV multiple "&TEXT(D65,"0.0x")&" above core-peer median "&TEXT(D66,"0.0x")&"; review terminal economics.","INFO: implied TV multiple is within 25% of core-peer median; diagnostic only.")) -> INFO: implied TV multiple 6.9x below core-peer median 11.6x; reflects conservative terminal economics, not an exit-multiple input.
F68: Methodology note: D65 compares the FY31 (terminal-year) implied EV/EBITDA to the FY26 (current) peer-median EV/EBITDA (D66) -- i.e. it assumes today's peer multiple structure persists through the forecast horizon. This is the standard implied-exit-multiple reasonableness check, not a same-year comparison. If sector multiples compress (e.g. AI-driven fee-pool disintermediation across the peer set), this check would overstate the terminal value's plausibility even when it reads PASS.
B69: Professional-model note: Explicit-period forecast assumptions are analyst estimates linked from Operating Drivers. Terminal reinvestment is formula-driven as terminal growth / terminal ROIC. Historical intrinsic-growth outputs are used as cross-checks, not as automatic forecast inputs.

Sheet Integrated Operating Model
A1: Integrated Operating Model
A2: ₹ crore | B2: FY26A | C2: FY27E | D2: FY28E | E2: FY29E | F2: FY30E | G2: FY31E
A3: Revenue | B3: ='Segment Profitability'!B31 -> 178650 | C3: ='Segment Profitability'!C31 -> 183041.22 | D3: ='Segment Profitability'!D31 -> 187795.96 | E3: ='Segment Profitability'!E31 -> 192927.49 | F3: ='Segment Profitability'!F31 -> 198458.63 | G3: ='Segment Profitability'!G31 -> 204412.39
A4: Revenue Growth | C4: =C3/B3-1 -> 0.024580011 | D4: =D3/C3-1 -> 0.025976365 | E4: =E3/D3-1 -> 0.027325024 | F4: =F3/E3-1 -> 0.028669518 | G4: =G3/F3-1 -> 0.03
A5: Segment Operating Income | B5: ='Segment Profitability'!B32 -> 42445 | C5: ='Segment Profitability'!C32 -> 43407.331 | D5: ='Segment Profitability'!D32 -> 44677.39 | E5: ='Segment Profitability'!E32 -> 46095.324 | F5: ='Segment Profitability'!F32 -> 47539.598 | G5: ='Segment Profitability'!G32 -> 49000.857
A6: Implied Segment Operating Margin | B6: =B5/B3 -> 0.23758746 | C6: =C5/C3 -> 0.23714512 | D6: =D5/D3 -> 0.23790389 | E6: =E5/E3 -> 0.23892564 | F6: =F5/F3 -> 0.23954412 | G6: =G5/G3 -> 0.23971569
A7: Corporate / Unallocated Costs | B7: ='Segment Profitability'!B32-'Normalization Bridge'!B5 -> 4902 | C7: =C3*'Operating Drivers'!B41 -> 5022.4912 | D7: =D3*'Operating Drivers'!C41 -> 5152.9573 | E7: =E3*'Operating Drivers'!D41 -> 5293.762 | F7: =F3*'Operating Drivers'!E41 -> 5445.5316 | G7: =G3*'Operating Drivers'!F41 -> 5608.8975
A8: Consolidated EBIT | B8: =B5-B7 -> 37543 | C8: =C5-C7 -> 38384.84 | D8: =D5-D7 -> 39524.433 | E8: =E5-E7 -> 40801.562 | F8: =F5-F7 -> 42094.066 | G8: =G5-G7 -> 43391.96
A9: Consolidated EBIT Margin | B9: =B8/B3 -> 0.21014833 | C9: =C8/C3 -> 0.20970599 | D9: =D8/D3 -> 0.21046476 | E9: =E8/E3 -> 0.21148651 | F9: =F8/F3 -> 0.21210499 | G9: =G8/G3 -> 0.21227656
A10: Normalized Tax Rate | B10: 0.295 | C10: 0.295 | D10: 0.295 | E10: 0.295 | F10: 0.295 | G10: 0.295
A11: NOPAT | B11: =B8*(1-B10) -> 26467.815 | C11: =C8*(1-C10) -> 27061.312 | D11: =D8*(1-D10) -> 27864.725 | E11: =E8*(1-E10) -> 28765.101 | F11: =F8*(1-F10) -> 29676.317 | G11: =G8*(1-G10) -> 30591.332
A12: Target ROIC | B12: 0 | C12: ='Operating Drivers'!B36 -> 0.45 | D12: ='Operating Drivers'!C36 -> 0.44 | E12: ='Operating Drivers'!D36 -> 0.43 | F12: ='Operating Drivers'!E36 -> 0.42 | G12: ='Operating Drivers'!F36 -> 0.4
A13: Reinvestment Rate | B13: 0 | C13: ='Operating Drivers'!B37 -> 0.054622247 | D13: ='Operating Drivers'!C37 -> 0.059037192 | E13: ='Operating Drivers'!D37 -> 0.063546568 | F13: ='Operating Drivers'!E37 -> 0.068260756 | G13: ='Operating Drivers'!F37 -> 0.075
A14: Reinvestment | B14: 0 | C14: =C11*C13 -> 1478.1497 | D14: =D11*D13 -> 1645.0551 | E14: =E11*E13 -> 1827.9235 | F14: =F11*F13 -> 2025.7278 | G14: =G11*G13 -> 2294.3499
A15: FCFF | B15: =B11-B14 -> 26467.815 | C15: =C11-C14 -> 25583.163 | D15: =D11-D14 -> 26219.67 | E15: =E11-E14 -> 26937.178 | F15: =F11-F14 -> 27650.589 | G15: =G11-G14 -> 28296.982
A16: Base Scenario Revenue Growth | C16: ='Operating Drivers'!B34 -> 0.024580011 | D16: ='Operating Drivers'!C34 -> 0.025976365 | E16: ='Operating Drivers'!D34 -> 0.027325024 | F16: ='Operating Drivers'!E34 -> 0.028669518 | G16: ='Operating Drivers'!F34 -> 0.03
A17: Note | B17: FY27E-FY31E FCFF is bottom-up from segment revenue and segment operating income, less normalized unallocable/corporate costs. FY26 normalized unallocable costs are ₹4,902 crore (₹6,191 crore reported less ₹1,289 crore Labour Code provision). | C17: =C4-C15 -> -25583.138 | D17: =D4-D15 -> -26219.644 | E17: =E4-E15 -> -26937.151 | F17: =F4-F15 -> -27650.56 | G17: =G4-G15 -> -28296.952
A18: Scenario / Integrated Margin Difference | C18: =C7-C16 -> 5022.4666 | D18: =D7-D16 -> 5152.9313 | E18: =E7-E16 -> 5293.7346 | F18: =F7-F16 -> 5445.5029 | G18: =G7-G16 -> 5608.8675

Sheet DCF Integration
A1: DCF Integration — Phase 7
A2: ₹ crore except per-share | B2: FY26A | C2: FY27E | D2: FY28E | E2: FY29E | F2: FY30E | G2: FY31E
A3: Integrated FCFF | C3: ='Integrated Operating Model'!C15 -> 25583.163 | D3: ='Integrated Operating Model'!D15 -> 26219.67 | E3: ='Integrated Operating Model'!E15 -> 26937.178 | F3: ='Integrated Operating Model'!F15 -> 27650.589 | G3: ='Integrated Operating Model'!G15 -> 28296.982
A4: Discount Period | B4: 0 | C4: 0.5 | D4: 1.5 | E4: 2.5 | F4: 3.5 | G4: 4.5
A5: WACC | B5: =WACC!L45 -> 0.11593086 | C5: =WACC!L45 -> 0.11593086 | D5: =WACC!L45 -> 0.11593086 | E5: =WACC!L45 -> 0.11593086 | F5: =WACC!L45 -> 0.11593086 | G5: =WACC!L45 -> 0.11593086
A6: Discount Factor | B6: =1/(1+B5)^B4 -> 1 | C6: =1/(1+C5)^C4 -> 0.94663238 | D6: =1/(1+D5)^D4 -> 0.84828945 | E6: =1/(1+E5)^E4 -> 0.76016309 | F6: =1/(1+F5)^F4 -> 0.68119192 | G6: =1/(1+G5)^G4 -> 0.61042485
A7: PV of FCFF | C7: =C3*C6 -> 24217.85 | D7: =D3*D6 -> 22241.869 | E7: =E3*E6 -> 20476.648 | F7: =F3*F6 -> 18835.358 | G7: =G3*G6 -> 17273.181
A8: Terminal Growth | B8: ='Operating Drivers'!$B$44 -> 0.03 | C8: ='Operating Drivers'!$B$44 -> 0.03 | D8: ='Operating Drivers'!$B$44 -> 0.03 | E8: ='Operating Drivers'!$B$44 -> 0.03 | F8: ='Operating Drivers'!$B$44 -> 0.03 | G8: ='Operating Drivers'!$B$44 -> 0.03
A9: Terminal ROIC | B9: ='Operating Drivers'!$B$45 -> 0.4 | C9: ='Operating Drivers'!$B$45 -> 0.4 | D9: ='Operating Drivers'!$B$45 -> 0.4 | E9: ='Operating Drivers'!$B$45 -> 0.4 | F9: ='Operating Drivers'!$B$45 -> 0.4 | G9: ='Operating Drivers'!$B$45 -> 0.4
